Workbook

Sheet Reference Rates
A1: Government Rates & Contribution Reference — NCR (Metro Manila), 30-Employee Payroll
A2: Rates as in force as of October 26, 2026, for the Aug – Oct 2026 quarter. Yellow cells are inputs; every monthly Payroll Register pulls its rates from this sheet. Wage orders and contribution tables change periodically — re-verify against DOLE/SSS/PhilHealth/Pag-IBIG/BIR before each payroll run.
A4: NCR Minimum Wage — Wage Order No. NCR-28 (effective September 26, 2026)
A5: Classification | B5: Daily Rate (8 hrs) | C5: Hourly Rate
A6: Non-agriculture, >15 workers — NEW (from Sept 26, 2026) | B6: 755 | C6: =B6/8 -> 94.375
A7: Non-agriculture, >15 workers — PREVIOUS | B7: 695 | C7: =B7/8 -> 86.875
A8: NCR-28 effective date | B8: 46291
A9: With 30 employees the business has more than 15 workers, so the Non-agriculture tier applies to everyone (the ₱718 / ₱658 small-retail tier used in the earlier 5-employee file no longer applies). Confirm classification with DOLE-NCR.
A11: Minimum Wage by Month (used for all Minimum Wage Earners)
A12: Month | B12: Month start | C12: Days at old rate | D12: Blended daily rate | E12: Hourly rate
A13: August 2026 | B13: 46235 | C13: =MAX(0,MIN(DAY(EOMONTH(B13,0)),$B$8-B13)) -> 31 | D13: =($B$7*C13+$B$6*(DAY(EOMONTH(B13,0))-C13))/DAY(EOMONTH(B13,0)) -> 695 | E13: =D13/8 -> 86.875
A14: September 2026 | B14: 46266 | C14: =MAX(0,MIN(DAY(EOMONTH(B14,0)),$B$8-B14)) -> 25 | D14: =($B$7*C14+$B$6*(DAY(EOMONTH(B14,0))-C14))/DAY(EOMONTH(B14,0)) -> 705 | E14: =D14/8 -> 88.125
A15: October 2026 | B15: 46296 | C15: =MAX(0,MIN(DAY(EOMONTH(B15,0)),$B$8-B15)) -> 0 | D15: =($B$7*C15+$B$6*(DAY(EOMONTH(B15,0))-C15))/DAY(EOMONTH(B15,0)) -> 755 | E15: =D15/8 -> 94.375
A16: Blended daily rate = calendar-day weighted average of old and new minimum (September: 25 days at ₱695, 5 days at ₱755) — an approximation for monthly payroll. For exact compliance, pay actual days worked before Sept 26 at the old rate and from Sept 26 at the new rate.
A18: Allowances (company policy — placeholders, edit to your actual policy)
A19: Meal allowance per working day (all employees) | B19: 50
A20: Per-diem by department (per trip day) | B20: Rate
A21: Delivery – Luzon | B21: 500
A22: Delivery – Samar | B22: 900
A23: Allowances are treated as non-taxable and are NOT included in the SSS / PhilHealth / Pag-IBIG contribution base (meal allowance within de minimis limits; per diem as substantiated travel reimbursement, higher for the longer inter-island Samar runs via RORO). Confirm treatment with your accountant — amounts above de minimis limits can become taxable.
A25: SSS Contribution (2026) — RA 11199, in force since January 2025
A26: Total contribution rate | B26: 0.15
A27: Employee share | B27: 0.05
A28: Employer share | B28: 0.1
A29: Minimum Monthly Salary Credit (MSC) | B29: 5000
A30: Maximum Monthly Salary Credit (MSC) | B30: 35000
A31: EC tier threshold (MSC) | B31: 15000
A32: EC — below threshold | B32: 10
A33: EC — at/above threshold | B33: 30
A35: PhilHealth Premium (2026) — RA 11223
A36: Total premium rate | B36: 0.05
A37: Employee share | B37: 0.025
A38: Employer share | B38: 0.025
A39: Premium floor (basic salary basis) | B39: 10000
A40: Premium ceiling (basic salary basis) | B40: 100000
A42: Pag-IBIG / HDMF Contribution (2026) — RA 9679
A43: Employee share (monthly comp. > ₱1,500) | B43: 0.02
A44: Employee share (monthly comp. ≤ ₱1,500) | B44: 0.01
A45: Employer share | B45: 0.02
A46: Monthly Fund Salary cap | B46: 10000
A48: BIR Monthly Withholding Tax Table (TRAIN Law, RR 11-2018 Annex E, in force since Jan 1, 2023)
A49: Monthly Taxable Income Bracket | B49: Base Tax | C49: Rate on Excess | D49: Over
A50: ₱0 – ₱20,833 | B50: 0 | C50: 0 | D50: 0
A51: ₱20,833 – ₱33,332 | B51: 0 | C51: 0.15 | D51: 20833
A52: ₱33,333 – ₱66,666 | B52: 1875 | C52: 0.2 | D52: 33333
A53: ₱66,667 – ₱166,666 | B53: 8541.8 | C53: 0.25 | D53: 66667
A54: ₱166,667 – ₱666,666 | B54: 33541.8 | C54: 0.3 | D54: 166667
A55: Over ₱666,667 | B55: 183541.8 | C55: 0.35 | D55: 666667
A57: Minimum Wage Earners (MWEs) are exempt from withholding tax on statutory basic pay, holiday pay, overtime and night differential (RA 9504 / TRAIN). Employees paid ABOVE the statutory minimum (drivers, supervisors, admin) are not MWEs, so their taxable income is subject to the table. SSS, PhilHealth and Pag-IBIG apply to everyone.
A59: Roster Note
A60: 30 employees: 12 Store, 8 Warehouse, 6 Delivery (3 Luzon routes, 3 Samar routes), 4 Admin / Supervisory. Names are left blank for you to fill in on the Aug 2026 sheet — they carry over automatically to Sep, Oct and the Summary. Hours, OT and trip days are illustrative; overwrite with actuals. 13th-month pay (due by Dec 24) is not part of this quarter.
A62: Sources
A63: • DOLE-NCR / RTWPB-NCR, Wage Order No. NCR-28 (effective Sept 26, 2026; ₱695 → ₱755 non-agriculture) — philstar.com/headlines/2026/09/27/2559226/ncr-wage-hike-takes-effect; emerhub.com/news/metro-manila-minimum-wage-rises-to-755-what-employers-need-to-update
A64: • Republic Act No. 11199 (Social Security Act of 2018); SSS schedule effective Jan 1, 2025 — sss.gov.ph
A65: • Republic Act No. 11223 (Universal Health Care Act); PhilHealth 5% premium — philhealth.gov.ph
A66: • Republic Act No. 9679 (HDMF Law of 2009); Pag-IBIG contribution table — pagibigfund.gov.ph
A67: • BIR Revised Withholding Tax Table, RR 11-2018 Annex E (TRAIN Law), in force since Jan 1, 2023 — bir.gov.ph
A68: • Meal allowance and per-diem amounts: assumptions by the preparer, not statutory figures.

Sheet Aug 2026
A1: Employee Payroll Register — August 2026
A2: Blue = input; black = formula; green = linked from another sheet. TYPE EMPLOYEE NAMES in the yellow Name cells on THIS sheet — they carry over to Sep, Oct and the Summary. Green-tinted rows = delivery drivers. Regular Hours default to 208 (26 days × 8 hrs). OT is the ordinary 125% premium. Per diem = Trip Days × the department rate on Reference Rates. Allowances are non-taxable and outside the SSS/PhilHealth/Pag-IBIG base. Printed pages cover columns A–W (employee-facing); employer-cost columns X–AC are on screen only.
A3: Pay Period: | B3: 2026-08-01 to 2026-08-31
A5: Employee ID | B5: Employee Name | C5: Department | D5: Position | E5: MWE (Y/N) | F5: Hourly Rate (₱) | G5: Regular Hours | H5: OT Hours (125%) | I5: Trip Days (per diem) | J5: Basic Pay | K5: OT Pay | L5: GROSS PAY | M5: Meal Allowance | N5: Per Diem | O5: SSS MSC | P5: SSS – EE | Q5: PhilHealth – EE | R5: Pag-IBIG – EE | S5: Total EE Contrib. | T5: Taxable Income | U5: Withholding Tax | V5: Total Deductions | W5: NET PAY | X5: SSS – ER | Y5: SSS – EC | Z5: PhilHealth – ER | AA5: Pag-IBIG – ER | AB5: Total ER Contrib. | AC5: TOTAL COST TO COMPANY
A6: EMP-001 | B6: Mikhail Dustin Elpedes | C6: Store | D6: Cashier | E6: Y | F6: ='Reference Rates'!$E$13 -> 86.875 | G6: 200 | H6: 0 | I6: 0 | J6: =F6*G6 -> 17375 | K6: =F6*1.25*H6 -> 0 | L6: =J6+K6 -> 17375 | M6: ='Reference Rates'!$B$19*G6/8 -> 1250 | N6: =I6*IFERROR(INDEX('Reference Rates'!$B$21:$B$22,MATCH(C6,'Reference Rates'!$A$21:$A$22,0)),0) -> 0 | O6: =MIN('Reference Rates'!$B$30,MAX('Reference Rates'!$B$29,MROUND(L6,500))) -> 17500 | P6: =O6*'Reference Rates'!$B$27 -> 875 | Q6: =MIN(MAX(L6,'Reference Rates'!$B$39),'Reference Rates'!$B$40)*'Reference Rates'!$B$37 -> 434.375 | R6: =MIN(L6,'Reference Rates'!$B$46)*IF(L6>1500,'Reference Rates'!$B$43,'Reference Rates'!$B$44) -> 200 | S6: =P6+Q6+R6 -> 1509.375 | T6: =IF(E6="Y",0,MAX(0,L6-S6)) -> 0 | U6: =IF(T6<='Reference Rates'!$D$51,0,IF(T6<='Reference Rates'!$D$52,'Reference Rates'!$B$51+(T6-'Reference Rates'!$D$51)*'Reference Rates'!$C$51,IF(T6<='Reference Rates'!$D$53,'Reference Rates'!$B$52+(T6-'Reference Rates'!$D$52)*'Reference Rates'!$C$52,IF(T6<='Reference Rates'!$D$54,'Reference Rates'!$B$53+(T6-'Reference Rates'!$D$53)*'Reference Rates'!$C$53,IF(T6<='Reference Rates'!$D$55,'Reference Rates'!$B$54+(T6-'Reference Rates'!$D$54)*'Reference Rates'!$C$54,'Reference Rates'!$B$55+(T6-'Reference Rates'!$D$55)*'Reference Rates'!$C$55))))) -> 0 | V6: =S6+U6 -> 1509.375 | W6: =L6+M6+N6-V6 -> 17115.625 | X6: =O6*'Reference Rates'!$B$28 -> 1750 | Y6: =IF(O6<'Reference Rates'!$B$31,'Reference Rates'!$B$32,'Reference Rates'!$B$33) -> 30 | Z6: =MIN(MAX(L6,'Reference Rates'!$B$39),'Reference Rates'!$B$40)*'Reference Rates'!$B$38 -> 434.375 | AA6: =MIN(L6,'Reference Rates'!$B$46)*'Reference Rates'!$B$45 -> 200 | AB6: =X6+Y6+Z6+AA6 -> 2414.375 | AC6: =L6+M6+N6+AB6 -> 21039.375
A7: EMP-002 | C7: Store | D7: Cashier | E7: Y | F7: ='Reference Rates'!$E$13 -> 86.875 | G7: 208 | H7: 6 | I7: 0 | J7: =F7*G7 -> 18070 | K7: =F7*1.25*H7 -> 651.5625 | L7: =J7+K7 -> 18721.562 | M7: ='Reference Rates'!$B$19*G7/8 -> 1300 | N7: =I7*IFERROR(INDEX('Reference Rates'!$B$21:$B$22,MATCH(C7,'Reference Rates'!$A$21:$A$22,0)),0) -> 0 | O7: =MIN('Reference Rates'!$B$30,MAX('Reference Rates'!$B$29,MROUND(L7,500))) -> 18500 | P7: =O7*'Reference Rates'!$B$27 -> 925 | Q7: =MIN(MAX(L7,'Reference Rates'!$B$39),'Reference Rates'!$B$40)*'Reference Rates'!$B$37 -> 468.03906 | R7: =MIN(L7,'Reference Rates'!$B$46)*IF(L7>1500,'Reference Rates'!$B$43,'Reference Rates'!$B$44) -> 200 | S7: =P7+Q7+R7 -> 1593.0391 | T7: =IF(E7="Y",0,MAX(0,L7-S7)) -> 0 | U7: =IF(T7<='Reference Rates'!$D$51,0,IF(T7<='Reference Rates'!$D$52,'Reference Rates'!$B$51+(T7-'Reference Rates'!$D$51)*'Reference Rates'!$C$51,IF(T7<='Reference Rates'!$D$53,'Reference Rates'!$B$52+(T7-'Reference Rates'!$D$52)*'Reference Rates'!$C$52,IF(T7<='Reference Rates'!$D$54,'Reference Rates'!$B$53+(T7-'Reference Rates'!$D$53)*'Reference Rates'!$C$53,IF(T7<='Reference Rates'!$D$55,'Reference Rates'!$B$54+(T7-'Reference Rates'!$D$54)*'Reference Rates'!$C$54,'Reference Rates'!$B$55+(T7-'Reference Rates'!$D$55)*'Reference Rates'!$C$55))))) -> 0 | V7: =S7+U7 -> 1593.0391 | W7: =L7+M7+N7-V7 -> 18428.523 | X7: =O7*'Reference Rates'!$B$28 -> 1850 | Y7: =IF(O7<'Reference Rates'!$B$31,'Reference Rates'!$B$32,'Reference Rates'!$B$33) -> 30 | Z7: =MIN(MAX(L7,'Reference Rates'!$B$39),'Reference Rates'!$B$40)*'Reference Rates'!$B$38 -> 468.03906 | AA7: =MIN(L7,'Reference Rates'!$B$46)*'Reference Rates'!$B$45 -> 200 | AB7: =X7+Y7+Z7+AA7 -> 2548.0391 | AC7: =L7+M7+N7+AB7 -> 22569.602
A8: EMP-003 | C8: Store | D8: Cashier | E8: Y | F8: ='Reference Rates'!$E$13 -> 86.875 | G8: 200 | H8: 0 | I8: 0 | J8: =F8*G8 -> 17375 | K8: =F8*1.25*H8 -> 0 | L8: =J8+K8 -> 17375 | M8: ='Reference Rates'!$B$19*G8/8 -> 1250 | N8: =I8*IFERROR(INDEX('Reference Rates'!$B$21:$B$22,MATCH(C8,'Reference Rates'!$A$21:$A$22,0)),0) -> 0 | O8: =MIN('Reference Rates'!$B$30,MAX('Reference Rates'!$B$29,MROUND(L8,500))) -> 17500 | P8: =O8*'Reference Rates'!$B$27 -> 875 | Q8: =MIN(MAX(L8,'Reference Rates'!$B$39),'Reference Rates'!$B$40)*'Reference Rates'!$B$37 -> 434.375 | R8: =MIN(L8,'Reference Rates'!$B$46)*IF(L8>1500,'Reference Rates'!$B$43,'Reference Rates'!$B$44) -> 200 | S8: =P8+Q8+R8 -> 1509.375 | T8: =IF(E8="Y",0,MAX(0,L8-S8)) -> 0 | U8: =IF(T8<='Reference Rates'!$D$51,0,IF(T8<='Reference Rates'!$D$52,'Reference Rates'!$B$51+(T8-'Reference Rates'!$D$51)*'Reference Rates'!$C$51,IF(T8<='Reference Rates'!$D$53,'Reference Rates'!$B$52+(T8-'Reference Rates'!$D$52)*'Reference Rates'!$C$52,IF(T8<='Reference Rates'!$D$54,'Reference Rates'!$B$53+(T8-'Reference Rates'!$D$53)*'Reference Rates'!$C$53,IF(T8<='Reference Rates'!$D$55,'Reference Rates'!$B$54+(T8-'Reference Rates'!$D$54)*'Reference Rates'!$C$54,'Reference Rates'!$B$55+(T8-'Reference Rates'!$D$55)*'Reference Rates'!$C$55))))) -> 0 | V8: =S8+U8 -> 1509.375 | W8: =L8+M8+N8-V8 -> 17115.625 | X8: =O8*'Reference Rates'!$B$28 -> 1750 | Y8: =IF(O8<'Reference Rates'!$B$31,'Reference Rates'!$B$32,'Reference Rates'!$B$33) -> 30 | Z8: =MIN(MAX(L8,'Reference Rates'!$B$39),'Reference Rates'!$B$40)*'Reference Rates'!$B$38 -> 434.375 | AA8: =MIN(L8,'Reference Rates'!$B$46)*'Reference Rates'!$B$45 -> 200 | AB8: =X8+Y8+Z8+AA8 -> 2414.375 | AC8: =L8+M8+N8+AB8 -> 21039.375
A9: EMP-004 | C9: Store | D9: Cashier | E9: Y | F9: ='Reference Rates'!$E$13 -> 86.875 | G9: 208 | H9: 0 | I9: 0 | J9: =F9*G9 -> 18070 | K9: =F9*1.25*H9 -> 0 | L9: =J9+K9 -> 18070 | M9: ='Reference Rates'!$B$19*G9/8 -> 1300 | N9: =I9*IFERROR(INDEX('Reference Rates'!$B$21:$B$22,MATCH(C9,'Reference Rates'!$A$21:$A$22,0)),0) -> 0 | O9: =MIN('Reference Rates'!$B$30,MAX('Reference Rates'!$B$29,MROUND(L9,500))) -> 18000 | P9: =O9*'Reference Rates'!$B$27 -> 900 | Q9: =MIN(MAX(L9,'Reference Rates'!$B$39),'Reference Rates'!$B$40)*'Reference Rates'!$B$37 -> 451.75 | R9: =MIN(L9,'Reference Rates'!$B$46)*IF(L9>1500,'Reference Rates'!$B$43,'Reference Rates'!$B$44) -> 200 | S9: =P9+Q9+R9 -> 1551.75 | T9: =IF(E9="Y",0,MAX(0,L9-S9)) -> 0 | U9: =IF(T9<='Reference Rates'!$D$51,0,IF(T9<='Reference Rates'!$D$52,'Reference Rates'!$B$51+(T9-'Reference Rates'!$D$51)*'Reference Rates'!$C$51,IF(T9<='Reference Rates'!$D$53,'Reference Rates'!$B$52+(T9-'Reference Rates'!$D$52)*'Reference Rates'!$C$52,IF(T9<='Reference Rates'!$D$54,'Reference Rates'!$B$53+(T9-'Reference Rates'!$D$53)*'Reference Rates'!$C$53,IF(T9<='Reference Rates'!$D$55,'Reference Rates'!$B$54+(T9-'Reference Rates'!$D$54)*'Reference Rates'!$C$54,'Reference Rates'!$B$55+(T9-'Reference Rates'!$D$55)*'Reference Rates'!$C$55))))) -> 0 | V9: =S9+U9 -> 1551.75 | W9: =L9+M9+N9-V9 -> 17818.25 | X9: =O9*'Reference Rates'!$B$28 -> 1800 | Y9: =IF(O9<'Reference Rates'!$B$31,'Reference Rates'!$B$32,'Reference Rates'!$B$33) -> 30 | Z9: =MIN(MAX(L9,'Reference Rates'!$B$39),'Reference Rates'!$B$40)*'Reference Rates'!$B$38 -> 451.75 | AA9: =MIN(L9,'Reference Rates'!$B$46)*'Reference Rates'!$B$45 -> 200 | AB9: =X9+Y9+Z9+AA9 -> 2481.75 | AC9: =L9+M9+N9+AB9 -> 21851.75
A10: EMP-005 | C10: Store | D10: Sales Clerk | E10: Y | F10: ='Reference Rates'!$E$13 -> 86.875 | G10: 208 | H10: 2 | I10: 0 | J10: =F10*G10 -> 18070 | K10: =F10*1.25*H10 -> 217.1875 | L10: =J10+K10 -> 18287.188 | M10: ='Reference Rates'!$B$19*G10/8 -> 1300 | N10: =I10*IFERROR(INDEX('Reference Rates'!$B$21:$B$22,MATCH(C10,'Reference Rates'!$A$21:$A$22,0)),0) -> 0 | O10: =MIN('Reference Rates'!$B$30,MAX('Reference Rates'!$B$29,MROUND(L10,500))) -> 18500 | P10: =O10*'Reference Rates'!$B$27 -> 925 | Q10: =MIN(MAX(L10,'Reference Rates'!$B$39),'Reference Rates'!$B$40)*'Reference Rates'!$B$37 -> 457.17969 | R10: =MIN(L10,'Reference Rates'!$B$46)*IF(L10>1500,'Reference Rates'!$B$43,'Reference Rates'!$B$44) -> 200 | S10: =P10+Q10+R10 -> 1582.1797 | T10: =IF(E10="Y",0,MAX(0,L10-S10)) -> 0 | U10: =IF(T10<='Reference Rates'!$D$51,0,IF(T10<='Reference Rates'!$D$52,'Reference Rates'!$B$51+(T10-'Reference Rates'!$D$51)*'Reference Rates'!$C$51,IF(T10<='Reference Rates'!$D$53,'Reference Rates'!$B$52+(T10-'Reference Rates'!$D$52)*'Reference Rates'!$C$52,IF(T10<='Reference Rates'!$D$54,'Reference Rates'!$B$53+(T10-'Reference Rates'!$D$53)*'Reference Rates'!$C$53,IF(T10<='Reference Rates'!$D$55,'Reference Rates'!$B$54+(T10-'Reference Rates'!$D$54)*'Reference Rates'!$C$54,'Reference Rates'!$B$55+(T10-'Reference Rates'!$D$55)*'Reference Rates'!$C$55))))) -> 0 | V10: =S10+U10 -> 1582.1797 | W10: =L10+M10+N10-V10 -> 18005.008 | X10: =O10*'Reference Rates'!$B$28 -> 1850 | Y10: =IF(O10<'Reference Rates'!$B$31,'Reference Rates'!$B$32,'Reference Rates'!$B$33) -> 30 | Z10: =MIN(MAX(L10,'Reference Rates'!$B$39),'Reference Rates'!$B$40)*'Reference Rates'!$B$38 -> 457.17969 | AA10: =MIN(L10,'Reference Rates'!$B$46)*'Reference Rates'!$B$45 -> 200 | AB10: =X10+Y10+Z10+AA10 -> 2537.1797 | AC10: =L10+M10+N10+AB10 -> 22124.367
A11: EMP-006 | C11: Store | D11: Sales Clerk | E11: Y | F11: ='Reference Rates'!$E$13 -> 86.875 | G11: 208 | H11: 0 | I11: 0 | J11: =F11*G11 -> 18070 | K11: =F11*1.25*H11 -> 0 | L11: =J11+K11 -> 18070 | M11: ='Reference Rates'!$B$19*G11/8 -> 1300 | N11: =I11*IFERROR(INDEX('Reference Rates'!$B$21:$B$22,MATCH(C11,'Reference Rates'!$A$21:$A$22,0)),0) -> 0 | O11: =MIN('Reference Rates'!$B$30,MAX('Reference Rates'!$B$29,MROUND(L11,500))) -> 18000 | P11: =O11*'Reference Rates'!$B$27 -> 900 | Q11: =MIN(MAX(L11,'Reference Rates'!$B$39),'Reference Rates'!$B$40)*'Reference Rates'!$B$37 -> 451.75 | R11: =MIN(L11,'Reference Rates'!$B$46)*IF(L11>1500,'Reference Rates'!$B$43,'Reference Rates'!$B$44) -> 200 | S11: =P11+Q11+R11 -> 1551.75 | T11: =IF(E11="Y",0,MAX(0,L11-S11)) -> 0 | U11: =IF(T11<='Reference Rates'!$D$51,0,IF(T11<='Reference Rates'!$D$52,'Reference Rates'!$B$51+(T11-'Reference Rates'!$D$51)*'Reference Rates'!$C$51,IF(T11<='Reference Rates'!$D$53,'Reference Rates'!$B$52+(T11-'Reference Rates'!$D$52)*'Reference Rates'!$C$52,IF(T11<='Reference Rates'!$D$54,'Reference Rates'!$B$53+(T11-'Reference Rates'!$D$53)*'Reference Rates'!$C$53,IF(T11<='Reference Rates'!$D$55,'Reference Rates'!$B$54+(T11-'Reference Rates'!$D$54)*'Reference Rates'!$C$54,'Reference Rates'!$B$55+(T11-'Reference Rates'!$D$55)*'Reference Rates'!$C$55))))) -> 0 | V11: =S11+U11 -> 1551.75 | W11: =L11+M11+N11-V11 -> 17818.25 | X11: =O11*'Reference Rates'!$B$28 -> 1800 | Y11: =IF(O11<'Reference Rates'!$B$31,'Reference Rates'!$B$32,'Reference Rates'!$B$33) -> 30 | Z11: =MIN(MAX(L11,'Reference Rates'!$B$39),'Reference Rates'!$B$40)*'Reference Rates'!$B$38 -> 451.75 | AA11: =MIN(L11,'Reference Rates'!$B$46)*'Reference Rates'!$B$45 -> 200 | AB11: =X11+Y11+Z11+AA11 -> 2481.75 | AC11: =L11+M11+N11+AB11 -> 21851.75
A12: EMP-007 | C12: Store | D12: Sales Clerk | E12: Y | F12: ='Reference Rates'!$E$13 -> 86.875 | G12: 208 | H12: 8 | I12: 0 | J12: =F12*G12 -> 18070 | K12: =F12*1.25*H12 -> 868.75 | L12: =J12+K12 -> 18938.75 | M12: ='Reference Rates'!$B$19*G12/8 -> 1300 | N12: =I12*IFERROR(INDEX('Reference Rates'!$B$21:$B$22,MATCH(C12,'Reference Rates'!$A$21:$A$22,0)),0) -> 0 | O12: =MIN('Reference Rates'!$B$30,MAX('Reference Rates'!$B$29,MROUND(L12,500))) -> 19000 | P12: =O12*'Reference Rates'!$B$27 -> 950 | Q12: =MIN(MAX(L12,'Reference Rates'!$B$39),'Reference Rates'!$B$40)*'Reference Rates'!$B$37 -> 473.46875 | R12: =MIN(L12,'Reference Rates'!$B$46)*IF(L12>1500,'Reference Rates'!$B$43,'Reference Rates'!$B$44) -> 200 | S12: =P12+Q12+R12 -> 1623.4688 | T12: =IF(E12="Y",0,MAX(0,L12-S12)) -> 0 | U12: =IF(T12<='Reference Rates'!$D$51,0,IF(T12<='Reference Rates'!$D$52,'Reference Rates'!$B$51+(T12-'Reference Rates'!$D$51)*'Reference Rates'!$C$51,IF(T12<='Reference Rates'!$D$53,'Reference Rates'!$B$52+(T12-'Reference Rates'!$D$52)*'Reference Rates'!$C$52,IF(T12<='Reference Rates'!$D$54,'Reference Rates'!$B$53+(T12-'Reference Rates'!$D$53)*'Reference Rates'!$C$53,IF(T12<='Reference Rates'!$D$55,'Reference Rates'!$B$54+(T12-'Reference Rates'!$D$54)*'Reference Rates'!$C$54,'Reference Rates'!$B$55+(T12-'Reference Rates'!$D$55)*'Reference Rates'!$C$55))))) -> 0 | V12: =S12+U12 -> 1623.4688 | W12: =L12+M12+N12-V12 -> 18615.281 | X12: =O12*'Reference Rates'!$B$28 -> 1900 | Y12: =IF(O12<'Reference Rates'!$B$31,'Reference Rates'!$B$32,'Reference Rates'!$B$33) -> 30 | Z12: =MIN(MAX(L12,'Reference Rates'!$B$39),'Reference Rates'!$B$40)*'Reference Rates'!$B$38 -> 473.46875 | AA12: =MIN(L12,'Reference Rates'!$B$46)*'Reference Rates'!$B$45 -> 200 | AB12: =X12+Y12+Z12+AA12 -> 2603.4688 | AC12: =L12+M12+N12+AB12 -> 22842.219
A13: EMP-008 | C13: Store | D13: Sales Clerk | E13: Y | F13: ='Reference Rates'!$E$13 -> 86.875 | G13: 208 | H13: 0 | I13: 0 | J13: =F13*G13 -> 18070 | K13: =F13*1.25*H13 -> 0 | L13: =J13+K13 -> 18070 | M13: ='Reference Rates'!$B$19*G13/8 -> 1300 | N13: =I13*IFERROR(INDEX('Reference Rates'!$B$21:$B$22,MATCH(C13,'Reference Rates'!$A$21:$A$22,0)),0) -> 0 | O13: =MIN('Reference Rates'!$B$30,MAX('Reference Rates'!$B$29,MROUND(L13,500))) -> 18000 | P13: =O13*'Reference Rates'!$B$27 -> 900 | Q13: =MIN(MAX(L13,'Reference Rates'!$B$39),'Reference Rates'!$B$40)*'Reference Rates'!$B$37 -> 451.75 | R13: =MIN(L13,'Reference Rates'!$B$46)*IF(L13>1500,'Reference Rates'!$B$43,'Reference Rates'!$B$44) -> 200 | S13: =P13+Q13+R13 -> 1551.75 | T13: =IF(E13="Y",0,MAX(0,L13-S13)) -> 0 | U13: =IF(T13<='Reference Rates'!$D$51,0,IF(T13<='Reference Rates'!$D$52,'Reference Rates'!$B$51+(T13-'Reference Rates'!$D$51)*'Reference Rates'!$C$51,IF(T13<='Reference Rates'!$D$53,'Reference Rates'!$B$52+(T13-'Reference Rates'!$D$52)*'Reference Rates'!$C$52,IF(T13<='Reference Rates'!$D$54,'Reference Rates'!$B$53+(T13-'Reference Rates'!$D$53)*'Reference Rates'!$C$53,IF(T13<='Reference Rates'!$D$55,'Reference Rates'!$B$54+(T13-'Reference Rates'!$D$54)*'Reference Rates'!$C$54,'Reference Rates'!$B$55+(T13-'Reference Rates'!$D$55)*'Reference Rates'!$C$55))))) -> 0 | V13: =S13+U13 -> 1551.75 | W13: =L13+M13+N13-V13 -> 17818.25 | X13: =O13*'Reference Rates'!$B$28 -> 1800 | Y13: =IF(O13<'Reference Rates'!$B$31,'Reference Rates'!$B$32,'Reference Rates'!$B$33) -> 30 | Z13: =MIN(MAX(L13,'Reference Rates'!$B$39),'Reference Rates'!$B$40)*'Reference Rates'!$B$38 -> 451.75 | AA13: =MIN(L13,'Reference Rates'!$B$46)*'Reference Rates'!$B$45 -> 200 | AB13: =X13+Y13+Z13+AA13 -> 2481.75 | AC13: =L13+M13+N13+AB13 -> 21851.75
A14: EMP-009 | C14: Store | D14: Sales Clerk | E14: Y | F14: ='Reference Rates'!$E$13 -> 86.875 | G14: 208 | H14: 0 | I14: 0 | J14: =F14*G14 -> 18070 | K14: =F14*1.25*H14 -> 0 | L14: =J14+K14 -> 18070 | M14: ='Reference Rates'!$B$19*G14/8 -> 1300 | N14: =I14*IFERROR(INDEX('Reference Rates'!$B$21:$B$22,MATCH(C14,'Reference Rates'!$A$21:$A$22,0)),0) -> 0 | O14: =MIN('Reference Rates'!$B$30,MAX('Reference Rates'!$B$29,MROUND(L14,500))) -> 18000 | P14: =O14*'Reference Rates'!$B$27 -> 900 | Q14: =MIN(MAX(L14,'Reference Rates'!$B$39),'Reference Rates'!$B$40)*'Reference Rates'!$B$37 -> 451.75 | R14: =MIN(L14,'Reference Rates'!$B$46)*IF(L14>1500,'Reference Rates'!$B$43,'Reference Rates'!$B$44) -> 200 | S14: =P14+Q14+R14 -> 1551.75 | T14: =IF(E14="Y",0,MAX(0,L14-S14)) -> 0 | U14: =IF(T14<='Reference Rates'!$D$51,0,IF(T14<='Reference Rates'!$D$52,'Reference Rates'!$B$51+(T14-'Reference Rates'!$D$51)*'Reference Rates'!$C$51,IF(T14<='Reference Rates'!$D$53,'Reference Rates'!$B$52+(T14-'Reference Rates'!$D$52)*'Reference Rates'!$C$52,IF(T14<='Reference Rates'!$D$54,'Reference Rates'!$B$53+(T14-'Reference Rates'!$D$53)*'Reference Rates'!$C$53,IF(T14<='Reference Rates'!$D$55,'Reference Rates'!$B$54+(T14-'Reference Rates'!$D$54)*'Reference Rates'!$C$54,'Reference Rates'!$B$55+(T14-'Reference Rates'!$D$55)*'Reference Rates'!$C$55))))) -> 0 | V14: =S14+U14 -> 1551.75 | W14: =L14+M14+N14-V14 -> 17818.25 | X14: =O14*'Reference Rates'!$B$28 -> 1800 | Y14: =IF(O14<'Reference Rates'!$B$31,'Reference Rates'!$B$32,'Reference Rates'!$B$33) -> 30 | Z14: =MIN(MAX(L14,'Reference Rates'!$B$39),'Reference Rates'!$B$40)*'Reference Rates'!$B$38 -> 451.75 | AA14: =MIN(L14,'Reference Rates'!$B$46)*'Reference Rates'!$B$45 -> 200 | AB14: =X14+Y14+Z14+AA14 -> 2481.75 | AC14: =L14+M14+N14+AB14 -> 21851.75
A15: EMP-010 | C15: Store | D15: Section Attendant (Frozen / Egg) | E15: Y | F15: ='Reference Rates'!$E$13 -> 86.875 | G15: 200 | H15: 8 | I15: 0 | J15: =F15*G15 -> 17375 | K15: =F15*1.25*H15 -> 868.75 | L15: =J15+K15 -> 18243.75 | M15: ='Reference Rates'!$B$19*G15/8 -> 1250 | N15: =I15*IFERROR(INDEX('Reference Rates'!$B$21:$B$22,MATCH(C15,'Reference Rates'!$A$21:$A$22,0)),0) -> 0 | O15: =MIN('Reference Rates'!$B$30,MAX('Reference Rates'!$B$29,MROUND(L15,500))) -> 18000 | P15: =O15*'Reference Rates'!$B$27 -> 900 | Q15: =MIN(MAX(L15,'Reference Rates'!$B$39),'Reference Rates'!$B$40)*'Reference Rates'!$B$37 -> 456.09375 | R15: =MIN(L15,'Reference Rates'!$B$46)*IF(L15>1500,'Reference Rates'!$B$43,'Reference Rates'!$B$44) -> 200 | S15: =P15+Q15+R15 -> 1556.0938 | T15: =IF(E15="Y",0,MAX(0,L15-S15)) -> 0 | U15: =IF(T15<='Reference Rates'!$D$51,0,IF(T15<='Reference Rates'!$D$52,'Reference Rates'!$B$51+(T15-'Reference Rates'!$D$51)*'Reference Rates'!$C$51,IF(T15<='Reference Rates'!$D$53,'Reference Rates'!$B$52+(T15-'Reference Rates'!$D$52)*'Reference Rates'!$C$52,IF(T15<='Reference Rates'!$D$54,'Reference Rates'!$B$53+(T15-'Reference Rates'!$D$53)*'Reference Rates'!$C$53,IF(T15<='Reference Rates'!$D$55,'Reference Rates'!$B$54+(T15-'Reference Rates'!$D$54)*'Reference Rates'!$C$54,'Reference Rates'!$B$55+(T15-'Reference Rates'!$D$55)*'Reference Rates'!$C$55))))) -> 0 | V15: =S15+U15 -> 1556.0938 | W15: =L15+M15+N15-V15 -> 17937.656 | X15: =O15*'Reference Rates'!$B$28 -> 1800 | Y15: =IF(O15<'Reference Rates'!$B$31,'Reference Rates'!$B$32,'Reference Rates'!$B$33) -> 30 | Z15: =MIN(MAX(L15,'Reference Rates'!$B$39),'Reference Rates'!$B$40)*'Reference Rates'!$B$38 -> 456.09375 | AA15: =MIN(L15,'Reference Rates'!$B$46)*'Reference Rates'!$B$45 -> 200 | AB15: =X15+Y15+Z15+AA15 -> 2486.0938 | AC15: =L15+M15+N15+AB15 -> 21979.844
A16: EMP-011 | C16: Store | D16: Section Attendant (Frozen / Egg) | E16: Y | F16: ='Reference Rates'!$E$13 -> 86.875 | G16: 208 | H16: 0 | I16: 0 | J16: =F16*G16 -> 18070 | K16: =F16*1.25*H16 -> 0 | L16: =J16+K16 -> 18070 | M16: ='Reference Rates'!$B$19*G16/8 -> 1300 | N16: =I16*IFERROR(INDEX('Reference Rates'!$B$21:$B$22,MATCH(C16,'Reference Rates'!$A$21:$A$22,0)),0) -> 0 | O16: =MIN('Reference Rates'!$B$30,MAX('Reference Rates'!$B$29,MROUND(L16,500))) -> 18000 | P16: =O16*'Reference Rates'!$B$27 -> 900 | Q16: =MIN(MAX(L16,'Reference Rates'!$B$39),'Reference Rates'!$B$40)*'Reference Rates'!$B$37 -> 451.75 | R16: =MIN(L16,'Reference Rates'!$B$46)*IF(L16>1500,'Reference Rates'!$B$43,'Reference Rates'!$B$44) -> 200 | S16: =P16+Q16+R16 -> 1551.75 | T16: =IF(E16="Y",0,MAX(0,L16-S16)) -> 0 | U16: =IF(T16<='Reference Rates'!$D$51,0,IF(T16<='Reference Rates'!$D$52,'Reference Rates'!$B$51+(T16-'Reference Rates'!$D$51)*'Reference Rates'!$C$51,IF(T16<='Reference Rates'!$D$53,'Reference Rates'!$B$52+(T16-'Reference Rates'!$D$52)*'Reference Rates'!$C$52,IF(T16<='Reference Rates'!$D$54,'Reference Rates'!$B$53+(T16-'Reference Rates'!$D$53)*'Reference Rates'!$C$53,IF(T16<='Reference Rates'!$D$55,'Reference Rates'!$B$54+(T16-'Reference Rates'!$D$54)*'Reference Rates'!$C$54,'Reference Rates'!$B$55+(T16-'Reference Rates'!$D$55)*'Reference Rates'!$C$55))))) -> 0 | V16: =S16+U16 -> 1551.75 | W16: =L16+M16+N16-V16 -> 17818.25 | X16: =O16*'Reference Rates'!$B$28 -> 1800 | Y16: =IF(O16<'Reference Rates'!$B$31,'Reference Rates'!$B$32,'Reference Rates'!$B$33) -> 30 | Z16: =MIN(MAX(L16,'Reference Rates'!$B$39),'Reference Rates'!$B$40)*'Reference Rates'!$B$38 -> 451.75 | AA16: =MIN(L16,'Reference Rates'!$B$46)*'Reference Rates'!$B$45 -> 200 | AB16: =X16+Y16+Z16+AA16 -> 2481.75 | AC16: =L16+M16+N16+AB16 -> 21851.75
A17: EMP-012 | C17: Store | D17: Section Attendant (Frozen / Egg) | E17: Y | F17: ='Reference Rates'!$E$13 -> 86.875 | G17: 208 | H17: 0 | I17: 0 | J17: =F17*G17 -> 18070 | K17: =F17*1.25*H17 -> 0 | L17: =J17+K17 -> 18070 | M17: ='Reference Rates'!$B$19*G17/8 -> 1300 | N17: =I17*IFERROR(INDEX('Reference Rates'!$B$21:$B$22,MATCH(C17,'Reference Rates'!$A$21:$A$22,0)),0) -> 0 | O17: =MIN('Reference Rates'!$B$30,MAX('Reference Rates'!$B$29,MROUND(L17,500))) -> 18000 | P17: =O17*'Reference Rates'!$B$27 -> 900 | Q17: =MIN(MAX(L17,'Reference Rates'!$B$39),'Reference Rates'!$B$40)*'Reference Rates'!$B$37 -> 451.75 | R17: =MIN(L17,'Reference Rates'!$B$46)*IF(L17>1500,'Reference Rates'!$B$43,'Reference Rates'!$B$44) -> 200 | S17: =P17+Q17+R17 -> 1551.75 | T17: =IF(E17="Y",0,MAX(0,L17-S17)) -> 0 | U17: =IF(T17<='Reference Rates'!$D$51,0,IF(T17<='Reference Rates'!$D$52,'Reference Rates'!$B$51+(T17-'Reference Rates'!$D$51)*'Reference Rates'!$C$51,IF(T17<='Reference Rates'!$D$53,'Reference Rates'!$B$52+(T17-'Reference Rates'!$D$52)*'Reference Rates'!$C$52,IF(T17<='Reference Rates'!$D$54,'Reference Rates'!$B$53+(T17-'Reference Rates'!$D$53)*'Reference Rates'!$C$53,IF(T17<='Reference Rates'!$D$55,'Reference Rates'!$B$54+(T17-'Reference Rates'!$D$54)*'Reference Rates'!$C$54,'Reference Rates'!$B$55+(T17-'Reference Rates'!$D$55)*'Reference Rates'!$C$55))))) -> 0 | V17: =S17+U17 -> 1551.75 | W17: =L17+M17+N17-V17 -> 17818.25 | X17: =O17*'Reference Rates'!$B$28 -> 1800 | Y17: =IF(O17<'Reference Rates'!$B$31,'Reference Rates'!$B$32,'Reference Rates'!$B$33) -> 30 | Z17: =MIN(MAX(L17,'Reference Rates'!$B$39),'Reference Rates'!$B$40)*'Reference Rates'!$B$38 -> 451.75 | AA17: =MIN(L17,'Reference Rates'!$B$46)*'Reference Rates'!$B$45 -> 200 | AB17: =X17+Y17+Z17+AA17 -> 2481.75 | AC17: =L17+M17+N17+AB17 -> 21851.75
A18: EMP-013 | B18: John Carlo Escartin | C18: Warehouse | D18: Stock Clerk | E18: Y | F18: ='Reference Rates'!$E$13 -> 86.875 | G18: 208 | H18: 11 | I18: 0 | J18: =F18*G18 -> 18070 | K18: =F18*1.25*H18 -> 1194.5312 | L18: =J18+K18 -> 19264.531 | M18: ='Reference Rates'!$B$19*G18/8 -> 1300 | N18: =I18*IFERROR(INDEX('Reference Rates'!$B$21:$B$22,MATCH(C18,'Reference Rates'!$A$21:$A$22,0)),0) -> 0 | O18: =MIN('Reference Rates'!$B$30,MAX('Reference Rates'!$B$29,MROUND(L18,500))) -> 19500 | P18: =O18*'Reference Rates'!$B$27 -> 975 | Q18: =MIN(MAX(L18,'Reference Rates'!$B$39),'Reference Rates'!$B$40)*'Reference Rates'!$B$37 -> 481.61328 | R18: =MIN(L18,'Reference Rates'!$B$46)*IF(L18>1500,'Reference Rates'!$B$43,'Reference Rates'!$B$44) -> 200 | S18: =P18+Q18+R18 -> 1656.6133 | T18: =IF(E18="Y",0,MAX(0,L18-S18)) -> 0 | U18: =IF(T18<='Reference Rates'!$D$51,0,IF(T18<='Reference Rates'!$D$52,'Reference Rates'!$B$51+(T18-'Reference Rates'!$D$51)*'Reference Rates'!$C$51,IF(T18<='Reference Rates'!$D$53,'Reference Rates'!$B$52+(T18-'Reference Rates'!$D$52)*'Reference Rates'!$C$52,IF(T18<='Reference Rates'!$D$54,'Reference Rates'!$B$53+(T18-'Reference Rates'!$D$53)*'Reference Rates'!$C$53,IF(T18<='Reference Rates'!$D$55,'Reference Rates'!$B$54+(T18-'Reference Rates'!$D$54)*'Reference Rates'!$C$54,'Reference Rates'!$B$55+(T18-'Reference Rates'!$D$55)*'Reference Rates'!$C$55))))) -> 0 | V18: =S18+U18 -> 1656.6133 | W18: =L18+M18+N18-V18 -> 18907.918 | X18: =O18*'Reference Rates'!$B$28 -> 1950 | Y18: =IF(O18<'Reference Rates'!$B$31,'Reference Rates'!$B$32,'Reference Rates'!$B$33) -> 30 | Z18: =MIN(MAX(L18,'Reference Rates'!$B$39),'Reference Rates'!$B$40)*'Reference Rates'!$B$38 -> 481.61328 | AA18: =MIN(L18,'Reference Rates'!$B$46)*'Reference Rates'!$B$45 -> 200 | AB18: =X18+Y18+Z18+AA18 -> 2661.6133 | AC18: =L18+M18+N18+AB18 -> 23226.145
A19: EMP-014 | C19: Warehouse | D19: Stock Clerk | E19: Y | F19: ='Reference Rates'!$E$13 -> 86.875 | G19: 208 | H19: 4 | I19: 0 | J19: =F19*G19 -> 18070 | K19: =F19*1.25*H19 -> 434.375 | L19: =J19+K19 -> 18504.375 | M19: ='Reference Rates'!$B$19*G19/8 -> 1300 | N19: =I19*IFERROR(INDEX('Reference Rates'!$B$21:$B$22,MATCH(C19,'Reference Rates'!$A$21:$A$22,0)),0) -> 0 | O19: =MIN('Reference Rates'!$B$30,MAX('Reference Rates'!$B$29,MROUND(L19,500))) -> 18500 | P19: =O19*'Reference Rates'!$B$27 -> 925 | Q19: =MIN(MAX(L19,'Reference Rates'!$B$39),'Reference Rates'!$B$40)*'Reference Rates'!$B$37 -> 462.60938 | R19: =MIN(L19,'Reference Rates'!$B$46)*IF(L19>1500,'Reference Rates'!$B$43,'Reference Rates'!$B$44) -> 200 | S19: =P19+Q19+R19 -> 1587.6094 | T19: =IF(E19="Y",0,MAX(0,L19-S19)) -> 0 | U19: =IF(T19<='Reference Rates'!$D$51,0,IF(T19<='Reference Rates'!$D$52,'Reference Rates'!$B$51+(T19-'Reference Rates'!$D$51)*'Reference Rates'!$C$51,IF(T19<='Reference Rates'!$D$53,'Reference Rates'!$B$52+(T19-'Reference Rates'!$D$52)*'Reference Rates'!$C$52,IF(T19<='Reference Rates'!$D$54,'Reference Rates'!$B$53+(T19-'Reference Rates'!$D$53)*'Reference Rates'!$C$53,IF(T19<='Reference Rates'!$D$55,'Reference Rates'!$B$54+(T19-'Reference Rates'!$D$54)*'Reference Rates'!$C$54,'Reference Rates'!$B$55+(T19-'Reference Rates'!$D$55)*'Reference Rates'!$C$55))))) -> 0 | V19: =S19+U19 -> 1587.6094 | W19: =L19+M19+N19-V19 -> 18216.766 | X19: =O19*'Reference Rates'!$B$28 -> 1850 | Y19: =IF(O19<'Reference Rates'!$B$31,'Reference Rates'!$B$32,'Reference Rates'!$B$33) -> 30 | Z19: =MIN(MAX(L19,'Reference Rates'!$B$39),'Reference Rates'!$B$40)*'Reference Rates'!$B$38 -> 462.60938 | AA19: =MIN(L19,'Reference Rates'!$B$46)*'Reference Rates'!$B$45 -> 200 | AB19: =X19+Y19+Z19+AA19 -> 2542.6094 | AC19: =L19+M19+N19+AB19 -> 22346.984
A20: EMP-015 | C20: Warehouse | D20: Stock Clerk | E20: Y | F20: ='Reference Rates'!$E$13 -> 86.875 | G20: 208 | H20: 6 | I20: 0 | J20: =F20*G20 -> 18070 | K20: =F20*1.25*H20 -> 651.5625 | L20: =J20+K20 -> 18721.562 | M20: ='Reference Rates'!$B$19*G20/8 -> 1300 | N20: =I20*IFERROR(INDEX('Reference Rates'!$B$21:$B$22,MATCH(C20,'Reference Rates'!$A$21:$A$22,0)),0) -> 0 | O20: =MIN('Reference Rates'!$B$30,MAX('Reference Rates'!$B$29,MROUND(L20,500))) -> 18500 | P20: =O20*'Reference Rates'!$B$27 -> 925 | Q20: =MIN(MAX(L20,'Reference Rates'!$B$39),'Reference Rates'!$B$40)*'Reference Rates'!$B$37 -> 468.03906 | R20: =MIN(L20,'Reference Rates'!$B$46)*IF(L20>1500,'Reference Rates'!$B$43,'Reference Rates'!$B$44) -> 200 | S20: =P20+Q20+R20 -> 1593.0391 | T20: =IF(E20="Y",0,MAX(0,L20-S20)) -> 0 | U20: =IF(T20<='Reference Rates'!$D$51,0,IF(T20<='Reference Rates'!$D$52,'Reference Rates'!$B$51+(T20-'Reference Rates'!$D$51)*'Reference Rates'!$C$51,IF(T20<='Reference Rates'!$D$53,'Reference Rates'!$B$52+(T20-'Reference Rates'!$D$52)*'Reference Rates'!$C$52,IF(T20<='Reference Rates'!$D$54,'Reference Rates'!$B$53+(T20-'Reference Rates'!$D$53)*'Reference Rates'!$C$53,IF(T20<='Reference Rates'!$D$55,'Reference Rates'!$B$54+(T20-'Reference Rates'!$D$54)*'Reference Rates'!$C$54,'Reference Rates'!$B$55+(T20-'Reference Rates'!$D$55)*'Reference Rates'!$C$55))))) -> 0 | V20: =S20+U20 -> 1593.0391 | W20: =L20+M20+N20-V20 -> 18428.523 | X20: =O20*'Reference Rates'!$B$28 -> 1850 | Y20: =IF(O20<'Reference Rates'!$B$31,'Reference Rates'!$B$32,'Reference Rates'!$B$33) -> 30 | Z20: =MIN(MAX(L20,'Reference Rates'!$B$39),'Reference Rates'!$B$40)*'Reference Rates'!$B$38 -> 468.03906 | AA20: =MIN(L20,'Reference Rates'!$B$46)*'Reference Rates'!$B$45 -> 200 | AB20: =X20+Y20+Z20+AA20 -> 2548.0391 | AC20: =L20+M20+N20+AB20 -> 22569.602
A21: EMP-016 | C21: Warehouse | D21: Warehouse Helper / Loader | E21: Y | F21: ='Reference Rates'!$E$13 -> 86.875 | G21: 208 | H21: 0 | I21: 0 | J21: =F21*G21 -> 18070 | K21: =F21*1.25*H21 -> 0 | L21: =J21+K21 -> 18070 | M21: ='Reference Rates'!$B$19*G21/8 -> 1300 | N21: =I21*IFERROR(INDEX('Reference Rates'!$B$21:$B$22,MATCH(C21,'Reference Rates'!$A$21:$A$22,0)),0) -> 0 | O21: =MIN('Reference Rates'!$B$30,MAX('Reference Rates'!$B$29,MROUND(L21,500))) -> 18000 | P21: =O21*'Reference Rates'!$B$27 -> 900 | Q21: =MIN(MAX(L21,'Reference Rates'!$B$39),'Reference Rates'!$B$40)*'Reference Rates'!$B$37 -> 451.75 | R21: =MIN(L21,'Reference Rates'!$B$46)*IF(L21>1500,'Reference Rates'!$B$43,'Reference Rates'!$B$44) -> 200 | S21: =P21+Q21+R21 -> 1551.75 | T21: =IF(E21="Y",0,MAX(0,L21-S21)) -> 0 | U21: =IF(T21<='Reference Rates'!$D$51,0,IF(T21<='Reference Rates'!$D$52,'Reference Rates'!$B$51+(T21-'Reference Rates'!$D$51)*'Reference Rates'!$C$51,IF(T21<='Reference Rates'!$D$53,'Reference Rates'!$B$52+(T21-'Reference Rates'!$D$52)*'Reference Rates'!$C$52,IF(T21<='Reference Rates'!$D$54,'Reference Rates'!$B$53+(T21-'Reference Rates'!$D$53)*'Reference Rates'!$C$53,IF(T21<='Reference Rates'!$D$55,'Reference Rates'!$B$54+(T21-'Reference Rates'!$D$54)*'Reference Rates'!$C$54,'Reference Rates'!$B$55+(T21-'Reference Rates'!$D$55)*'Reference Rates'!$C$55))))) -> 0 | V21: =S21+U21 -> 1551.75 | W21: =L21+M21+N21-V21 -> 17818.25 | X21: =O21*'Reference Rates'!$B$28 -> 1800 | Y21: =IF(O21<'Reference Rates'!$B$31,'Reference Rates'!$B$32,'Reference Rates'!$B$33) -> 30 | Z21: =MIN(MAX(L21,'Reference Rates'!$B$39),'Reference Rates'!$B$40)*'Reference Rates'!$B$38 -> 451.75 | AA21: =MIN(L21,'Reference Rates'!$B$46)*'Reference Rates'!$B$45 -> 200 | AB21: =X21+Y21+Z21+AA21 -> 2481.75 | AC21: =L21+M21+N21+AB21 -> 21851.75
A22: EMP-017 | C22: Warehouse | D22: Warehouse Helper / Loader | E22: Y | F22: ='Reference Rates'!$E$13 -> 86.875 | G22: 208 | H22: 5 | I22: 0 | J22: =F22*G22 -> 18070 | K22: =F22*1.25*H22 -> 542.96875 | L22: =J22+K22 -> 18612.969 | M22: ='Reference Rates'!$B$19*G22/8 -> 1300 | N22: =I22*IFERROR(INDEX('Reference Rates'!$B$21:$B$22,MATCH(C22,'Reference Rates'!$A$21:$A$22,0)),0) -> 0 | O22: =MIN('Reference Rates'!$B$30,MAX('Reference Rates'!$B$29,MROUND(L22,500))) -> 18500 | P22: =O22*'Reference Rates'!$B$27 -> 925 | Q22: =MIN(MAX(L22,'Reference Rates'!$B$39),'Reference Rates'!$B$40)*'Reference Rates'!$B$37 -> 465.32422 | R22: =MIN(L22,'Reference Rates'!$B$46)*IF(L22>1500,'Reference Rates'!$B$43,'Reference Rates'!$B$44) -> 200 | S22: =P22+Q22+R22 -> 1590.3242 | T22: =IF(E22="Y",0,MAX(0,L22-S22)) -> 0 | U22: =IF(T22<='Reference Rates'!$D$51,0,IF(T22<='Reference Rates'!$D$52,'Reference Rates'!$B$51+(T22-'Reference Rates'!$D$51)*'Reference Rates'!$C$51,IF(T22<='Reference Rates'!$D$53,'Reference Rates'!$B$52+(T22-'Reference Rates'!$D$52)*'Reference Rates'!$C$52,IF(T22<='Reference Rates'!$D$54,'Reference Rates'!$B$53+(T22-'Reference Rates'!$D$53)*'Reference Rates'!$C$53,IF(T22<='Reference Rates'!$D$55,'Reference Rates'!$B$54+(T22-'Reference Rates'!$D$54)*'Reference Rates'!$C$54,'Reference Rates'!$B$55+(T22-'Reference Rates'!$D$55)*'Reference Rates'!$C$55))))) -> 0 | V22: =S22+U22 -> 1590.3242 | W22: =L22+M22+N22-V22 -> 18322.645 | X22: =O22*'Reference Rates'!$B$28 -> 1850 | Y22: =IF(O22<'Reference Rates'!$B$31,'Reference Rates'!$B$32,'Reference Rates'!$B$33) -> 30 | Z22: =MIN(MAX(L22,'Reference Rates'!$B$39),'Reference Rates'!$B$40)*'Reference Rates'!$B$38 -> 465.32422 | AA22: =MIN(L22,'Reference Rates'!$B$46)*'Reference Rates'!$B$45 -> 200 | AB22: =X22+Y22+Z22+AA22 -> 2545.3242 | AC22: =L22+M22+N22+AB22 -> 22458.293
A23: EMP-018 | C23: Warehouse | D23: Warehouse Helper / Loader | E23: Y | F23: ='Reference Rates'!$E$13 -> 86.875 | G23: 208 | H23: 0 | I23: 0 | J23: =F23*G23 -> 18070 | K23: =F23*1.25*H23 -> 0 | L23: =J23+K23 -> 18070 | M23: ='Reference Rates'!$B$19*G23/8 -> 1300 | N23: =I23*IFERROR(INDEX('Reference Rates'!$B$21:$B$22,MATCH(C23,'Reference Rates'!$A$21:$A$22,0)),0) -> 0 | O23: =MIN('Reference Rates'!$B$30,MAX('Reference Rates'!$B$29,MROUND(L23,500))) -> 18000 | P23: =O23*'Reference Rates'!$B$27 -> 900 | Q23: =MIN(MAX(L23,'Reference Rates'!$B$39),'Reference Rates'!$B$40)*'Reference Rates'!$B$37 -> 451.75 | R23: =MIN(L23,'Reference Rates'!$B$46)*IF(L23>1500,'Reference Rates'!$B$43,'Reference Rates'!$B$44) -> 200 | S23: =P23+Q23+R23 -> 1551.75 | T23: =IF(E23="Y",0,MAX(0,L23-S23)) -> 0 | U23: =IF(T23<='Reference Rates'!$D$51,0,IF(T23<='Reference Rates'!$D$52,'Reference Rates'!$B$51+(T23-'Reference Rates'!$D$51)*'Reference Rates'!$C$51,IF(T23<='Reference Rates'!$D$53,'Reference Rates'!$B$52+(T23-'Reference Rates'!$D$52)*'Reference Rates'!$C$52,IF(T23<='Reference Rates'!$D$54,'Reference Rates'!$B$53+(T23-'Reference Rates'!$D$53)*'Reference Rates'!$C$53,IF(T23<='Reference Rates'!$D$55,'Reference Rates'!$B$54+(T23-'Reference Rates'!$D$54)*'Reference Rates'!$C$54,'Reference Rates'!$B$55+(T23-'Reference Rates'!$D$55)*'Reference Rates'!$C$55))))) -> 0 | V23: =S23+U23 -> 1551.75 | W23: =L23+M23+N23-V23 -> 17818.25 | X23: =O23*'Reference Rates'!$B$28 -> 1800 | Y23: =IF(O23<'Reference Rates'!$B$31,'Reference Rates'!$B$32,'Reference Rates'!$B$33) -> 30 | Z23: =MIN(MAX(L23,'Reference Rates'!$B$39),'Reference Rates'!$B$40)*'Reference Rates'!$B$38 -> 451.75 | AA23: =MIN(L23,'Reference Rates'!$B$46)*'Reference Rates'!$B$45 -> 200 | AB23: =X23+Y23+Z23+AA23 -> 2481.75 | AC23: =L23+M23+N23+AB23 -> 21851.75
A24: EMP-019 | C24: Warehouse | D24: Inventory Clerk | E24: Y | F24: ='Reference Rates'!$E$13 -> 86.875 | G24: 208 | H24: 12 | I24: 0 | J24: =F24*G24 -> 18070 | K24: =F24*1.25*H24 -> 1303.125 | L24: =J24+K24 -> 19373.125 | M24: ='Reference Rates'!$B$19*G24/8 -> 1300 | N24: =I24*IFERROR(INDEX('Reference Rates'!$B$21:$B$22,MATCH(C24,'Reference Rates'!$A$21:$A$22,0)),0) -> 0 | O24: =MIN('Reference Rates'!$B$30,MAX('Reference Rates'!$B$29,MROUND(L24,500))) -> 19500 | P24: =O24*'Reference Rates'!$B$27 -> 975 | Q24: =MIN(MAX(L24,'Reference Rates'!$B$39),'Reference Rates'!$B$40)*'Reference Rates'!$B$37 -> 484.32812 | R24: =MIN(L24,'Reference Rates'!$B$46)*IF(L24>1500,'Reference Rates'!$B$43,'Reference Rates'!$B$44) -> 200 | S24: =P24+Q24+R24 -> 1659.3281 | T24: =IF(E24="Y",0,MAX(0,L24-S24)) -> 0 | U24: =IF(T24<='Reference Rates'!$D$51,0,IF(T24<='Reference Rates'!$D$52,'Reference Rates'!$B$51+(T24-'Reference Rates'!$D$51)*'Reference Rates'!$C$51,IF(T24<='Reference Rates'!$D$53,'Reference Rates'!$B$52+(T24-'Reference Rates'!$D$52)*'Reference Rates'!$C$52,IF(T24<='Reference Rates'!$D$54,'Reference Rates'!$B$53+(T24-'Reference Rates'!$D$53)*'Reference Rates'!$C$53,IF(T24<='Reference Rates'!$D$55,'Reference Rates'!$B$54+(T24-'Reference Rates'!$D$54)*'Reference Rates'!$C$54,'Reference Rates'!$B$55+(T24-'Reference Rates'!$D$55)*'Reference Rates'!$C$55))))) -> 0 | V24: =S24+U24 -> 1659.3281 | W24: =L24+M24+N24-V24 -> 19013.797 | X24: =O24*'Reference Rates'!$B$28 -> 1950 | Y24: =IF(O24<'Reference Rates'!$B$31,'Reference Rates'!$B$32,'Reference Rates'!$B$33) -> 30 | Z24: =MIN(MAX(L24,'Reference Rates'!$B$39),'Reference Rates'!$B$40)*'Reference Rates'!$B$38 -> 484.32812 | AA24: =MIN(L24,'Reference Rates'!$B$46)*'Reference Rates'!$B$45 -> 200 | AB24: =X24+Y24+Z24+AA24 -> 2664.3281 | AC24: =L24+M24+N24+AB24 -> 23337.453
A25: EMP-020 | C25: Warehouse | D25: Inventory Clerk | E25: Y | F25: ='Reference Rates'!$E$13 -> 86.875 | G25: 208 | H25: 0 | I25: 0 | J25: =F25*G25 -> 18070 | K25: =F25*1.25*H25 -> 0 | L25: =J25+K25 -> 18070 | M25: ='Reference Rates'!$B$19*G25/8 -> 1300 | N25: =I25*IFERROR(INDEX('Reference Rates'!$B$21:$B$22,MATCH(C25,'Reference Rates'!$A$21:$A$22,0)),0) -> 0 | O25: =MIN('Reference Rates'!$B$30,MAX('Reference Rates'!$B$29,MROUND(L25,500))) -> 18000 | P25: =O25*'Reference Rates'!$B$27 -> 900 | Q25: =MIN(MAX(L25,'Reference Rates'!$B$39),'Reference Rates'!$B$40)*'Reference Rates'!$B$37 -> 451.75 | R25: =MIN(L25,'Reference Rates'!$B$46)*IF(L25>1500,'Reference Rates'!$B$43,'Reference Rates'!$B$44) -> 200 | S25: =P25+Q25+R25 -> 1551.75 | T25: =IF(E25="Y",0,MAX(0,L25-S25)) -> 0 | U25: =IF(T25<='Reference Rates'!$D$51,0,IF(T25<='Reference Rates'!$D$52,'Reference Rates'!$B$51+(T25-'Reference Rates'!$D$51)*'Reference Rates'!$C$51,IF(T25<='Reference Rates'!$D$53,'Reference Rates'!$B$52+(T25-'Reference Rates'!$D$52)*'Reference Rates'!$C$52,IF(T25<='Reference Rates'!$D$54,'Reference Rates'!$B$53+(T25-'Reference Rates'!$D$53)*'Reference Rates'!$C$53,IF(T25<='Reference Rates'!$D$55,'Reference Rates'!$B$54+(T25-'Reference Rates'!$D$54)*'Reference Rates'!$C$54,'Reference Rates'!$B$55+(T25-'Reference Rates'!$D$55)*'Reference Rates'!$C$55))))) -> 0 | V25: =S25+U25 -> 1551.75 | W25: =L25+M25+N25-V25 -> 17818.25 | X25: =O25*'Reference Rates'!$B$28 -> 1800 | Y25: =IF(O25<'Reference Rates'!$B$31,'Reference Rates'!$B$32,'Reference Rates'!$B$33) -> 30 | Z25: =MIN(MAX(L25,'Reference Rates'!$B$39),'Reference Rates'!$B$40)*'Reference Rates'!$B$38 -> 451.75 | AA25: =MIN(L25,'Reference Rates'!$B$46)*'Reference Rates'!$B$45 -> 200 | AB25: =X25+Y25+Z25+AA25 -> 2481.75 | AC25: =L25+M25+N25+AB25 -> 21851.75
A26: EMP-021 | B26: Joshua Cedric D. Cortez | C26: Delivery – Luzon | D26: Delivery Driver – Luzon Routes | E26: N | F26: 100 | G26: 208 | H26: 12 | I26: 8 | J26: =F26*G26 -> 20800 | K26: =F26*1.25*H26 -> 1500 | L26: =J26+K26 -> 22300 | M26: ='Reference Rates'!$B$19*G26/8 -> 1300 | N26: =I26*IFERROR(INDEX('Reference Rates'!$B$21:$B$22,MATCH(C26,'Reference Rates'!$A$21:$A$22,0)),0) -> 4000 | O26: =MIN('Reference Rates'!$B$30,MAX('Reference Rates'!$B$29,MROUND(L26,500))) -> 22500 | P26: =O26*'Reference Rates'!$B$27 -> 1125 | Q26: =MIN(MAX(L26,'Reference Rates'!$B$39),'Reference Rates'!$B$40)*'Reference Rates'!$B$37 -> 557.5 | R26: =MIN(L26,'Reference Rates'!$B$46)*IF(L26>1500,'Reference Rates'!$B$43,'Reference Rates'!$B$44) -> 200 | S26: =P26+Q26+R26 -> 1882.5 | T26: =IF(E26="Y",0,MAX(0,L26-S26)) -> 20417.5 | U26: =IF(T26<='Reference Rates'!$D$51,0,IF(T26<='Reference Rates'!$D$52,'Reference Rates'!$B$51+(T26-'Reference Rates'!$D$51)*'Reference Rates'!$C$51,IF(T26<='Reference Rates'!$D$53,'Reference Rates'!$B$52+(T26-'Reference Rates'!$D$52)*'Reference Rates'!$C$52,IF(T26<='Reference Rates'!$D$54,'Reference Rates'!$B$53+(T26-'Reference Rates'!$D$53)*'Reference Rates'!$C$53,IF(T26<='Reference Rates'!$D$55,'Reference Rates'!$B$54+(T26-'Reference Rates'!$D$54)*'Reference Rates'!$C$54,'Reference Rates'!$B$55+(T26-'Reference Rates'!$D$55)*'Reference Rates'!$C$55))))) -> 0 | V26: =S26+U26 -> 1882.5 | W26: =L26+M26+N26-V26 -> 25717.5 | X26: =O26*'Reference Rates'!$B$28 -> 2250 | Y26: =IF(O26<'Reference Rates'!$B$31,'Reference Rates'!$B$32,'Reference Rates'!$B$33) -> 30 | Z26: =MIN(MAX(L26,'Reference Rates'!$B$39),'Reference Rates'!$B$40)*'Reference Rates'!$B$38 -> 557.5 | AA26: =MIN(L26,'Reference Rates'!$B$46)*'Reference Rates'!$B$45 -> 200 | AB26: =X26+Y26+Z26+AA26 -> 3037.5 | AC26: =L26+M26+N26+AB26 -> 30637.5
A27: EMP-022 | C27: Delivery – Luzon | D27: Delivery Driver – Luzon Routes | E27: N | F27: 105 | G27: 208 | H27: 9 | I27: 7 | J27: =F27*G27 -> 21840 | K27: =F27*1.25*H27 -> 1181.25 | L27: =J27+K27 -> 23021.25 | M27: ='Reference Rates'!$B$19*G27/8 -> 1300 | N27: =I27*IFERROR(INDEX('Reference Rates'!$B$21:$B$22,MATCH(C27,'Reference Rates'!$A$21:$A$22,0)),0) -> 3500 | O27: =MIN('Reference Rates'!$B$30,MAX('Reference Rates'!$B$29,MROUND(L27,500))) -> 23000 | P27: =O27*'Reference Rates'!$B$27 -> 1150 | Q27: =MIN(MAX(L27,'Reference Rates'!$B$39),'Reference Rates'!$B$40)*'Reference Rates'!$B$37 -> 575.53125 | R27: =MIN(L27,'Reference Rates'!$B$46)*IF(L27>1500,'Reference Rates'!$B$43,'Reference Rates'!$B$44) -> 200 | S27: =P27+Q27+R27 -> 1925.5312 | T27: =IF(E27="Y",0,MAX(0,L27-S27)) -> 21095.719 | U27: =IF(T27<='Reference Rates'!$D$51,0,IF(T27<='Reference Rates'!$D$52,'Reference Rates'!$B$51+(T27-'Reference Rates'!$D$51)*'Reference Rates'!$C$51,IF(T27<='Reference Rates'!$D$53,'Reference Rates'!$B$52+(T27-'Reference Rates'!$D$52)*'Reference Rates'!$C$52,IF(T27<='Reference Rates'!$D$54,'Reference Rates'!$B$53+(T27-'Reference Rates'!$D$53)*'Reference Rates'!$C$53,IF(T27<='Reference Rates'!$D$55,'Reference Rates'!$B$54+(T27-'Reference Rates'!$D$54)*'Reference Rates'!$C$54,'Reference Rates'!$B$55+(T27-'Reference Rates'!$D$55)*'Reference Rates'!$C$55))))) -> 39.407812 | V27: =S27+U27 -> 1964.9391 | W27: =L27+M27+N27-V27 -> 25856.311 | X27: =O27*'Reference Rates'!$B$28 -> 2300 | Y27: =IF(O27<'Reference Rates'!$B$31,'Reference Rates'!$B$32,'Reference Rates'!$B$33) -> 30 | Z27: =MIN(MAX(L27,'Reference Rates'!$B$39),'Reference Rates'!$B$40)*'Reference Rates'!$B$38 -> 575.53125 | AA27: =MIN(L27,'Reference Rates'!$B$46)*'Reference Rates'!$B$45 -> 200 | AB27: =X27+Y27+Z27+AA27 -> 3105.5312 | AC27: =L27+M27+N27+AB27 -> 30926.781
A28: EMP-023 | C28: Delivery – Luzon | D28: Delivery Driver – Luzon Routes | E28: N | F28: 100 | G28: 208 | H28: 16 | I28: 9 | J28: =F28*G28 -> 20800 | K28: =F28*1.25*H28 -> 2000 | L28: =J28+K28 -> 22800 | M28: ='Reference Rates'!$B$19*G28/8 -> 1300 | N28: =I28*IFERROR(INDEX('Reference Rates'!$B$21:$B$22,MATCH(C28,'Reference Rates'!$A$21:$A$22,0)),0) -> 4500 | O28: =MIN('Reference Rates'!$B$30,MAX('Reference Rates'!$B$29,MROUND(L28,500))) -> 23000 | P28: =O28*'Reference Rates'!$B$27 -> 1150 | Q28: =MIN(MAX(L28,'Reference Rates'!$B$39),'Reference Rates'!$B$40)*'Reference Rates'!$B$37 -> 570 | R28: =MIN(L28,'Reference Rates'!$B$46)*IF(L28>1500,'Reference Rates'!$B$43,'Reference Rates'!$B$44) -> 200 | S28: =P28+Q28+R28 -> 1920 | T28: =IF(E28="Y",0,MAX(0,L28-S28)) -> 20880 | U28: =IF(T28<='Reference Rates'!$D$51,0,IF(T28<='Reference Rates'!$D$52,'Reference Rates'!$B$51+(T28-'Reference Rates'!$D$51)*'Reference Rates'!$C$51,IF(T28<='Reference Rates'!$D$53,'Reference Rates'!$B$52+(T28-'Reference Rates'!$D$52)*'Reference Rates'!$C$52,IF(T28<='Reference Rates'!$D$54,'Reference Rates'!$B$53+(T28-'Reference Rates'!$D$53)*'Reference Rates'!$C$53,IF(T28<='Reference Rates'!$D$55,'Reference Rates'!$B$54+(T28-'Reference Rates'!$D$54)*'Reference Rates'!$C$54,'Reference Rates'!$B$55+(T28-'Reference Rates'!$D$55)*'Reference Rates'!$C$55))))) -> 7.05 | V28: =S28+U28 -> 1927.05 | W28: =L28+M28+N28-V28 -> 26672.95 | X28: =O28*'Reference Rates'!$B$28 -> 2300 | Y28: =IF(O28<'Reference Rates'!$B$31,'Reference Rates'!$B$32,'Reference Rates'!$B$33) -> 30 | Z28: =MIN(MAX(L28,'Reference Rates'!$B$39),'Reference Rates'!$B$40)*'Reference Rates'!$B$38 -> 570 | AA28: =MIN(L28,'Reference Rates'!$B$46)*'Reference Rates'!$B$45 -> 200 | AB28: =X28+Y28+Z28+AA28 -> 3100 | AC28: =L28+M28+N28+AB28 -> 31700
A29: EMP-024 | B29: Tristan Judd Mari Magsino | C29: Delivery – Samar | D29: Delivery Driver – Samar Routes | E29: N | F29: 110 | G29: 208 | H29: 23 | I29: 10 | J29: =F29*G29 -> 22880 | K29: =F29*1.25*H29 -> 3162.5 | L29: =J29+K29 -> 26042.5 | M29: ='Reference Rates'!$B$19*G29/8 -> 1300 | N29: =I29*IFERROR(INDEX('Reference Rates'!$B$21:$B$22,MATCH(C29,'Reference Rates'!$A$21:$A$22,0)),0) -> 9000 | O29: =MIN('Reference Rates'!$B$30,MAX('Reference Rates'!$B$29,MROUND(L29,500))) -> 26000 | P29: =O29*'Reference Rates'!$B$27 -> 1300 | Q29: =MIN(MAX(L29,'Reference Rates'!$B$39),'Reference Rates'!$B$40)*'Reference Rates'!$B$37 -> 651.0625 | R29: =MIN(L29,'Reference Rates'!$B$46)*IF(L29>1500,'Reference Rates'!$B$43,'Reference Rates'!$B$44) -> 200 | S29: =P29+Q29+R29 -> 2151.0625 | T29: =IF(E29="Y",0,MAX(0,L29-S29)) -> 23891.438 | U29: =IF(T29<='Reference Rates'!$D$51,0,IF(T29<='Reference Rates'!$D$52,'Reference Rates'!$B$51+(T29-'Reference Rates'!$D$51)*'Reference Rates'!$C$51,IF(T29<='Reference Rates'!$D$53,'Reference Rates'!$B$52+(T29-'Reference Rates'!$D$52)*'Reference Rates'!$C$52,IF(T29<='Reference Rates'!$D$54,'Reference Rates'!$B$53+(T29-'Reference Rates'!$D$53)*'Reference Rates'!$C$53,IF(T29<='Reference Rates'!$D$55,'Reference Rates'!$B$54+(T29-'Reference Rates'!$D$54)*'Reference Rates'!$C$54,'Reference Rates'!$B$55+(T29-'Reference Rates'!$D$55)*'Reference Rates'!$C$55))))) -> 458.76562 | V29: =S29+U29 -> 2609.8281 | W29: =L29+M29+N29-V29 -> 33732.672 | X29: =O29*'Reference Rates'!$B$28 -> 2600 | Y29: =IF(O29<'Reference Rates'!$B$31,'Reference Rates'!$B$32,'Reference Rates'!$B$33) -> 30 | Z29: =MIN(MAX(L29,'Reference Rates'!$B$39),'Reference Rates'!$B$40)*'Reference Rates'!$B$38 -> 651.0625 | AA29: =MIN(L29,'Reference Rates'!$B$46)*'Reference Rates'!$B$45 -> 200 | AB29: =X29+Y29+Z29+AA29 -> 3481.0625 | AC29: =L29+M29+N29+AB29 -> 39823.562
A30: EMP-025 | C30: Delivery – Samar | D30: Delivery Driver – Samar Routes | E30: N | F30: 115 | G30: 208 | H30: 16 | I30: 10 | J30: =F30*G30 -> 23920 | K30: =F30*1.25*H30 -> 2300 | L30: =J30+K30 -> 26220 | M30: ='Reference Rates'!$B$19*G30/8 -> 1300 | N30: =I30*IFERROR(INDEX('Reference Rates'!$B$21:$B$22,MATCH(C30,'Reference Rates'!$A$21:$A$22,0)),0) -> 9000 | O30: =MIN('Reference Rates'!$B$30,MAX('Reference Rates'!$B$29,MROUND(L30,500))) -> 26000 | P30: =O30*'Reference Rates'!$B$27 -> 1300 | Q30: =MIN(MAX(L30,'Reference Rates'!$B$39),'Reference Rates'!$B$40)*'Reference Rates'!$B$37 -> 655.5 | R30: =MIN(L30,'Reference Rates'!$B$46)*IF(L30>1500,'Reference Rates'!$B$43,'Reference Rates'!$B$44) -> 200 | S30: =P30+Q30+R30 -> 2155.5 | T30: =IF(E30="Y",0,MAX(0,L30-S30)) -> 24064.5 | U30: =IF(T30<='Reference Rates'!$D$51,0,IF(T30<='Reference Rates'!$D$52,'Reference Rates'!$B$51+(T30-'Reference Rates'!$D$51)*'Reference Rates'!$C$51,IF(T30<='Reference Rates'!$D$53,'Reference Rates'!$B$52+(T30-'Reference Rates'!$D$52)*'Reference Rates'!$C$52,IF(T30<='Reference Rates'!$D$54,'Reference Rates'!$B$53+(T30-'Reference Rates'!$D$53)*'Reference Rates'!$C$53,IF(T30<='Reference Rates'!$D$55,'Reference Rates'!$B$54+(T30-'Reference Rates'!$D$54)*'Reference Rates'!$C$54,'Reference Rates'!$B$55+(T30-'Reference Rates'!$D$55)*'Reference Rates'!$C$55))))) -> 484.725 | V30: =S30+U30 -> 2640.225 | W30: =L30+M30+N30-V30 -> 33879.775 | X30: =O30*'Reference Rates'!$B$28 -> 2600 | Y30: =IF(O30<'Reference Rates'!$B$31,'Reference Rates'!$B$32,'Reference Rates'!$B$33) -> 30 | Z30: =MIN(MAX(L30,'Reference Rates'!$B$39),'Reference Rates'!$B$40)*'Reference Rates'!$B$38 -> 655.5 | AA30: =MIN(L30,'Reference Rates'!$B$46)*'Reference Rates'!$B$45 -> 200 | AB30: =X30+Y30+Z30+AA30 -> 3485.5 | AC30: =L30+M30+N30+AB30 -> 40005.5
A31: EMP-026 | C31: Delivery – Samar | D31: Delivery Driver – Samar Routes | E31: N | F31: 110 | G31: 208 | H31: 16 | I31: 8 | J31: =F31*G31 -> 22880 | K31: =F31*1.25*H31 -> 2200 | L31: =J31+K31 -> 25080 | M31: ='Reference Rates'!$B$19*G31/8 -> 1300 | N31: =I31*IFERROR(INDEX('Reference Rates'!$B$21:$B$22,MATCH(C31,'Reference Rates'!$A$21:$A$22,0)),0) -> 7200 | O31: =MIN('Reference Rates'!$B$30,MAX('Reference Rates'!$B$29,MROUND(L31,500))) -> 25000 | P31: =O31*'Reference Rates'!$B$27 -> 1250 | Q31: =MIN(MAX(L31,'Reference Rates'!$B$39),'Reference Rates'!$B$40)*'Reference Rates'!$B$37 -> 627 | R31: =MIN(L31,'Reference Rates'!$B$46)*IF(L31>1500,'Reference Rates'!$B$43,'Reference Rates'!$B$44) -> 200 | S31: =P31+Q31+R31 -> 2077 | T31: =IF(E31="Y",0,MAX(0,L31-S31)) -> 23003 | U31: =IF(T31<='Reference Rates'!$D$51,0,IF(T31<='Reference Rates'!$D$52,'Reference Rates'!$B$51+(T31-'Reference Rates'!$D$51)*'Reference Rates'!$C$51,IF(T31<='Reference Rates'!$D$53,'Reference Rates'!$B$52+(T31-'Reference Rates'!$D$52)*'Reference Rates'!$C$52,IF(T31<='Reference Rates'!$D$54,'Reference Rates'!$B$53+(T31-'Reference Rates'!$D$53)*'Reference Rates'!$C$53,IF(T31<='Reference Rates'!$D$55,'Reference Rates'!$B$54+(T31-'Reference Rates'!$D$54)*'Reference Rates'!$C$54,'Reference Rates'!$B$55+(T31-'Reference Rates'!$D$55)*'Reference Rates'!$C$55))))) -> 325.5 | V31: =S31+U31 -> 2402.5 | W31: =L31+M31+N31-V31 -> 31177.5 | X31: =O31*'Reference Rates'!$B$28 -> 2500 | Y31: =IF(O31<'Reference Rates'!$B$31,'Reference Rates'!$B$32,'Reference Rates'!$B$33) -> 30 | Z31: =MIN(MAX(L31,'Reference Rates'!$B$39),'Reference Rates'!$B$40)*'Reference Rates'!$B$38 -> 627 | AA31: =MIN(L31,'Reference Rates'!$B$46)*'Reference Rates'!$B$45 -> 200 | AB31: =X31+Y31+Z31+AA31 -> 3357 | AC31: =L31+M31+N31+AB31 -> 36937
A32: EMP-027 | C32: Admin / Supervisory | D32: Store Supervisor | E32: N | F32: 120 | G32: 208 | H32: 3 | I32: 0 | J32: =F32*G32 -> 24960 | K32: =F32*1.25*H32 -> 450 | L32: =J32+K32 -> 25410 | M32: ='Reference Rates'!$B$19*G32/8 -> 1300 | N32: =I32*IFERROR(INDEX('Reference Rates'!$B$21:$B$22,MATCH(C32,'Reference Rates'!$A$21:$A$22,0)),0) -> 0 | O32: =MIN('Reference Rates'!$B$30,MAX('Reference Rates'!$B$29,MROUND(L32,500))) -> 25500 | P32: =O32*'Reference Rates'!$B$27 -> 1275 | Q32: =MIN(MAX(L32,'Reference Rates'!$B$39),'Reference Rates'!$B$40)*'Reference Rates'!$B$37 -> 635.25 | R32: =MIN(L32,'Reference Rates'!$B$46)*IF(L32>1500,'Reference Rates'!$B$43,'Reference Rates'!$B$44) -> 200 | S32: =P32+Q32+R32 -> 2110.25 | T32: =IF(E32="Y",0,MAX(0,L32-S32)) -> 23299.75 | U32: =IF(T32<='Reference Rates'!$D$51,0,IF(T32<='Reference Rates'!$D$52,'Reference Rates'!$B$51+(T32-'Reference Rates'!$D$51)*'Reference Rates'!$C$51,IF(T32<='Reference Rates'!$D$53,'Reference Rates'!$B$52+(T32-'Reference Rates'!$D$52)*'Reference Rates'!$C$52,IF(T32<='Reference Rates'!$D$54,'Reference Rates'!$B$53+(T32-'Reference Rates'!$D$53)*'Reference Rates'!$C$53,IF(T32<='Reference Rates'!$D$55,'Reference Rates'!$B$54+(T32-'Reference Rates'!$D$54)*'Reference Rates'!$C$54,'Reference Rates'!$B$55+(T32-'Reference Rates'!$D$55)*'Reference Rates'!$C$55))))) -> 370.0125 | V32: =S32+U32 -> 2480.2625 | W32: =L32+M32+N32-V32 -> 24229.737 | X32: =O32*'Reference Rates'!$B$28 -> 2550 | Y32: =IF(O32<'Reference Rates'!$B$31,'Reference Rates'!$B$32,'Reference Rates'!$B$33) -> 30 | Z32: =MIN(MAX(L32,'Reference Rates'!$B$39),'Reference Rates'!$B$40)*'Reference Rates'!$B$38 -> 635.25 | AA32: =MIN(L32,'Reference Rates'!$B$46)*'Reference Rates'!$B$45 -> 200 | AB32: =X32+Y32+Z32+AA32 -> 3415.25 | AC32: =L32+M32+N32+AB32 -> 30125.25
A33: EMP-028 | C33: Admin / Supervisory | D33: Warehouse & Logistics Supervisor | E33: N | F33: 130 | G33: 208 | H33: 0 | I33: 0 | J33: =F33*G33 -> 27040 | K33: =F33*1.25*H33 -> 0 | L33: =J33+K33 -> 27040 | M33: ='Reference Rates'!$B$19*G33/8 -> 1300 | N33: =I33*IFERROR(INDEX('Reference Rates'!$B$21:$B$22,MATCH(C33,'Reference Rates'!$A$21:$A$22,0)),0) -> 0 | O33: =MIN('Reference Rates'!$B$30,MAX('Reference Rates'!$B$29,MROUND(L33,500))) -> 27000 | P33: =O33*'Reference Rates'!$B$27 -> 1350 | Q33: =MIN(MAX(L33,'Reference Rates'!$B$39),'Reference Rates'!$B$40)*'Reference Rates'!$B$37 -> 676 | R33: =MIN(L33,'Reference Rates'!$B$46)*IF(L33>1500,'Reference Rates'!$B$43,'Reference Rates'!$B$44) -> 200 | S33: =P33+Q33+R33 -> 2226 | T33: =IF(E33="Y",0,MAX(0,L33-S33)) -> 24814 | U33: =IF(T33<='Reference Rates'!$D$51,0,IF(T33<='Reference Rates'!$D$52,'Reference Rates'!$B$51+(T33-'Reference Rates'!$D$51)*'Reference Rates'!$C$51,IF(T33<='Reference Rates'!$D$53,'Reference Rates'!$B$52+(T33-'Reference Rates'!$D$52)*'Reference Rates'!$C$52,IF(T33<='Reference Rates'!$D$54,'Reference Rates'!$B$53+(T33-'Reference Rates'!$D$53)*'Reference Rates'!$C$53,IF(T33<='Reference Rates'!$D$55,'Reference Rates'!$B$54+(T33-'Reference Rates'!$D$54)*'Reference Rates'!$C$54,'Reference Rates'!$B$55+(T33-'Reference Rates'!$D$55)*'Reference Rates'!$C$55))))) -> 597.15 | V33: =S33+U33 -> 2823.15 | W33: =L33+M33+N33-V33 -> 25516.85 | X33: =O33*'Reference Rates'!$B$28 -> 2700 | Y33: =IF(O33<'Reference Rates'!$B$31,'Reference Rates'!$B$32,'Reference Rates'!$B$33) -> 30 | Z33: =MIN(MAX(L33,'Reference Rates'!$B$39),'Reference Rates'!$B$40)*'Reference Rates'!$B$38 -> 676 | AA33: =MIN(L33,'Reference Rates'!$B$46)*'Reference Rates'!$B$45 -> 200 | AB33: =X33+Y33+Z33+AA33 -> 3606 | AC33: =L33+M33+N33+AB33 -> 31946
A34: EMP-029 | C34: Admin / Supervisory | D34: Admin & Payroll Officer | E34: N | F34: 140 | G34: 208 | H34: 0 | I34: 0 | J34: =F34*G34 -> 29120 | K34: =F34*1.25*H34 -> 0 | L34: =J34+K34 -> 29120 | M34: ='Reference Rates'!$B$19*G34/8 -> 1300 | N34: =I34*IFERROR(INDEX('Reference Rates'!$B$21:$B$22,MATCH(C34,'Reference Rates'!$A$21:$A$22,0)),0) -> 0 | O34: =MIN('Reference Rates'!$B$30,MAX('Reference Rates'!$B$29,MROUND(L34,500))) -> 29000 | P34: =O34*'Reference Rates'!$B$27 -> 1450 | Q34: =MIN(MAX(L34,'Reference Rates'!$B$39),'Reference Rates'!$B$40)*'Reference Rates'!$B$37 -> 728 | R34: =MIN(L34,'Reference Rates'!$B$46)*IF(L34>1500,'Reference Rates'!$B$43,'Reference Rates'!$B$44) -> 200 | S34: =P34+Q34+R34 -> 2378 | T34: =IF(E34="Y",0,MAX(0,L34-S34)) -> 26742 | U34: =IF(T34<='Reference Rates'!$D$51,0,IF(T34<='Reference Rates'!$D$52,'Reference Rates'!$B$51+(T34-'Reference Rates'!$D$51)*'Reference Rates'!$C$51,IF(T34<='Reference Rates'!$D$53,'Reference Rates'!$B$52+(T34-'Reference Rates'!$D$52)*'Reference Rates'!$C$52,IF(T34<='Reference Rates'!$D$54,'Reference Rates'!$B$53+(T34-'Reference Rates'!$D$53)*'Reference Rates'!$C$53,IF(T34<='Reference Rates'!$D$55,'Reference Rates'!$B$54+(T34-'Reference Rates'!$D$54)*'Reference Rates'!$C$54,'Reference Rates'!$B$55+(T34-'Reference Rates'!$D$55)*'Reference Rates'!$C$55))))) -> 886.35 | V34: =S34+U34 -> 3264.35 | W34: =L34+M34+N34-V34 -> 27155.65 | X34: =O34*'Reference Rates'!$B$28 -> 2900 | Y34: =IF(O34<'Reference Rates'!$B$31,'Reference Rates'!$B$32,'Reference Rates'!$B$33) -> 30 | Z34: =MIN(MAX(L34,'Reference Rates'!$B$39),'Reference Rates'!$B$40)*'Reference Rates'!$B$38 -> 728 | AA34: =MIN(L34,'Reference Rates'!$B$46)*'Reference Rates'!$B$45 -> 200 | AB34: =X34+Y34+Z34+AA34 -> 3858 | AC34: =L34+M34+N34+AB34 -> 34278
A35: EMP-030 | B35: Johnbel A. Maliñana | C35: Admin / Supervisory | D35: Operations Manager | E35: N | F35: 160 | G35: 208 | H35: 0 | I35: 0 | J35: =F35*G35 -> 33280 | K35: =F35*1.25*H35 -> 0 | L35: =J35+K35 -> 33280 | M35: ='Reference Rates'!$B$19*G35/8 -> 1300 | N35: =I35*IFERROR(INDEX('Reference Rates'!$B$21:$B$22,MATCH(C35,'Reference Rates'!$A$21:$A$22,0)),0) -> 0 | O35: =MIN('Reference Rates'!$B$30,MAX('Reference Rates'!$B$29,MROUND(L35,500))) -> 33500 | P35: =O35*'Reference Rates'!$B$27 -> 1675 | Q35: =MIN(MAX(L35,'Reference Rates'!$B$39),'Reference Rates'!$B$40)*'Reference Rates'!$B$37 -> 832 | R35: =MIN(L35,'Reference Rates'!$B$46)*IF(L35>1500,'Reference Rates'!$B$43,'Reference Rates'!$B$44) -> 200 | S35: =P35+Q35+R35 -> 2707 | T35: =IF(E35="Y",0,MAX(0,L35-S35)) -> 30573 | U35: =IF(T35<='Reference Rates'!$D$51,0,IF(T35<='Reference Rates'!$D$52,'Reference Rates'!$B$51+(T35-'Reference Rates'!$D$51)*'Reference Rates'!$C$51,IF(T35<='Reference Rates'!$D$53,'Reference Rates'!$B$52+(T35-'Reference Rates'!$D$52)*'Reference Rates'!$C$52,IF(T35<='Reference Rates'!$D$54,'Reference Rates'!$B$53+(T35-'Reference Rates'!$D$53)*'Reference Rates'!$C$53,IF(T35<='Reference Rates'!$D$55,'Reference Rates'!$B$54+(T35-'Reference Rates'!$D$54)*'Reference Rates'!$C$54,'Reference Rates'!$B$55+(T35-'Reference Rates'!$D$55)*'Reference Rates'!$C$55))))) -> 1461 | V35: =S35+U35 -> 4168 | W35: =L35+M35+N35-V35 -> 30412 | X35: =O35*'Reference Rates'!$B$28 -> 3350 | Y35: =IF(O35<'Reference Rates'!$B$31,'Reference Rates'!$B$32,'Reference Rates'!$B$33) -> 30 | Z35: =MIN(MAX(L35,'Reference Rates'!$B$39),'Reference Rates'!$B$40)*'Reference Rates'!$B$38 -> 832 | AA35: =MIN(L35,'Reference Rates'!$B$46)*'Reference Rates'!$B$45 -> 200 | AB35: =X35+Y35+Z35+AA35 -> 4412 | AC35: =L35+M35+N35+AB35 -> 38992
A36: TOTAL | G36: =SUM(G6:G35) -> 6216 | H36: =SUM(H6:H35) -> 157 | I36: =SUM(I6:I35) -> 52 | J36: =SUM(J6:J35) -> 606835 | K36: =SUM(K6:K35) -> 19526.562 | L36: =SUM(L6:L35) -> 626361.56 | M36: =SUM(M6:M35) -> 38850 | N36: =SUM(N6:N35) -> 37200 | P36: =SUM(P6:P35) -> 31300 | Q36: =SUM(Q6:Q35) -> 15659.039 | R36: =SUM(R6:R35) -> 6000 | S36: =SUM(S6:S35) -> 52959.039 | T36: =SUM(T6:T35) -> 238780.91 | U36: =SUM(U6:U35) -> 4629.9609 | V36: =SUM(V6:V35) -> 57589 | W36: =SUM(W6:W35) -> 644822.56 | ... AC36: =SUM(AC6:AC35) -> 787570.6
A38: Legend: | B38: Blue = input (edit) | C38: Black = formula | D38: Green text = linked from another sheet | G38: Green row = delivery driver

Sheet Sep 2026
A1: Employee Payroll Register — September 2026
A2: Blue = input; black = formula; green = linked from another sheet. Names, departments, positions, MWE status and fixed hourly rates are linked from the Aug 2026 sheet. Green-tinted rows = delivery drivers. Regular Hours default to 208 (26 days × 8 hrs). OT is the ordinary 125% premium. Per diem = Trip Days × the department rate on Reference Rates. Allowances are non-taxable and outside the SSS/PhilHealth/Pag-IBIG base. Printed pages cover columns A–W (employee-facing); employer-cost columns X–AC are on screen only.
A3: Pay Period: | B3: 2026-09-01 to 2026-09-30
A5: Employee ID | B5: Employee Name | C5: Department | D5: Position | E5: MWE (Y/N) | F5: Hourly Rate (₱) | G5: Regular Hours | H5: OT Hours (125%) | I5: Trip Days (per diem) | J5: Basic Pay | K5: OT Pay | L5: GROSS PAY | M5: Meal Allowance | N5: Per Diem | O5: SSS MSC | P5: SSS – EE | Q5: PhilHealth – EE | R5: Pag-IBIG – EE | S5: Total EE Contrib. | T5: Taxable Income | U5: Withholding Tax | V5: Total Deductions | W5: NET PAY | X5: SSS – ER | Y5: SSS – EC | Z5: PhilHealth – ER | AA5: Pag-IBIG – ER | AB5: Total ER Contrib. | AC5: TOTAL COST TO COMPANY
A6: ='Aug 2026'!A6 -> EMP-001 | B6: =IF('Aug 2026'!B6="","",'Aug 2026'!B6) -> Mikhail Dustin Elpedes | C6: ='Aug 2026'!C6 -> Store | D6: ='Aug 2026'!D6 -> Cashier | E6: ='Aug 2026'!E6 -> Y | F6: ='Reference Rates'!$E$14 -> 88.125 | G6: 208 | H6: 2 | I6: 0 | J6: =F6*G6 -> 18330 | K6: =F6*1.25*H6 -> 220.3125 | L6: =J6+K6 -> 18550.312 | M6: ='Reference Rates'!$B$19*G6/8 -> 1300 | N6: =I6*IFERROR(INDEX('Reference Rates'!$B$21:$B$22,MATCH(C6,'Reference Rates'!$A$21:$A$22,0)),0) -> 0 | O6: =MIN('Reference Rates'!$B$30,MAX('Reference Rates'!$B$29,MROUND(L6,500))) -> 18500 | P6: =O6*'Reference Rates'!$B$27 -> 925 | Q6: =MIN(MAX(L6,'Reference Rates'!$B$39),'Reference Rates'!$B$40)*'Reference Rates'!$B$37 -> 463.75781 | R6: =MIN(L6,'Reference Rates'!$B$46)*IF(L6>1500,'Reference Rates'!$B$43,'Reference Rates'!$B$44) -> 200 | S6: =P6+Q6+R6 -> 1588.7578 | T6: =IF(E6="Y",0,MAX(0,L6-S6)) -> 0 | U6: =IF(T6<='Reference Rates'!$D$51,0,IF(T6<='Reference Rates'!$D$52,'Reference Rates'!$B$51+(T6-'Reference Rates'!$D$51)*'Reference Rates'!$C$51,IF(T6<='Reference Rates'!$D$53,'Reference Rates'!$B$52+(T6-'Reference Rates'!$D$52)*'Reference Rates'!$C$52,IF(T6<='Reference Rates'!$D$54,'Reference Rates'!$B$53+(T6-'Reference Rates'!$D$53)*'Reference Rates'!$C$53,IF(T6<='Reference Rates'!$D$55,'Reference Rates'!$B$54+(T6-'Reference Rates'!$D$54)*'Reference Rates'!$C$54,'Reference Rates'!$B$55+(T6-'Reference Rates'!$D$55)*'Reference Rates'!$C$55))))) -> 0 | V6: =S6+U6 -> 1588.7578 | W6: =L6+M6+N6-V6 -> 18261.555 | X6: =O6*'Reference Rates'!$B$28 -> 1850 | Y6: =IF(O6<'Reference Rates'!$B$31,'Reference Rates'!$B$32,'Reference Rates'!$B$33) -> 30 | Z6: =MIN(MAX(L6,'Reference Rates'!$B$39),'Reference Rates'!$B$40)*'Reference Rates'!$B$38 -> 463.75781 | AA6: =MIN(L6,'Reference Rates'!$B$46)*'Reference Rates'!$B$45 -> 200 | AB6: =X6+Y6+Z6+AA6 -> 2543.7578 | AC6: =L6+M6+N6+AB6 -> 22394.07
A7: ='Aug 2026'!A7 -> EMP-002 | B7: =IF('Aug 2026'!B7="","",'Aug 2026'!B7) | C7: ='Aug 2026'!C7 -> Store | D7: ='Aug 2026'!D7 -> Cashier | E7: ='Aug 2026'!E7 -> Y | F7: ='Reference Rates'!$E$14 -> 88.125 | G7: 208 | H7: 5 | I7: 0 | J7: =F7*G7 -> 18330 | K7: =F7*1.25*H7 -> 550.78125 | L7: =J7+K7 -> 18880.781 | M7: ='Reference Rates'!$B$19*G7/8 -> 1300 | N7: =I7*IFERROR(INDEX('Reference Rates'!$B$21:$B$22,MATCH(C7,'Reference Rates'!$A$21:$A$22,0)),0) -> 0 | O7: =MIN('Reference Rates'!$B$30,MAX('Reference Rates'!$B$29,MROUND(L7,500))) -> 19000 | P7: =O7*'Reference Rates'!$B$27 -> 950 | Q7: =MIN(MAX(L7,'Reference Rates'!$B$39),'Reference Rates'!$B$40)*'Reference Rates'!$B$37 -> 472.01953 | R7: =MIN(L7,'Reference Rates'!$B$46)*IF(L7>1500,'Reference Rates'!$B$43,'Reference Rates'!$B$44) -> 200 | S7: =P7+Q7+R7 -> 1622.0195 | T7: =IF(E7="Y",0,MAX(0,L7-S7)) -> 0 | U7: =IF(T7<='Reference Rates'!$D$51,0,IF(T7<='Reference Rates'!$D$52,'Reference Rates'!$B$51+(T7-'Reference Rates'!$D$51)*'Reference Rates'!$C$51,IF(T7<='Reference Rates'!$D$53,'Reference Rates'!$B$52+(T7-'Reference Rates'!$D$52)*'Reference Rates'!$C$52,IF(T7<='Reference Rates'!$D$54,'Reference Rates'!$B$53+(T7-'Reference Rates'!$D$53)*'Reference Rates'!$C$53,IF(T7<='Reference Rates'!$D$55,'Reference Rates'!$B$54+(T7-'Reference Rates'!$D$54)*'Reference Rates'!$C$54,'Reference Rates'!$B$55+(T7-'Reference Rates'!$D$55)*'Reference Rates'!$C$55))))) -> 0 | V7: =S7+U7 -> 1622.0195 | W7: =L7+M7+N7-V7 -> 18558.762 | X7: =O7*'Reference Rates'!$B$28 -> 1900 | Y7: =IF(O7<'Reference Rates'!$B$31,'Reference Rates'!$B$32,'Reference Rates'!$B$33) -> 30 | Z7: =MIN(MAX(L7,'Reference Rates'!$B$39),'Reference Rates'!$B$40)*'Reference Rates'!$B$38 -> 472.01953 | AA7: =MIN(L7,'Reference Rates'!$B$46)*'Reference Rates'!$B$45 -> 200 | AB7: =X7+Y7+Z7+AA7 -> 2602.0195 | AC7: =L7+M7+N7+AB7 -> 22782.801
A8: ='Aug 2026'!A8 -> EMP-003 | B8: =IF('Aug 2026'!B8="","",'Aug 2026'!B8) | C8: ='Aug 2026'!C8 -> Store | D8: ='Aug 2026'!D8 -> Cashier | E8: ='Aug 2026'!E8 -> Y | F8: ='Reference Rates'!$E$14 -> 88.125 | G8: 208 | H8: 0 | I8: 0 | J8: =F8*G8 -> 18330 | K8: =F8*1.25*H8 -> 0 | L8: =J8+K8 -> 18330 | M8: ='Reference Rates'!$B$19*G8/8 -> 1300 | N8: =I8*IFERROR(INDEX('Reference Rates'!$B$21:$B$22,MATCH(C8,'Reference Rates'!$A$21:$A$22,0)),0) -> 0 | O8: =MIN('Reference Rates'!$B$30,MAX('Reference Rates'!$B$29,MROUND(L8,500))) -> 18500 | P8: =O8*'Reference Rates'!$B$27 -> 925 | Q8: =MIN(MAX(L8,'Reference Rates'!$B$39),'Reference Rates'!$B$40)*'Reference Rates'!$B$37 -> 458.25 | R8: =MIN(L8,'Reference Rates'!$B$46)*IF(L8>1500,'Reference Rates'!$B$43,'Reference Rates'!$B$44) -> 200 | S8: =P8+Q8+R8 -> 1583.25 | T8: =IF(E8="Y",0,MAX(0,L8-S8)) -> 0 | U8: =IF(T8<='Reference Rates'!$D$51,0,IF(T8<='Reference Rates'!$D$52,'Reference Rates'!$B$51+(T8-'Reference Rates'!$D$51)*'Reference Rates'!$C$51,IF(T8<='Reference Rates'!$D$53,'Reference Rates'!$B$52+(T8-'Reference Rates'!$D$52)*'Reference Rates'!$C$52,IF(T8<='Reference Rates'!$D$54,'Reference Rates'!$B$53+(T8-'Reference Rates'!$D$53)*'Reference Rates'!$C$53,IF(T8<='Reference Rates'!$D$55,'Reference Rates'!$B$54+(T8-'Reference Rates'!$D$54)*'Reference Rates'!$C$54,'Reference Rates'!$B$55+(T8-'Reference Rates'!$D$55)*'Reference Rates'!$C$55))))) -> 0 | V8: =S8+U8 -> 1583.25 | W8: =L8+M8+N8-V8 -> 18046.75 | X8: =O8*'Reference Rates'!$B$28 -> 1850 | Y8: =IF(O8<'Reference Rates'!$B$31,'Reference Rates'!$B$32,'Reference Rates'!$B$33) -> 30 | Z8: =MIN(MAX(L8,'Reference Rates'!$B$39),'Reference Rates'!$B$40)*'Reference Rates'!$B$38 -> 458.25 | AA8: =MIN(L8,'Reference Rates'!$B$46)*'Reference Rates'!$B$45 -> 200 | AB8: =X8+Y8+Z8+AA8 -> 2538.25 | AC8: =L8+M8+N8+AB8 -> 22168.25
A9: ='Aug 2026'!A9 -> EMP-004 | B9: =IF('Aug 2026'!B9="","",'Aug 2026'!B9) | C9: ='Aug 2026'!C9 -> Store | D9: ='Aug 2026'!D9 -> Cashier | E9: ='Aug 2026'!E9 -> Y | F9: ='Reference Rates'!$E$14 -> 88.125 | G9: 208 | H9: 4 | I9: 0 | J9: =F9*G9 -> 18330 | K9: =F9*1.25*H9 -> 440.625 | L9: =J9+K9 -> 18770.625 | M9: ='Reference Rates'!$B$19*G9/8 -> 1300 | N9: =I9*IFERROR(INDEX('Reference Rates'!$B$21:$B$22,MATCH(C9,'Reference Rates'!$A$21:$A$22,0)),0) -> 0 | O9: =MIN('Reference Rates'!$B$30,MAX('Reference Rates'!$B$29,MROUND(L9,500))) -> 19000 | P9: =O9*'Reference Rates'!$B$27 -> 950 | Q9: =MIN(MAX(L9,'Reference Rates'!$B$39),'Reference Rates'!$B$40)*'Reference Rates'!$B$37 -> 469.26562 | R9: =MIN(L9,'Reference Rates'!$B$46)*IF(L9>1500,'Reference Rates'!$B$43,'Reference Rates'!$B$44) -> 200 | S9: =P9+Q9+R9 -> 1619.2656 | T9: =IF(E9="Y",0,MAX(0,L9-S9)) -> 0 | U9: =IF(T9<='Reference Rates'!$D$51,0,IF(T9<='Reference Rates'!$D$52,'Reference Rates'!$B$51+(T9-'Reference Rates'!$D$51)*'Reference Rates'!$C$51,IF(T9<='Reference Rates'!$D$53,'Reference Rates'!$B$52+(T9-'Reference Rates'!$D$52)*'Reference Rates'!$C$52,IF(T9<='Reference Rates'!$D$54,'Reference Rates'!$B$53+(T9-'Reference Rates'!$D$53)*'Reference Rates'!$C$53,IF(T9<='Reference Rates'!$D$55,'Reference Rates'!$B$54+(T9-'Reference Rates'!$D$54)*'Reference Rates'!$C$54,'Reference Rates'!$B$55+(T9-'Reference Rates'!$D$55)*'Reference Rates'!$C$55))))) -> 0 | V9: =S9+U9 -> 1619.2656 | W9: =L9+M9+N9-V9 -> 18451.359 | X9: =O9*'Reference Rates'!$B$28 -> 1900 | Y9: =IF(O9<'Reference Rates'!$B$31,'Reference Rates'!$B$32,'Reference Rates'!$B$33) -> 30 | Z9: =MIN(MAX(L9,'Reference Rates'!$B$39),'Reference Rates'!$B$40)*'Reference Rates'!$B$38 -> 469.26562 | AA9: =MIN(L9,'Reference Rates'!$B$46)*'Reference Rates'!$B$45 -> 200 | AB9: =X9+Y9+Z9+AA9 -> 2599.2656 | AC9: =L9+M9+N9+AB9 -> 22669.891
A10: ='Aug 2026'!A10 -> EMP-005 | B10: =IF('Aug 2026'!B10="","",'Aug 2026'!B10) | C10: ='Aug 2026'!C10 -> Store | D10: ='Aug 2026'!D10 -> Sales Clerk | E10: ='Aug 2026'!E10 -> Y | F10: ='Reference Rates'!$E$14 -> 88.125 | G10: 208 | H10: 0 | I10: 0 | J10: =F10*G10 -> 18330 | K10: =F10*1.25*H10 -> 0 | L10: =J10+K10 -> 18330 | M10: ='Reference Rates'!$B$19*G10/8 -> 1300 | N10: =I10*IFERROR(INDEX('Reference Rates'!$B$21:$B$22,MATCH(C10,'Reference Rates'!$A$21:$A$22,0)),0) -> 0 | O10: =MIN('Reference Rates'!$B$30,MAX('Reference Rates'!$B$29,MROUND(L10,500))) -> 18500 | P10: =O10*'Reference Rates'!$B$27 -> 925 | Q10: =MIN(MAX(L10,'Reference Rates'!$B$39),'Reference Rates'!$B$40)*'Reference Rates'!$B$37 -> 458.25 | R10: =MIN(L10,'Reference Rates'!$B$46)*IF(L10>1500,'Reference Rates'!$B$43,'Reference Rates'!$B$44) -> 200 | S10: =P10+Q10+R10 -> 1583.25 | T10: =IF(E10="Y",0,MAX(0,L10-S10)) -> 0 | U10: =IF(T10<='Reference Rates'!$D$51,0,IF(T10<='Reference Rates'!$D$52,'Reference Rates'!$B$51+(T10-'Reference Rates'!$D$51)*'Reference Rates'!$C$51,IF(T10<='Reference Rates'!$D$53,'Reference Rates'!$B$52+(T10-'Reference Rates'!$D$52)*'Reference Rates'!$C$52,IF(T10<='Reference Rates'!$D$54,'Reference Rates'!$B$53+(T10-'Reference Rates'!$D$53)*'Reference Rates'!$C$53,IF(T10<='Reference Rates'!$D$55,'Reference Rates'!$B$54+(T10-'Reference Rates'!$D$54)*'Reference Rates'!$C$54,'Reference Rates'!$B$55+(T10-'Reference Rates'!$D$55)*'Reference Rates'!$C$55))))) -> 0 | V10: =S10+U10 -> 1583.25 | W10: =L10+M10+N10-V10 -> 18046.75 | X10: =O10*'Reference Rates'!$B$28 -> 1850 | Y10: =IF(O10<'Reference Rates'!$B$31,'Reference Rates'!$B$32,'Reference Rates'!$B$33) -> 30 | Z10: =MIN(MAX(L10,'Reference Rates'!$B$39),'Reference Rates'!$B$40)*'Reference Rates'!$B$38 -> 458.25 | AA10: =MIN(L10,'Reference Rates'!$B$46)*'Reference Rates'!$B$45 -> 200 | AB10: =X10+Y10+Z10+AA10 -> 2538.25 | AC10: =L10+M10+N10+AB10 -> 22168.25
A11: ='Aug 2026'!A11 -> EMP-006 | B11: =IF('Aug 2026'!B11="","",'Aug 2026'!B11) | C11: ='Aug 2026'!C11 -> Store | D11: ='Aug 2026'!D11 -> Sales Clerk | E11: ='Aug 2026'!E11 -> Y | F11: ='Reference Rates'!$E$14 -> 88.125 | G11: 208 | H11: 0 | I11: 0 | J11: =F11*G11 -> 18330 | K11: =F11*1.25*H11 -> 0 | L11: =J11+K11 -> 18330 | M11: ='Reference Rates'!$B$19*G11/8 -> 1300 | N11: =I11*IFERROR(INDEX('Reference Rates'!$B$21:$B$22,MATCH(C11,'Reference Rates'!$A$21:$A$22,0)),0) -> 0 | O11: =MIN('Reference Rates'!$B$30,MAX('Reference Rates'!$B$29,MROUND(L11,500))) -> 18500 | P11: =O11*'Reference Rates'!$B$27 -> 925 | Q11: =MIN(MAX(L11,'Reference Rates'!$B$39),'Reference Rates'!$B$40)*'Reference Rates'!$B$37 -> 458.25 | R11: =MIN(L11,'Reference Rates'!$B$46)*IF(L11>1500,'Reference Rates'!$B$43,'Reference Rates'!$B$44) -> 200 | S11: =P11+Q11+R11 -> 1583.25 | T11: =IF(E11="Y",0,MAX(0,L11-S11)) -> 0 | U11: =IF(T11<='Reference Rates'!$D$51,0,IF(T11<='Reference Rates'!$D$52,'Reference Rates'!$B$51+(T11-'Reference Rates'!$D$51)*'Reference Rates'!$C$51,IF(T11<='Reference Rates'!$D$53,'Reference Rates'!$B$52+(T11-'Reference Rates'!$D$52)*'Reference Rates'!$C$52,IF(T11<='Reference Rates'!$D$54,'Reference Rates'!$B$53+(T11-'Reference Rates'!$D$53)*'Reference Rates'!$C$53,IF(T11<='Reference Rates'!$D$55,'Reference Rates'!$B$54+(T11-'Reference Rates'!$D$54)*'Reference Rates'!$C$54,'Reference Rates'!$B$55+(T11-'Reference Rates'!$D$55)*'Reference Rates'!$C$55))))) -> 0 | V11: =S11+U11 -> 1583.25 | W11: =L11+M11+N11-V11 -> 18046.75 | X11: =O11*'Reference Rates'!$B$28 -> 1850 | Y11: =IF(O11<'Reference Rates'!$B$31,'Reference Rates'!$B$32,'Reference Rates'!$B$33) -> 30 | Z11: =MIN(MAX(L11,'Reference Rates'!$B$39),'Reference Rates'!$B$40)*'Reference Rates'!$B$38 -> 458.25 | AA11: =MIN(L11,'Reference Rates'!$B$46)*'Reference Rates'!$B$45 -> 200 | AB11: =X11+Y11+Z11+AA11 -> 2538.25 | AC11: =L11+M11+N11+AB11 -> 22168.25
A12: ='Aug 2026'!A12 -> EMP-007 | B12: =IF('Aug 2026'!B12="","",'Aug 2026'!B12) | C12: ='Aug 2026'!C12 -> Store | D12: ='Aug 2026'!D12 -> Sales Clerk | E12: ='Aug 2026'!E12 -> Y | F12: ='Reference Rates'!$E$14 -> 88.125 | G12: 200 | H12: 0 | I12: 0 | J12: =F12*G12 -> 17625 | K12: =F12*1.25*H12 -> 0 | L12: =J12+K12 -> 17625 | M12: ='Reference Rates'!$B$19*G12/8 -> 1250 | N12: =I12*IFERROR(INDEX('Reference Rates'!$B$21:$B$22,MATCH(C12,'Reference Rates'!$A$21:$A$22,0)),0) -> 0 | O12: =MIN('Reference Rates'!$B$30,MAX('Reference Rates'!$B$29,MROUND(L12,500))) -> 17500 | P12: =O12*'Reference Rates'!$B$27 -> 875 | Q12: =MIN(MAX(L12,'Reference Rates'!$B$39),'Reference Rates'!$B$40)*'Reference Rates'!$B$37 -> 440.625 | R12: =MIN(L12,'Reference Rates'!$B$46)*IF(L12>1500,'Reference Rates'!$B$43,'Reference Rates'!$B$44) -> 200 | S12: =P12+Q12+R12 -> 1515.625 | T12: =IF(E12="Y",0,MAX(0,L12-S12)) -> 0 | U12: =IF(T12<='Reference Rates'!$D$51,0,IF(T12<='Reference Rates'!$D$52,'Reference Rates'!$B$51+(T12-'Reference Rates'!$D$51)*'Reference Rates'!$C$51,IF(T12<='Reference Rates'!$D$53,'Reference Rates'!$B$52+(T12-'Reference Rates'!$D$52)*'Reference Rates'!$C$52,IF(T12<='Reference Rates'!$D$54,'Reference Rates'!$B$53+(T12-'Reference Rates'!$D$53)*'Reference Rates'!$C$53,IF(T12<='Reference Rates'!$D$55,'Reference Rates'!$B$54+(T12-'Reference Rates'!$D$54)*'Reference Rates'!$C$54,'Reference Rates'!$B$55+(T12-'Reference Rates'!$D$55)*'Reference Rates'!$C$55))))) -> 0 | V12: =S12+U12 -> 1515.625 | W12: =L12+M12+N12-V12 -> 17359.375 | X12: =O12*'Reference Rates'!$B$28 -> 1750 | Y12: =IF(O12<'Reference Rates'!$B$31,'Reference Rates'!$B$32,'Reference Rates'!$B$33) -> 30 | Z12: =MIN(MAX(L12,'Reference Rates'!$B$39),'Reference Rates'!$B$40)*'Reference Rates'!$B$38 -> 440.625 | AA12: =MIN(L12,'Reference Rates'!$B$46)*'Reference Rates'!$B$45 -> 200 | AB12: =X12+Y12+Z12+AA12 -> 2420.625 | AC12: =L12+M12+N12+AB12 -> 21295.625
A13: ='Aug 2026'!A13 -> EMP-008 | B13: =IF('Aug 2026'!B13="","",'Aug 2026'!B13) | C13: ='Aug 2026'!C13 -> Store | D13: ='Aug 2026'!D13 -> Sales Clerk | E13: ='Aug 2026'!E13 -> Y | F13: ='Reference Rates'!$E$14 -> 88.125 | G13: 208 | H13: 5 | I13: 0 | J13: =F13*G13 -> 18330 | K13: =F13*1.25*H13 -> 550.78125 | L13: =J13+K13 -> 18880.781 | M13: ='Reference Rates'!$B$19*G13/8 -> 1300 | N13: =I13*IFERROR(INDEX('Reference Rates'!$B$21:$B$22,MATCH(C13,'Reference Rates'!$A$21:$A$22,0)),0) -> 0 | O13: =MIN('Reference Rates'!$B$30,MAX('Reference Rates'!$B$29,MROUND(L13,500))) -> 19000 | P13: =O13*'Reference Rates'!$B$27 -> 950 | Q13: =MIN(MAX(L13,'Reference Rates'!$B$39),'Reference Rates'!$B$40)*'Reference Rates'!$B$37 -> 472.01953 | R13: =MIN(L13,'Reference Rates'!$B$46)*IF(L13>1500,'Reference Rates'!$B$43,'Reference Rates'!$B$44) -> 200 | S13: =P13+Q13+R13 -> 1622.0195 | T13: =IF(E13="Y",0,MAX(0,L13-S13)) -> 0 | U13: =IF(T13<='Reference Rates'!$D$51,0,IF(T13<='Reference Rates'!$D$52,'Reference Rates'!$B$51+(T13-'Reference Rates'!$D$51)*'Reference Rates'!$C$51,IF(T13<='Reference Rates'!$D$53,'Reference Rates'!$B$52+(T13-'Reference Rates'!$D$52)*'Reference Rates'!$C$52,IF(T13<='Reference Rates'!$D$54,'Reference Rates'!$B$53+(T13-'Reference Rates'!$D$53)*'Reference Rates'!$C$53,IF(T13<='Reference Rates'!$D$55,'Reference Rates'!$B$54+(T13-'Reference Rates'!$D$54)*'Reference Rates'!$C$54,'Reference Rates'!$B$55+(T13-'Reference Rates'!$D$55)*'Reference Rates'!$C$55))))) -> 0 | V13: =S13+U13 -> 1622.0195 | W13: =L13+M13+N13-V13 -> 18558.762 | X13: =O13*'Reference Rates'!$B$28 -> 1900 | Y13: =IF(O13<'Reference Rates'!$B$31,'Reference Rates'!$B$32,'Reference Rates'!$B$33) -> 30 | Z13: =MIN(MAX(L13,'Reference Rates'!$B$39),'Reference Rates'!$B$40)*'Reference Rates'!$B$38 -> 472.01953 | AA13: =MIN(L13,'Reference Rates'!$B$46)*'Reference Rates'!$B$45 -> 200 | AB13: =X13+Y13+Z13+AA13 -> 2602.0195 | AC13: =L13+M13+N13+AB13 -> 22782.801
A14: ='Aug 2026'!A14 -> EMP-009 | B14: =IF('Aug 2026'!B14="","",'Aug 2026'!B14) | C14: ='Aug 2026'!C14 -> Store | D14: ='Aug 2026'!D14 -> Sales Clerk | E14: ='Aug 2026'!E14 -> Y | F14: ='Reference Rates'!$E$14 -> 88.125 | G14: 200 | H14: 7 | I14: 0 | J14: =F14*G14 -> 17625 | K14: =F14*1.25*H14 -> 771.09375 | L14: =J14+K14 -> 18396.094 | M14: ='Reference Rates'!$B$19*G14/8 -> 1250 | N14: =I14*IFERROR(INDEX('Reference Rates'!$B$21:$B$22,MATCH(C14,'Reference Rates'!$A$21:$A$22,0)),0) -> 0 | O14: =MIN('Reference Rates'!$B$30,MAX('Reference Rates'!$B$29,MROUND(L14,500))) -> 18500 | P14: =O14*'Reference Rates'!$B$27 -> 925 | Q14: =MIN(MAX(L14,'Reference Rates'!$B$39),'Reference Rates'!$B$40)*'Reference Rates'!$B$37 -> 459.90234 | R14: =MIN(L14,'Reference Rates'!$B$46)*IF(L14>1500,'Reference Rates'!$B$43,'Reference Rates'!$B$44) -> 200 | S14: =P14+Q14+R14 -> 1584.9023 | T14: =IF(E14="Y",0,MAX(0,L14-S14)) -> 0 | U14: =IF(T14<='Reference Rates'!$D$51,0,IF(T14<='Reference Rates'!$D$52,'Reference Rates'!$B$51+(T14-'Reference Rates'!$D$51)*'Reference Rates'!$C$51,IF(T14<='Reference Rates'!$D$53,'Reference Rates'!$B$52+(T14-'Reference Rates'!$D$52)*'Reference Rates'!$C$52,IF(T14<='Reference Rates'!$D$54,'Reference Rates'!$B$53+(T14-'Reference Rates'!$D$53)*'Reference Rates'!$C$53,IF(T14<='Reference Rates'!$D$55,'Reference Rates'!$B$54+(T14-'Reference Rates'!$D$54)*'Reference Rates'!$C$54,'Reference Rates'!$B$55+(T14-'Reference Rates'!$D$55)*'Reference Rates'!$C$55))))) -> 0 | V14: =S14+U14 -> 1584.9023 | W14: =L14+M14+N14-V14 -> 18061.191 | X14: =O14*'Reference Rates'!$B$28 -> 1850 | Y14: =IF(O14<'Reference Rates'!$B$31,'Reference Rates'!$B$32,'Reference Rates'!$B$33) -> 30 | Z14: =MIN(MAX(L14,'Reference Rates'!$B$39),'Reference Rates'!$B$40)*'Reference Rates'!$B$38 -> 459.90234 | AA14: =MIN(L14,'Reference Rates'!$B$46)*'Reference Rates'!$B$45 -> 200 | AB14: =X14+Y14+Z14+AA14 -> 2539.9023 | AC14: =L14+M14+N14+AB14 -> 22185.996
A15: ='Aug 2026'!A15 -> EMP-010 | B15: =IF('Aug 2026'!B15="","",'Aug 2026'!B15) | C15: ='Aug 2026'!C15 -> Store | D15: ='Aug 2026'!D15 -> Section Attendant (Frozen / Egg) | E15: ='Aug 2026'!E15 -> Y | F15: ='Reference Rates'!$E$14 -> 88.125 | G15: 208 | H15: 5 | I15: 0 | J15: =F15*G15 -> 18330 | K15: =F15*1.25*H15 -> 550.78125 | L15: =J15+K15 -> 18880.781 | M15: ='Reference Rates'!$B$19*G15/8 -> 1300 | N15: =I15*IFERROR(INDEX('Reference Rates'!$B$21:$B$22,MATCH(C15,'Reference Rates'!$A$21:$A$22,0)),0) -> 0 | O15: =MIN('Reference Rates'!$B$30,MAX('Reference Rates'!$B$29,MROUND(L15,500))) -> 19000 | P15: =O15*'Reference Rates'!$B$27 -> 950 | Q15: =MIN(MAX(L15,'Reference Rates'!$B$39),'Reference Rates'!$B$40)*'Reference Rates'!$B$37 -> 472.01953 | R15: =MIN(L15,'Reference Rates'!$B$46)*IF(L15>1500,'Reference Rates'!$B$43,'Reference Rates'!$B$44) -> 200 | S15: =P15+Q15+R15 -> 1622.0195 | T15: =IF(E15="Y",0,MAX(0,L15-S15)) -> 0 | U15: =IF(T15<='Reference Rates'!$D$51,0,IF(T15<='Reference Rates'!$D$52,'Reference Rates'!$B$51+(T15-'Reference Rates'!$D$51)*'Reference Rates'!$C$51,IF(T15<='Reference Rates'!$D$53,'Reference Rates'!$B$52+(T15-'Reference Rates'!$D$52)*'Reference Rates'!$C$52,IF(T15<='Reference Rates'!$D$54,'Reference Rates'!$B$53+(T15-'Reference Rates'!$D$53)*'Reference Rates'!$C$53,IF(T15<='Reference Rates'!$D$55,'Reference Rates'!$B$54+(T15-'Reference Rates'!$D$54)*'Reference Rates'!$C$54,'Reference Rates'!$B$55+(T15-'Reference Rates'!$D$55)*'Reference Rates'!$C$55))))) -> 0 | V15: =S15+U15 -> 1622.0195 | W15: =L15+M15+N15-V15 -> 18558.762 | X15: =O15*'Reference Rates'!$B$28 -> 1900 | Y15: =IF(O15<'Reference Rates'!$B$31,'Reference Rates'!$B$32,'Reference Rates'!$B$33) -> 30 | Z15: =MIN(MAX(L15,'Reference Rates'!$B$39),'Reference Rates'!$B$40)*'Reference Rates'!$B$38 -> 472.01953 | AA15: =MIN(L15,'Reference Rates'!$B$46)*'Reference Rates'!$B$45 -> 200 | AB15: =X15+Y15+Z15+AA15 -> 2602.0195 | AC15: =L15+M15+N15+AB15 -> 22782.801
A16: ='Aug 2026'!A16 -> EMP-011 | B16: =IF('Aug 2026'!B16="","",'Aug 2026'!B16) | C16: ='Aug 2026'!C16 -> Store | D16: ='Aug 2026'!D16 -> Section Attendant (Frozen / Egg) | E16: ='Aug 2026'!E16 -> Y | F16: ='Reference Rates'!$E$14 -> 88.125 | G16: 208 | H16: 0 | I16: 0 | J16: =F16*G16 -> 18330 | K16: =F16*1.25*H16 -> 0 | L16: =J16+K16 -> 18330 | M16: ='Reference Rates'!$B$19*G16/8 -> 1300 | N16: =I16*IFERROR(INDEX('Reference Rates'!$B$21:$B$22,MATCH(C16,'Reference Rates'!$A$21:$A$22,0)),0) -> 0 | O16: =MIN('Reference Rates'!$B$30,MAX('Reference Rates'!$B$29,MROUND(L16,500))) -> 18500 | P16: =O16*'Reference Rates'!$B$27 -> 925 | Q16: =MIN(MAX(L16,'Reference Rates'!$B$39),'Reference Rates'!$B$40)*'Reference Rates'!$B$37 -> 458.25 | R16: =MIN(L16,'Reference Rates'!$B$46)*IF(L16>1500,'Reference Rates'!$B$43,'Reference Rates'!$B$44) -> 200 | S16: =P16+Q16+R16 -> 1583.25 | T16: =IF(E16="Y",0,MAX(0,L16-S16)) -> 0 | U16: =IF(T16<='Reference Rates'!$D$51,0,IF(T16<='Reference Rates'!$D$52,'Reference Rates'!$B$51+(T16-'Reference Rates'!$D$51)*'Reference Rates'!$C$51,IF(T16<='Reference Rates'!$D$53,'Reference Rates'!$B$52+(T16-'Reference Rates'!$D$52)*'Reference Rates'!$C$52,IF(T16<='Reference Rates'!$D$54,'Reference Rates'!$B$53+(T16-'Reference Rates'!$D$53)*'Reference Rates'!$C$53,IF(T16<='Reference Rates'!$D$55,'Reference Rates'!$B$54+(T16-'Reference Rates'!$D$54)*'Reference Rates'!$C$54,'Reference Rates'!$B$55+(T16-'Reference Rates'!$D$55)*'Reference Rates'!$C$55))))) -> 0 | V16: =S16+U16 -> 1583.25 | W16: =L16+M16+N16-V16 -> 18046.75 | X16: =O16*'Reference Rates'!$B$28 -> 1850 | Y16: =IF(O16<'Reference Rates'!$B$31,'Reference Rates'!$B$32,'Reference Rates'!$B$33) -> 30 | Z16: =MIN(MAX(L16,'Reference Rates'!$B$39),'Reference Rates'!$B$40)*'Reference Rates'!$B$38 -> 458.25 | AA16: =MIN(L16,'Reference Rates'!$B$46)*'Reference Rates'!$B$45 -> 200 | AB16: =X16+Y16+Z16+AA16 -> 2538.25 | AC16: =L16+M16+N16+AB16 -> 22168.25
A17: ='Aug 2026'!A17 -> EMP-012 | B17: =IF('Aug 2026'!B17="","",'Aug 2026'!B17) | C17: ='Aug 2026'!C17 -> Store | D17: ='Aug 2026'!D17 -> Section Attendant (Frozen / Egg) | E17: ='Aug 2026'!E17 -> Y | F17: ='Reference Rates'!$E$14 -> 88.125 | G17: 208 | H17: 0 | I17: 0 | J17: =F17*G17 -> 18330 | K17: =F17*1.25*H17 -> 0 | L17: =J17+K17 -> 18330 | M17: ='Reference Rates'!$B$19*G17/8 -> 1300 | N17: =I17*IFERROR(INDEX('Reference Rates'!$B$21:$B$22,MATCH(C17,'Reference Rates'!$A$21:$A$22,0)),0) -> 0 | O17: =MIN('Reference Rates'!$B$30,MAX('Reference Rates'!$B$29,MROUND(L17,500))) -> 18500 | P17: =O17*'Reference Rates'!$B$27 -> 925 | Q17: =MIN(MAX(L17,'Reference Rates'!$B$39),'Reference Rates'!$B$40)*'Reference Rates'!$B$37 -> 458.25 | R17: =MIN(L17,'Reference Rates'!$B$46)*IF(L17>1500,'Reference Rates'!$B$43,'Reference Rates'!$B$44) -> 200 | S17: =P17+Q17+R17 -> 1583.25 | T17: =IF(E17="Y",0,MAX(0,L17-S17)) -> 0 | U17: =IF(T17<='Reference Rates'!$D$51,0,IF(T17<='Reference Rates'!$D$52,'Reference Rates'!$B$51+(T17-'Reference Rates'!$D$51)*'Reference Rates'!$C$51,IF(T17<='Reference Rates'!$D$53,'Reference Rates'!$B$52+(T17-'Reference Rates'!$D$52)*'Reference Rates'!$C$52,IF(T17<='Reference Rates'!$D$54,'Reference Rates'!$B$53+(T17-'Reference Rates'!$D$53)*'Reference Rates'!$C$53,IF(T17<='Reference Rates'!$D$55,'Reference Rates'!$B$54+(T17-'Reference Rates'!$D$54)*'Reference Rates'!$C$54,'Reference Rates'!$B$55+(T17-'Reference Rates'!$D$55)*'Reference Rates'!$C$55))))) -> 0 | V17: =S17+U17 -> 1583.25 | W17: =L17+M17+N17-V17 -> 18046.75 | X17: =O17*'Reference Rates'!$B$28 -> 1850 | Y17: =IF(O17<'Reference Rates'!$B$31,'Reference Rates'!$B$32,'Reference Rates'!$B$33) -> 30 | Z17: =MIN(MAX(L17,'Reference Rates'!$B$39),'Reference Rates'!$B$40)*'Reference Rates'!$B$38 -> 458.25 | AA17: =MIN(L17,'Reference Rates'!$B$46)*'Reference Rates'!$B$45 -> 200 | AB17: =X17+Y17+Z17+AA17 -> 2538.25 | AC17: =L17+M17+N17+AB17 -> 22168.25
... A25: ='Aug 2026'!A25 -> EMP-020 | B25: =IF('Aug 2026'!B25="","",'Aug 2026'!B25) | C25: ='Aug 2026'!C25 -> Warehouse | D25: ='Aug 2026'!D25 -> Inventory Clerk | E25: ='Aug 2026'!E25 -> Y | F25: ='Reference Rates'!$E$14 -> 88.125 | G25: 200 | H25: 13 | I25: 0 | J25: =F25*G25 -> 17625 | K25: =F25*1.25*H25 -> 1432.0312 | L25: =J25+K25 -> 19057.031 | M25: ='Reference Rates'!$B$19*G25/8 -> 1250 | N25: =I25*IFERROR(INDEX('Reference Rates'!$B$21:$B$22,MATCH(C25,'Reference Rates'!$A$21:$A$22,0)),0) -> 0 | O25: =MIN('Reference Rates'!$B$30,MAX('Reference Rates'!$B$29,MROUND(L25,500))) -> 19000 | P25: =O25*'Reference Rates'!$B$27 -> 950 | Q25: =MIN(MAX(L25,'Reference Rates'!$B$39),'Reference Rates'!$B$40)*'Reference Rates'!$B$37 -> 476.42578 | R25: =MIN(L25,'Reference Rates'!$B$46)*IF(L25>1500,'Reference Rates'!$B$43,'Reference Rates'!$B$44) -> 200 | S25: =P25+Q25+R25 -> 1626.4258 | T25: =IF(E25="Y",0,MAX(0,L25-S25)) -> 0 | U25: =IF(T25<='Reference Rates'!$D$51,0,IF(T25<='Reference Rates'!$D$52,'Reference Rates'!$B$51+(T25-'Reference Rates'!$D$51)*'Reference Rates'!$C$51,IF(T25<='Reference Rates'!$D$53,'Reference Rates'!$B$52+(T25-'Reference Rates'!$D$52)*'Reference Rates'!$C$52,IF(T25<='Reference Rates'!$D$54,'Reference Rates'!$B$53+(T25-'Reference Rates'!$D$53)*'Reference Rates'!$C$53,IF(T25<='Reference Rates'!$D$55,'Reference Rates'!$B$54+(T25-'Reference Rates'!$D$54)*'Reference Rates'!$C$54,'Reference Rates'!$B$55+(T25-'Reference Rates'!$D$55)*'Reference Rates'!$C$55))))) -> 0 | V25: =S25+U25 -> 1626.4258 | W25: =L25+M25+N25-V25 -> 18680.605 | X25: =O25*'Reference Rates'!$B$28 -> 1900 | Y25: =IF(O25<'Reference Rates'!$B$31,'Reference Rates'!$B$32,'Reference Rates'!$B$33) -> 30 | Z25: =MIN(MAX(L25,'Reference Rates'!$B$39),'Reference Rates'!$B$40)*'Reference Rates'!$B$38 -> 476.42578 | AA25: =MIN(L25,'Reference Rates'!$B$46)*'Reference Rates'!$B$45 -> 200 | AB25: =X25+Y25+Z25+AA25 -> 2606.4258 | AC25: =L25+M25+N25+AB25 -> 22913.457
A26: ='Aug 2026'!A26 -> EMP-021 | B26: =IF('Aug 2026'!B26="","",'Aug 2026'!B26) -> Joshua Cedric D. Cortez | C26: ='Aug 2026'!C26 -> Delivery – Luzon | D26: ='Aug 2026'!D26 -> Delivery Driver – Luzon Routes | E26: ='Aug 2026'!E26 -> N | F26: ='Aug 2026'!F26 -> 100 | G26: 200 | H26: 13 | I26: 9 | J26: =F26*G26 -> 20000 | K26: =F26*1.25*H26 -> 1625 | L26: =J26+K26 -> 21625 | M26: ='Reference Rates'!$B$19*G26/8 -> 1250 | N26: =I26*IFERROR(INDEX('Reference Rates'!$B$21:$B$22,MATCH(C26,'Reference Rates'!$A$21:$A$22,0)),0) -> 4500 | O26: =MIN('Reference Rates'!$B$30,MAX('Reference Rates'!$B$29,MROUND(L26,500))) -> 21500 | P26: =O26*'Reference Rates'!$B$27 -> 1075 | Q26: =MIN(MAX(L26,'Reference Rates'!$B$39),'Reference Rates'!$B$40)*'Reference Rates'!$B$37 -> 540.625 | R26: =MIN(L26,'Reference Rates'!$B$46)*IF(L26>1500,'Reference Rates'!$B$43,'Reference Rates'!$B$44) -> 200 | S26: =P26+Q26+R26 -> 1815.625 | T26: =IF(E26="Y",0,MAX(0,L26-S26)) -> 19809.375 | U26: =IF(T26<='Reference Rates'!$D$51,0,IF(T26<='Reference Rates'!$D$52,'Reference Rates'!$B$51+(T26-'Reference Rates'!$D$51)*'Reference Rates'!$C$51,IF(T26<='Reference Rates'!$D$53,'Reference Rates'!$B$52+(T26-'Reference Rates'!$D$52)*'Reference Rates'!$C$52,IF(T26<='Reference Rates'!$D$54,'Reference Rates'!$B$53+(T26-'Reference Rates'!$D$53)*'Reference Rates'!$C$53,IF(T26<='Reference Rates'!$D$55,'Reference Rates'!$B$54+(T26-'Reference Rates'!$D$54)*'Reference Rates'!$C$54,'Reference Rates'!$B$55+(T26-'Reference Rates'!$D$55)*'Reference Rates'!$C$55))))) -> 0 | V26: =S26+U26 -> 1815.625 | W26: =L26+M26+N26-V26 -> 25559.375 | X26: =O26*'Reference Rates'!$B$28 -> 2150 | Y26: =IF(O26<'Reference Rates'!$B$31,'Reference Rates'!$B$32,'Reference Rates'!$B$33) -> 30 | Z26: =MIN(MAX(L26,'Reference Rates'!$B$39),'Reference Rates'!$B$40)*'Reference Rates'!$B$38 -> 540.625 | AA26: =MIN(L26,'Reference Rates'!$B$46)*'Reference Rates'!$B$45 -> 200 | AB26: =X26+Y26+Z26+AA26 -> 2920.625 | AC26: =L26+M26+N26+AB26 -> 30295.625
A27: ='Aug 2026'!A27 -> EMP-022 | B27: =IF('Aug 2026'!B27="","",'Aug 2026'!B27) | C27: ='Aug 2026'!C27 -> Delivery – Luzon | D27: ='Aug 2026'!D27 -> Delivery Driver – Luzon Routes | E27: ='Aug 2026'!E27 -> N | F27: ='Aug 2026'!F27 -> 105 | G27: 208 | H27: 17 | I27: 10 | J27: =F27*G27 -> 21840 | K27: =F27*1.25*H27 -> 2231.25 | L27: =J27+K27 -> 24071.25 | M27: ='Reference Rates'!$B$19*G27/8 -> 1300 | N27: =I27*IFERROR(INDEX('Reference Rates'!$B$21:$B$22,MATCH(C27,'Reference Rates'!$A$21:$A$22,0)),0) -> 5000 | O27: =MIN('Reference Rates'!$B$30,MAX('Reference Rates'!$B$29,MROUND(L27,500))) -> 24000 | P27: =O27*'Reference Rates'!$B$27 -> 1200 | Q27: =MIN(MAX(L27,'Reference Rates'!$B$39),'Reference Rates'!$B$40)*'Reference Rates'!$B$37 -> 601.78125 | R27: =MIN(L27,'Reference Rates'!$B$46)*IF(L27>1500,'Reference Rates'!$B$43,'Reference Rates'!$B$44) -> 200 | S27: =P27+Q27+R27 -> 2001.7812 | T27: =IF(E27="Y",0,MAX(0,L27-S27)) -> 22069.469 | U27: =IF(T27<='Reference Rates'!$D$51,0,IF(T27<='Reference Rates'!$D$52,'Reference Rates'!$B$51+(T27-'Reference Rates'!$D$51)*'Reference Rates'!$C$51,IF(T27<='Reference Rates'!$D$53,'Reference Rates'!$B$52+(T27-'Reference Rates'!$D$52)*'Reference Rates'!$C$52,IF(T27<='Reference Rates'!$D$54,'Reference Rates'!$B$53+(T27-'Reference Rates'!$D$53)*'Reference Rates'!$C$53,IF(T27<='Reference Rates'!$D$55,'Reference Rates'!$B$54+(T27-'Reference Rates'!$D$54)*'Reference Rates'!$C$54,'Reference Rates'!$B$55+(T27-'Reference Rates'!$D$55)*'Reference Rates'!$C$55))))) -> 185.47031 | V27: =S27+U27 -> 2187.2516 | W27: =L27+M27+N27-V27 -> 28183.998 | X27: =O27*'Reference Rates'!$B$28 -> 2400 | Y27: =IF(O27<'Reference Rates'!$B$31,'Reference Rates'!$B$32,'Reference Rates'!$B$33) -> 30 | Z27: =MIN(MAX(L27,'Reference Rates'!$B$39),'Reference Rates'!$B$40)*'Reference Rates'!$B$38 -> 601.78125 | AA27: =MIN(L27,'Reference Rates'!$B$46)*'Reference Rates'!$B$45 -> 200 | AB27: =X27+Y27+Z27+AA27 -> 3231.7812 | AC27: =L27+M27+N27+AB27 -> 33603.031
A28: ='Aug 2026'!A28 -> EMP-023 | B28: =IF('Aug 2026'!B28="","",'Aug 2026'!B28) | C28: ='Aug 2026'!C28 -> Delivery – Luzon | D28: ='Aug 2026'!D28 -> Delivery Driver – Luzon Routes | E28: ='Aug 2026'!E28 -> N | F28: ='Aug 2026'!F28 -> 100 | G28: 208 | H28: 14 | I28: 8 | J28: =F28*G28 -> 20800 | K28: =F28*1.25*H28 -> 1750 | L28: =J28+K28 -> 22550 | M28: ='Reference Rates'!$B$19*G28/8 -> 1300 | N28: =I28*IFERROR(INDEX('Reference Rates'!$B$21:$B$22,MATCH(C28,'Reference Rates'!$A$21:$A$22,0)),0) -> 4000 | O28: =MIN('Reference Rates'!$B$30,MAX('Reference Rates'!$B$29,MROUND(L28,500))) -> 22500 | P28: =O28*'Reference Rates'!$B$27 -> 1125 | Q28: =MIN(MAX(L28,'Reference Rates'!$B$39),'Reference Rates'!$B$40)*'Reference Rates'!$B$37 -> 563.75 | R28: =MIN(L28,'Reference Rates'!$B$46)*IF(L28>1500,'Reference Rates'!$B$43,'Reference Rates'!$B$44) -> 200 | S28: =P28+Q28+R28 -> 1888.75 | T28: =IF(E28="Y",0,MAX(0,L28-S28)) -> 20661.25 | U28: =IF(T28<='Reference Rates'!$D$51,0,IF(T28<='Reference Rates'!$D$52,'Reference Rates'!$B$51+(T28-'Reference Rates'!$D$51)*'Reference Rates'!$C$51,IF(T28<='Reference Rates'!$D$53,'Reference Rates'!$B$52+(T28-'Reference Rates'!$D$52)*'Reference Rates'!$C$52,IF(T28<='Reference Rates'!$D$54,'Reference Rates'!$B$53+(T28-'Reference Rates'!$D$53)*'Reference Rates'!$C$53,IF(T28<='Reference Rates'!$D$55,'Reference Rates'!$B$54+(T28-'Reference Rates'!$D$54)*'Reference Rates'!$C$54,'Reference Rates'!$B$55+(T28-'Reference Rates'!$D$55)*'Reference Rates'!$C$55))))) -> 0 | V28: =S28+U28 -> 1888.75 | W28: =L28+M28+N28-V28 -> 25961.25 | X28: =O28*'Reference Rates'!$B$28 -> 2250 | Y28: =IF(O28<'Reference Rates'!$B$31,'Reference Rates'!$B$32,'Reference Rates'!$B$33) -> 30 | Z28: =MIN(MAX(L28,'Reference Rates'!$B$39),'Reference Rates'!$B$40)*'Reference Rates'!$B$38 -> 563.75 | AA28: =MIN(L28,'Reference Rates'!$B$46)*'Reference Rates'!$B$45 -> 200 | AB28: =X28+Y28+Z28+AA28 -> 3043.75 | AC28: =L28+M28+N28+AB28 -> 30893.75
A29: ='Aug 2026'!A29 -> EMP-024 | B29: =IF('Aug 2026'!B29="","",'Aug 2026'!B29) -> Tristan Judd Mari Magsino | C29: ='Aug 2026'!C29 -> Delivery – Samar | D29: ='Aug 2026'!D29 -> Delivery Driver – Samar Routes | E29: ='Aug 2026'!E29 -> N | F29: ='Aug 2026'!F29 -> 110 | G29: 208 | H29: 22 | I29: 12 | J29: =F29*G29 -> 22880 | K29: =F29*1.25*H29 -> 3025 | L29: =J29+K29 -> 25905 | M29: ='Reference Rates'!$B$19*G29/8 -> 1300 | N29: =I29*IFERROR(INDEX('Reference Rates'!$B$21:$B$22,MATCH(C29,'Reference Rates'!$A$21:$A$22,0)),0) -> 10800 | O29: =MIN('Reference Rates'!$B$30,MAX('Reference Rates'!$B$29,MROUND(L29,500))) -> 26000 | P29: =O29*'Reference Rates'!$B$27 -> 1300 | Q29: =MIN(MAX(L29,'Reference Rates'!$B$39),'Reference Rates'!$B$40)*'Reference Rates'!$B$37 -> 647.625 | R29: =MIN(L29,'Reference Rates'!$B$46)*IF(L29>1500,'Reference Rates'!$B$43,'Reference Rates'!$B$44) -> 200 | S29: =P29+Q29+R29 -> 2147.625 | T29: =IF(E29="Y",0,MAX(0,L29-S29)) -> 23757.375 | U29: =IF(T29<='Reference Rates'!$D$51,0,IF(T29<='Reference Rates'!$D$52,'Reference Rates'!$B$51+(T29-'Reference Rates'!$D$51)*'Reference Rates'!$C$51,IF(T29<='Reference Rates'!$D$53,'Reference Rates'!$B$52+(T29-'Reference Rates'!$D$52)*'Reference Rates'!$C$52,IF(T29<='Reference Rates'!$D$54,'Reference Rates'!$B$53+(T29-'Reference Rates'!$D$53)*'Reference Rates'!$C$53,IF(T29<='Reference Rates'!$D$55,'Reference Rates'!$B$54+(T29-'Reference Rates'!$D$54)*'Reference Rates'!$C$54,'Reference Rates'!$B$55+(T29-'Reference Rates'!$D$55)*'Reference Rates'!$C$55))))) -> 438.65625 | V29: =S29+U29 -> 2586.2812 | W29: =L29+M29+N29-V29 -> 35418.719 | X29: =O29*'Reference Rates'!$B$28 -> 2600 | Y29: =IF(O29<'Reference Rates'!$B$31,'Reference Rates'!$B$32,'Reference Rates'!$B$33) -> 30 | Z29: =MIN(MAX(L29,'Reference Rates'!$B$39),'Reference Rates'!$B$40)*'Reference Rates'!$B$38 -> 647.625 | AA29: =MIN(L29,'Reference Rates'!$B$46)*'Reference Rates'!$B$45 -> 200 | AB29: =X29+Y29+Z29+AA29 -> 3477.625 | AC29: =L29+M29+N29+AB29 -> 41482.625
A30: ='Aug 2026'!A30 -> EMP-025 | B30: =IF('Aug 2026'!B30="","",'Aug 2026'!B30) | C30: ='Aug 2026'!C30 -> Delivery – Samar | D30: ='Aug 2026'!D30 -> Delivery Driver – Samar Routes | E30: ='Aug 2026'!E30 -> N | F30: ='Aug 2026'!F30 -> 115 | G30: 208 | H30: 21 | I30: 11 | J30: =F30*G30 -> 23920 | K30: =F30*1.25*H30 -> 3018.75 | L30: =J30+K30 -> 26938.75 | M30: ='Reference Rates'!$B$19*G30/8 -> 1300 | N30: =I30*IFERROR(INDEX('Reference Rates'!$B$21:$B$22,MATCH(C30,'Reference Rates'!$A$21:$A$22,0)),0) -> 9900 | O30: =MIN('Reference Rates'!$B$30,MAX('Reference Rates'!$B$29,MROUND(L30,500))) -> 27000 | P30: =O30*'Reference Rates'!$B$27 -> 1350 | Q30: =MIN(MAX(L30,'Reference Rates'!$B$39),'Reference Rates'!$B$40)*'Reference Rates'!$B$37 -> 673.46875 | R30: =MIN(L30,'Reference Rates'!$B$46)*IF(L30>1500,'Reference Rates'!$B$43,'Reference Rates'!$B$44) -> 200 | S30: =P30+Q30+R30 -> 2223.4688 | T30: =IF(E30="Y",0,MAX(0,L30-S30)) -> 24715.281 | U30: =IF(T30<='Reference Rates'!$D$51,0,IF(T30<='Reference Rates'!$D$52,'Reference Rates'!$B$51+(T30-'Reference Rates'!$D$51)*'Reference Rates'!$C$51,IF(T30<='Reference Rates'!$D$53,'Reference Rates'!$B$52+(T30-'Reference Rates'!$D$52)*'Reference Rates'!$C$52,IF(T30<='Reference Rates'!$D$54,'Reference Rates'!$B$53+(T30-'Reference Rates'!$D$53)*'Reference Rates'!$C$53,IF(T30<='Reference Rates'!$D$55,'Reference Rates'!$B$54+(T30-'Reference Rates'!$D$54)*'Reference Rates'!$C$54,'Reference Rates'!$B$55+(T30-'Reference Rates'!$D$55)*'Reference Rates'!$C$55))))) -> 582.34219 | V30: =S30+U30 -> 2805.8109 | W30: =L30+M30+N30-V30 -> 35332.939 | X30: =O30*'Reference Rates'!$B$28 -> 2700 | Y30: =IF(O30<'Reference Rates'!$B$31,'Reference Rates'!$B$32,'Reference Rates'!$B$33) -> 30 | Z30: =MIN(MAX(L30,'Reference Rates'!$B$39),'Reference Rates'!$B$40)*'Reference Rates'!$B$38 -> 673.46875 | AA30: =MIN(L30,'Reference Rates'!$B$46)*'Reference Rates'!$B$45 -> 200 | AB30: =X30+Y30+Z30+AA30 -> 3603.4688 | AC30: =L30+M30+N30+AB30 -> 41742.219
A31: ='Aug 2026'!A31 -> EMP-026 | B31: =IF('Aug 2026'!B31="","",'Aug 2026'!B31) | C31: ='Aug 2026'!C31 -> Delivery – Samar | D31: ='Aug 2026'!D31 -> Delivery Driver – Samar Routes | E31: ='Aug 2026'!E31 -> N | F31: ='Aug 2026'!F31 -> 110 | G31: 208 | H31: 24 | I31: 12 | J31: =F31*G31 -> 22880 | K31: =F31*1.25*H31 -> 3300 | L31: =J31+K31 -> 26180 | M31: ='Reference Rates'!$B$19*G31/8 -> 1300 | N31: =I31*IFERROR(INDEX('Reference Rates'!$B$21:$B$22,MATCH(C31,'Reference Rates'!$A$21:$A$22,0)),0) -> 10800 | O31: =MIN('Reference Rates'!$B$30,MAX('Reference Rates'!$B$29,MROUND(L31,500))) -> 26000 | P31: =O31*'Reference Rates'!$B$27 -> 1300 | Q31: =MIN(MAX(L31,'Reference Rates'!$B$39),'Reference Rates'!$B$40)*'Reference Rates'!$B$37 -> 654.5 | R31: =MIN(L31,'Reference Rates'!$B$46)*IF(L31>1500,'Reference Rates'!$B$43,'Reference Rates'!$B$44) -> 200 | S31: =P31+Q31+R31 -> 2154.5 | T31: =IF(E31="Y",0,MAX(0,L31-S31)) -> 24025.5 | U31: =IF(T31<='Reference Rates'!$D$51,0,IF(T31<='Reference Rates'!$D$52,'Reference Rates'!$B$51+(T31-'Reference Rates'!$D$51)*'Reference Rates'!$C$51,IF(T31<='Reference Rates'!$D$53,'Reference Rates'!$B$52+(T31-'Reference Rates'!$D$52)*'Reference Rates'!$C$52,IF(T31<='Reference Rates'!$D$54,'Reference Rates'!$B$53+(T31-'Reference Rates'!$D$53)*'Reference Rates'!$C$53,IF(T31<='Reference Rates'!$D$55,'Reference Rates'!$B$54+(T31-'Reference Rates'!$D$54)*'Reference Rates'!$C$54,'Reference Rates'!$B$55+(T31-'Reference Rates'!$D$55)*'Reference Rates'!$C$55))))) -> 478.875 | V31: =S31+U31 -> 2633.375 | W31: =L31+M31+N31-V31 -> 35646.625 | X31: =O31*'Reference Rates'!$B$28 -> 2600 | Y31: =IF(O31<'Reference Rates'!$B$31,'Reference Rates'!$B$32,'Reference Rates'!$B$33) -> 30 | Z31: =MIN(MAX(L31,'Reference Rates'!$B$39),'Reference Rates'!$B$40)*'Reference Rates'!$B$38 -> 654.5 | AA31: =MIN(L31,'Reference Rates'!$B$46)*'Reference Rates'!$B$45 -> 200 | AB31: =X31+Y31+Z31+AA31 -> 3484.5 | AC31: =L31+M31+N31+AB31 -> 41764.5
A32: ='Aug 2026'!A32 -> EMP-027 | B32: =IF('Aug 2026'!B32="","",'Aug 2026'!B32) | C32: ='Aug 2026'!C32 -> Admin / Supervisory | D32: ='Aug 2026'!D32 -> Store Supervisor | E32: ='Aug 2026'!E32 -> N | F32: ='Aug 2026'!F32 -> 120 | G32: 208 | H32: 0 | I32: 0 | J32: =F32*G32 -> 24960 | K32: =F32*1.25*H32 -> 0 | L32: =J32+K32 -> 24960 | M32: ='Reference Rates'!$B$19*G32/8 -> 1300 | N32: =I32*IFERROR(INDEX('Reference Rates'!$B$21:$B$22,MATCH(C32,'Reference Rates'!$A$21:$A$22,0)),0) -> 0 | O32: =MIN('Reference Rates'!$B$30,MAX('Reference Rates'!$B$29,MROUND(L32,500))) -> 25000 | P32: =O32*'Reference Rates'!$B$27 -> 1250 | Q32: =MIN(MAX(L32,'Reference Rates'!$B$39),'Reference Rates'!$B$40)*'Reference Rates'!$B$37 -> 624 | R32: =MIN(L32,'Reference Rates'!$B$46)*IF(L32>1500,'Reference Rates'!$B$43,'Reference Rates'!$B$44) -> 200 | S32: =P32+Q32+R32 -> 2074 | T32: =IF(E32="Y",0,MAX(0,L32-S32)) -> 22886 | U32: =IF(T32<='Reference Rates'!$D$51,0,IF(T32<='Reference Rates'!$D$52,'Reference Rates'!$B$51+(T32-'Reference Rates'!$D$51)*'Reference Rates'!$C$51,IF(T32<='Reference Rates'!$D$53,'Reference Rates'!$B$52+(T32-'Reference Rates'!$D$52)*'Reference Rates'!$C$52,IF(T32<='Reference Rates'!$D$54,'Reference Rates'!$B$53+(T32-'Reference Rates'!$D$53)*'Reference Rates'!$C$53,IF(T32<='Reference Rates'!$D$55,'Reference Rates'!$B$54+(T32-'Reference Rates'!$D$54)*'Reference Rates'!$C$54,'Reference Rates'!$B$55+(T32-'Reference Rates'!$D$55)*'Reference Rates'!$C$55))))) -> 307.95 | V32: =S32+U32 -> 2381.95 | W32: =L32+M32+N32-V32 -> 23878.05 | X32: =O32*'Reference Rates'!$B$28 -> 2500 | Y32: =IF(O32<'Reference Rates'!$B$31,'Reference Rates'!$B$32,'Reference Rates'!$B$33) -> 30 | Z32: =MIN(MAX(L32,'Reference Rates'!$B$39),'Reference Rates'!$B$40)*'Reference Rates'!$B$38 -> 624 | AA32: =MIN(L32,'Reference Rates'!$B$46)*'Reference Rates'!$B$45 -> 200 | AB32: =X32+Y32+Z32+AA32 -> 3354 | AC32: =L32+M32+N32+AB32 -> 29614
A33: ='Aug 2026'!A33 -> EMP-028 | B33: =IF('Aug 2026'!B33="","",'Aug 2026'!B33) | C33: ='Aug 2026'!C33 -> Admin / Supervisory | D33: ='Aug 2026'!D33 -> Warehouse & Logistics Supervisor | E33: ='Aug 2026'!E33 -> N | F33: ='Aug 2026'!F33 -> 130 | G33: 208 | H33: 0 | I33: 0 | J33: =F33*G33 -> 27040 | K33: =F33*1.25*H33 -> 0 | L33: =J33+K33 -> 27040 | M33: ='Reference Rates'!$B$19*G33/8 -> 1300 | N33: =I33*IFERROR(INDEX('Reference Rates'!$B$21:$B$22,MATCH(C33,'Reference Rates'!$A$21:$A$22,0)),0) -> 0 | O33: =MIN('Reference Rates'!$B$30,MAX('Reference Rates'!$B$29,MROUND(L33,500))) -> 27000 | P33: =O33*'Reference Rates'!$B$27 -> 1350 | Q33: =MIN(MAX(L33,'Reference Rates'!$B$39),'Reference Rates'!$B$40)*'Reference Rates'!$B$37 -> 676 | R33: =MIN(L33,'Reference Rates'!$B$46)*IF(L33>1500,'Reference Rates'!$B$43,'Reference Rates'!$B$44) -> 200 | S33: =P33+Q33+R33 -> 2226 | T33: =IF(E33="Y",0,MAX(0,L33-S33)) -> 24814 | U33: =IF(T33<='Reference Rates'!$D$51,0,IF(T33<='Reference Rates'!$D$52,'Reference Rates'!$B$51+(T33-'Reference Rates'!$D$51)*'Reference Rates'!$C$51,IF(T33<='Reference Rates'!$D$53,'Reference Rates'!$B$52+(T33-'Reference Rates'!$D$52)*'Reference Rates'!$C$52,IF(T33<='Reference Rates'!$D$54,'Reference Rates'!$B$53+(T33-'Reference Rates'!$D$53)*'Reference Rates'!$C$53,IF(T33<='Reference Rates'!$D$55,'Reference Rates'!$B$54+(T33-'Reference Rates'!$D$54)*'Reference Rates'!$C$54,'Reference Rates'!$B$55+(T33-'Reference Rates'!$D$55)*'Reference Rates'!$C$55))))) -> 597.15 | V33: =S33+U33 -> 2823.15 | W33: =L33+M33+N33-V33 -> 25516.85 | X33: =O33*'Reference Rates'!$B$28 -> 2700 | Y33: =IF(O33<'Reference Rates'!$B$31,'Reference Rates'!$B$32,'Reference Rates'!$B$33) -> 30 | Z33: =MIN(MAX(L33,'Reference Rates'!$B$39),'Reference Rates'!$B$40)*'Reference Rates'!$B$38 -> 676 | AA33: =MIN(L33,'Reference Rates'!$B$46)*'Reference Rates'!$B$45 -> 200 | AB33: =X33+Y33+Z33+AA33 -> 3606 | AC33: =L33+M33+N33+AB33 -> 31946
A34: ='Aug 2026'!A34 -> EMP-029 | B34: =IF('Aug 2026'!B34="","",'Aug 2026'!B34) | C34: ='Aug 2026'!C34 -> Admin / Supervisory | D34: ='Aug 2026'!D34 -> Admin & Payroll Officer | E34: ='Aug 2026'!E34 -> N | F34: ='Aug 2026'!F34 -> 140 | G34: 208 | H34: 0 | I34: 0 | J34: =F34*G34 -> 29120 | K34: =F34*1.25*H34 -> 0 | L34: =J34+K34 -> 29120 | M34: ='Reference Rates'!$B$19*G34/8 -> 1300 | N34: =I34*IFERROR(INDEX('Reference Rates'!$B$21:$B$22,MATCH(C34,'Reference Rates'!$A$21:$A$22,0)),0) -> 0 | O34: =MIN('Reference Rates'!$B$30,MAX('Reference Rates'!$B$29,MROUND(L34,500))) -> 29000 | P34: =O34*'Reference Rates'!$B$27 -> 1450 | Q34: =MIN(MAX(L34,'Reference Rates'!$B$39),'Reference Rates'!$B$40)*'Reference Rates'!$B$37 -> 728 | R34: =MIN(L34,'Reference Rates'!$B$46)*IF(L34>1500,'Reference Rates'!$B$43,'Reference Rates'!$B$44) -> 200 | S34: =P34+Q34+R34 -> 2378 | T34: =IF(E34="Y",0,MAX(0,L34-S34)) -> 26742 | U34: =IF(T34<='Reference Rates'!$D$51,0,IF(T34<='Reference Rates'!$D$52,'Reference Rates'!$B$51+(T34-'Reference Rates'!$D$51)*'Reference Rates'!$C$51,IF(T34<='Reference Rates'!$D$53,'Reference Rates'!$B$52+(T34-'Reference Rates'!$D$52)*'Reference Rates'!$C$52,IF(T34<='Reference Rates'!$D$54,'Reference Rates'!$B$53+(T34-'Reference Rates'!$D$53)*'Reference Rates'!$C$53,IF(T34<='Reference Rates'!$D$55,'Reference Rates'!$B$54+(T34-'Reference Rates'!$D$54)*'Reference Rates'!$C$54,'Reference Rates'!$B$55+(T34-'Reference Rates'!$D$55)*'Reference Rates'!$C$55))))) -> 886.35 | V34: =S34+U34 -> 3264.35 | W34: =L34+M34+N34-V34 -> 27155.65 | X34: =O34*'Reference Rates'!$B$28 -> 2900 | Y34: =IF(O34<'Reference Rates'!$B$31,'Reference Rates'!$B$32,'Reference Rates'!$B$33) -> 30 | Z34: =MIN(MAX(L34,'Reference Rates'!$B$39),'Reference Rates'!$B$40)*'Reference Rates'!$B$38 -> 728 | AA34: =MIN(L34,'Reference Rates'!$B$46)*'Reference Rates'!$B$45 -> 200 | AB34: =X34+Y34+Z34+AA34 -> 3858 | AC34: =L34+M34+N34+AB34 -> 34278
A35: ='Aug 2026'!A35 -> EMP-030 | B35: =IF('Aug 2026'!B35="","",'Aug 2026'!B35) -> Johnbel A. Maliñana | C35: ='Aug 2026'!C35 -> Admin / Supervisory | D35: ='Aug 2026'!D35 -> Operations Manager | E35: ='Aug 2026'!E35 -> N | F35: ='Aug 2026'!F35 -> 160 | G35: 208 | H35: 0 | I35: 0 | J35: =F35*G35 -> 33280 | K35: =F35*1.25*H35 -> 0 | L35: =J35+K35 -> 33280 | M35: ='Reference Rates'!$B$19*G35/8 -> 1300 | N35: =I35*IFERROR(INDEX('Reference Rates'!$B$21:$B$22,MATCH(C35,'Reference Rates'!$A$21:$A$22,0)),0) -> 0 | O35: =MIN('Reference Rates'!$B$30,MAX('Reference Rates'!$B$29,MROUND(L35,500))) -> 33500 | P35: =O35*'Reference Rates'!$B$27 -> 1675 | Q35: =MIN(MAX(L35,'Reference Rates'!$B$39),'Reference Rates'!$B$40)*'Reference Rates'!$B$37 -> 832 | R35: =MIN(L35,'Reference Rates'!$B$46)*IF(L35>1500,'Reference Rates'!$B$43,'Reference Rates'!$B$44) -> 200 | S35: =P35+Q35+R35 -> 2707 | T35: =IF(E35="Y",0,MAX(0,L35-S35)) -> 30573 | U35: =IF(T35<='Reference Rates'!$D$51,0,IF(T35<='Reference Rates'!$D$52,'Reference Rates'!$B$51+(T35-'Reference Rates'!$D$51)*'Reference Rates'!$C$51,IF(T35<='Reference Rates'!$D$53,'Reference Rates'!$B$52+(T35-'Reference Rates'!$D$52)*'Reference Rates'!$C$52,IF(T35<='Reference Rates'!$D$54,'Reference Rates'!$B$53+(T35-'Reference Rates'!$D$53)*'Reference Rates'!$C$53,IF(T35<='Reference Rates'!$D$55,'Reference Rates'!$B$54+(T35-'Reference Rates'!$D$54)*'Reference Rates'!$C$54,'Reference Rates'!$B$55+(T35-'Reference Rates'!$D$55)*'Reference Rates'!$C$55))))) -> 1461 | V35: =S35+U35 -> 4168 | W35: =L35+M35+N35-V35 -> 30412 | X35: =O35*'Reference Rates'!$B$28 -> 3350 | Y35: =IF(O35<'Reference Rates'!$B$31,'Reference Rates'!$B$32,'Reference Rates'!$B$33) -> 30 | Z35: =MIN(MAX(L35,'Reference Rates'!$B$39),'Reference Rates'!$B$40)*'Reference Rates'!$B$38 -> 832 | AA35: =MIN(L35,'Reference Rates'!$B$46)*'Reference Rates'!$B$45 -> 200 | AB35: =X35+Y35+Z35+AA35 -> 4412 | AC35: =L35+M35+N35+AB35 -> 38992
A36: TOTAL | G36: =SUM(G6:G35) -> 6208 | H36: =SUM(H6:H35) -> 185 | I36: =SUM(I6:I35) -> 62 | J36: =SUM(J6:J35) -> 611205 | K36: =SUM(K6:K35) -> 23101.562 | L36: =SUM(L6:L35) -> 634306.56 | M36: =SUM(M6:M35) -> 38800 | N36: =SUM(N6:N35) -> 45000 | P36: =SUM(P6:P35) -> 31825 | Q36: =SUM(Q6:Q35) -> 15857.664 | R36: =SUM(R6:R35) -> 6000 | S36: =SUM(S6:S35) -> 53682.664 | T36: =SUM(T6:T35) -> 240053.25 | U36: =SUM(U6:U35) -> 4937.7937 | V36: =SUM(V6:V35) -> 58620.458 | W36: =SUM(W6:W35) -> 659486.1 | ... AC36: =SUM(AC6:AC35) -> 804514.23
A38: Legend: | B38: Blue = input (edit) | C38: Black = formula | D38: Green text = linked from another sheet | G38: Green row = delivery driver

Sheet Oct 2026
A1: Employee Payroll Register — October 2026
A2: Blue = input; black = formula; green = linked from another sheet. Names, departments, positions, MWE status and fixed hourly rates are linked from the Aug 2026 sheet. Green-tinted rows = delivery drivers. Regular Hours default to 208 (26 days × 8 hrs). OT is the ordinary 125% premium. Per diem = Trip Days × the department rate on Reference Rates. Allowances are non-taxable and outside the SSS/PhilHealth/Pag-IBIG base. Printed pages cover columns A–W (employee-facing); employer-cost columns X–AC are on screen only.
A3: Pay Period: | B3: 2026-10-01 to 2026-10-31
A5: Employee ID | B5: Employee Name | C5: Department | D5: Position | E5: MWE (Y/N) | F5: Hourly Rate (₱) | G5: Regular Hours | H5: OT Hours (125%) | I5: Trip Days (per diem) | J5: Basic Pay | K5: OT Pay | L5: GROSS PAY | M5: Meal Allowance | N5: Per Diem | O5: SSS MSC | P5: SSS – EE | Q5: PhilHealth – EE | R5: Pag-IBIG – EE | S5: Total EE Contrib. | T5: Taxable Income | U5: Withholding Tax | V5: Total Deductions | W5: NET PAY | X5: SSS – ER | Y5: SSS – EC | Z5: PhilHealth – ER | AA5: Pag-IBIG – ER | AB5: Total ER Contrib. | AC5: TOTAL COST TO COMPANY
A6: ='Aug 2026'!A6 -> EMP-001 | B6: =IF('Aug 2026'!B6="","",'Aug 2026'!B6) -> Mikhail Dustin Elpedes | C6: ='Aug 2026'!C6 -> Store | D6: ='Aug 2026'!D6 -> Cashier | E6: ='Aug 2026'!E6 -> Y | F6: ='Reference Rates'!$E$15 -> 94.375 | G6: 208 | H6: 6 | I6: 0 | J6: =F6*G6 -> 19630 | K6: =F6*1.25*H6 -> 707.8125 | L6: =J6+K6 -> 20337.812 | M6: ='Reference Rates'!$B$19*G6/8 -> 1300 | N6: =I6*IFERROR(INDEX('Reference Rates'!$B$21:$B$22,MATCH(C6,'Reference Rates'!$A$21:$A$22,0)),0) -> 0 | O6: =MIN('Reference Rates'!$B$30,MAX('Reference Rates'!$B$29,MROUND(L6,500))) -> 20500 | P6: =O6*'Reference Rates'!$B$27 -> 1025 | Q6: =MIN(MAX(L6,'Reference Rates'!$B$39),'Reference Rates'!$B$40)*'Reference Rates'!$B$37 -> 508.44531 | R6: =MIN(L6,'Reference Rates'!$B$46)*IF(L6>1500,'Reference Rates'!$B$43,'Reference Rates'!$B$44) -> 200 | S6: =P6+Q6+R6 -> 1733.4453 | T6: =IF(E6="Y",0,MAX(0,L6-S6)) -> 0 | U6: =IF(T6<='Reference Rates'!$D$51,0,IF(T6<='Reference Rates'!$D$52,'Reference Rates'!$B$51+(T6-'Reference Rates'!$D$51)*'Reference Rates'!$C$51,IF(T6<='Reference Rates'!$D$53,'Reference Rates'!$B$52+(T6-'Reference Rates'!$D$52)*'Reference Rates'!$C$52,IF(T6<='Reference Rates'!$D$54,'Reference Rates'!$B$53+(T6-'Reference Rates'!$D$53)*'Reference Rates'!$C$53,IF(T6<='Reference Rates'!$D$55,'Reference Rates'!$B$54+(T6-'Reference Rates'!$D$54)*'Reference Rates'!$C$54,'Reference Rates'!$B$55+(T6-'Reference Rates'!$D$55)*'Reference Rates'!$C$55))))) -> 0 | V6: =S6+U6 -> 1733.4453 | W6: =L6+M6+N6-V6 -> 19904.367 | X6: =O6*'Reference Rates'!$B$28 -> 2050 | Y6: =IF(O6<'Reference Rates'!$B$31,'Reference Rates'!$B$32,'Reference Rates'!$B$33) -> 30 | Z6: =MIN(MAX(L6,'Reference Rates'!$B$39),'Reference Rates'!$B$40)*'Reference Rates'!$B$38 -> 508.44531 | AA6: =MIN(L6,'Reference Rates'!$B$46)*'Reference Rates'!$B$45 -> 200 | AB6: =X6+Y6+Z6+AA6 -> 2788.4453 | AC6: =L6+M6+N6+AB6 -> 24426.258
A7: ='Aug 2026'!A7 -> EMP-002 | B7: =IF('Aug 2026'!B7="","",'Aug 2026'!B7) | C7: ='Aug 2026'!C7 -> Store | D7: ='Aug 2026'!D7 -> Cashier | E7: ='Aug 2026'!E7 -> Y | F7: ='Reference Rates'!$E$15 -> 94.375 | G7: 208 | H7: 3 | I7: 0 | J7: =F7*G7 -> 19630 | K7: =F7*1.25*H7 -> 353.90625 | L7: =J7+K7 -> 19983.906 | M7: ='Reference Rates'!$B$19*G7/8 -> 1300 | N7: =I7*IFERROR(INDEX('Reference Rates'!$B$21:$B$22,MATCH(C7,'Reference Rates'!$A$21:$A$22,0)),0) -> 0 | O7: =MIN('Reference Rates'!$B$30,MAX('Reference Rates'!$B$29,MROUND(L7,500))) -> 20000 | P7: =O7*'Reference Rates'!$B$27 -> 1000 | Q7: =MIN(MAX(L7,'Reference Rates'!$B$39),'Reference Rates'!$B$40)*'Reference Rates'!$B$37 -> 499.59766 | R7: =MIN(L7,'Reference Rates'!$B$46)*IF(L7>1500,'Reference Rates'!$B$43,'Reference Rates'!$B$44) -> 200 | S7: =P7+Q7+R7 -> 1699.5977 | T7: =IF(E7="Y",0,MAX(0,L7-S7)) -> 0 | U7: =IF(T7<='Reference Rates'!$D$51,0,IF(T7<='Reference Rates'!$D$52,'Reference Rates'!$B$51+(T7-'Reference Rates'!$D$51)*'Reference Rates'!$C$51,IF(T7<='Reference Rates'!$D$53,'Reference Rates'!$B$52+(T7-'Reference Rates'!$D$52)*'Reference Rates'!$C$52,IF(T7<='Reference Rates'!$D$54,'Reference Rates'!$B$53+(T7-'Reference Rates'!$D$53)*'Reference Rates'!$C$53,IF(T7<='Reference Rates'!$D$55,'Reference Rates'!$B$54+(T7-'Reference Rates'!$D$54)*'Reference Rates'!$C$54,'Reference Rates'!$B$55+(T7-'Reference Rates'!$D$55)*'Reference Rates'!$C$55))))) -> 0 | V7: =S7+U7 -> 1699.5977 | W7: =L7+M7+N7-V7 -> 19584.309 | X7: =O7*'Reference Rates'!$B$28 -> 2000 | Y7: =IF(O7<'Reference Rates'!$B$31,'Reference Rates'!$B$32,'Reference Rates'!$B$33) -> 30 | Z7: =MIN(MAX(L7,'Reference Rates'!$B$39),'Reference Rates'!$B$40)*'Reference Rates'!$B$38 -> 499.59766 | AA7: =MIN(L7,'Reference Rates'!$B$46)*'Reference Rates'!$B$45 -> 200 | AB7: =X7+Y7+Z7+AA7 -> 2729.5977 | AC7: =L7+M7+N7+AB7 -> 24013.504
A8: ='Aug 2026'!A8 -> EMP-003 | B8: =IF('Aug 2026'!B8="","",'Aug 2026'!B8) | C8: ='Aug 2026'!C8 -> Store | D8: ='Aug 2026'!D8 -> Cashier | E8: ='Aug 2026'!E8 -> Y | F8: ='Reference Rates'!$E$15 -> 94.375 | G8: 200 | H8: 5 | I8: 0 | J8: =F8*G8 -> 18875 | K8: =F8*1.25*H8 -> 589.84375 | L8: =J8+K8 -> 19464.844 | M8: ='Reference Rates'!$B$19*G8/8 -> 1250 | N8: =I8*IFERROR(INDEX('Reference Rates'!$B$21:$B$22,MATCH(C8,'Reference Rates'!$A$21:$A$22,0)),0) -> 0 | O8: =MIN('Reference Rates'!$B$30,MAX('Reference Rates'!$B$29,MROUND(L8,500))) -> 19500 | P8: =O8*'Reference Rates'!$B$27 -> 975 | Q8: =MIN(MAX(L8,'Reference Rates'!$B$39),'Reference Rates'!$B$40)*'Reference Rates'!$B$37 -> 486.62109 | R8: =MIN(L8,'Reference Rates'!$B$46)*IF(L8>1500,'Reference Rates'!$B$43,'Reference Rates'!$B$44) -> 200 | S8: =P8+Q8+R8 -> 1661.6211 | T8: =IF(E8="Y",0,MAX(0,L8-S8)) -> 0 | U8: =IF(T8<='Reference Rates'!$D$51,0,IF(T8<='Reference Rates'!$D$52,'Reference Rates'!$B$51+(T8-'Reference Rates'!$D$51)*'Reference Rates'!$C$51,IF(T8<='Reference Rates'!$D$53,'Reference Rates'!$B$52+(T8-'Reference Rates'!$D$52)*'Reference Rates'!$C$52,IF(T8<='Reference Rates'!$D$54,'Reference Rates'!$B$53+(T8-'Reference Rates'!$D$53)*'Reference Rates'!$C$53,IF(T8<='Reference Rates'!$D$55,'Reference Rates'!$B$54+(T8-'Reference Rates'!$D$54)*'Reference Rates'!$C$54,'Reference Rates'!$B$55+(T8-'Reference Rates'!$D$55)*'Reference Rates'!$C$55))))) -> 0 | V8: =S8+U8 -> 1661.6211 | W8: =L8+M8+N8-V8 -> 19053.223 | X8: =O8*'Reference Rates'!$B$28 -> 1950 | Y8: =IF(O8<'Reference Rates'!$B$31,'Reference Rates'!$B$32,'Reference Rates'!$B$33) -> 30 | Z8: =MIN(MAX(L8,'Reference Rates'!$B$39),'Reference Rates'!$B$40)*'Reference Rates'!$B$38 -> 486.62109 | AA8: =MIN(L8,'Reference Rates'!$B$46)*'Reference Rates'!$B$45 -> 200 | AB8: =X8+Y8+Z8+AA8 -> 2666.6211 | AC8: =L8+M8+N8+AB8 -> 23381.465
A9: ='Aug 2026'!A9 -> EMP-004 | B9: =IF('Aug 2026'!B9="","",'Aug 2026'!B9) | C9: ='Aug 2026'!C9 -> Store | D9: ='Aug 2026'!D9 -> Cashier | E9: ='Aug 2026'!E9 -> Y | F9: ='Reference Rates'!$E$15 -> 94.375 | G9: 208 | H9: 6 | I9: 0 | J9: =F9*G9 -> 19630 | K9: =F9*1.25*H9 -> 707.8125 | L9: =J9+K9 -> 20337.812 | M9: ='Reference Rates'!$B$19*G9/8 -> 1300 | N9: =I9*IFERROR(INDEX('Reference Rates'!$B$21:$B$22,MATCH(C9,'Reference Rates'!$A$21:$A$22,0)),0) -> 0 | O9: =MIN('Reference Rates'!$B$30,MAX('Reference Rates'!$B$29,MROUND(L9,500))) -> 20500 | P9: =O9*'Reference Rates'!$B$27 -> 1025 | Q9: =MIN(MAX(L9,'Reference Rates'!$B$39),'Reference Rates'!$B$40)*'Reference Rates'!$B$37 -> 508.44531 | R9: =MIN(L9,'Reference Rates'!$B$46)*IF(L9>1500,'Reference Rates'!$B$43,'Reference Rates'!$B$44) -> 200 | S9: =P9+Q9+R9 -> 1733.4453 | T9: =IF(E9="Y",0,MAX(0,L9-S9)) -> 0 | U9: =IF(T9<='Reference Rates'!$D$51,0,IF(T9<='Reference Rates'!$D$52,'Reference Rates'!$B$51+(T9-'Reference Rates'!$D$51)*'Reference Rates'!$C$51,IF(T9<='Reference Rates'!$D$53,'Reference Rates'!$B$52+(T9-'Reference Rates'!$D$52)*'Reference Rates'!$C$52,IF(T9<='Reference Rates'!$D$54,'Reference Rates'!$B$53+(T9-'Reference Rates'!$D$53)*'Reference Rates'!$C$53,IF(T9<='Reference Rates'!$D$55,'Reference Rates'!$B$54+(T9-'Reference Rates'!$D$54)*'Reference Rates'!$C$54,'Reference Rates'!$B$55+(T9-'Reference Rates'!$D$55)*'Reference Rates'!$C$55))))) -> 0 | V9: =S9+U9 -> 1733.4453 | W9: =L9+M9+N9-V9 -> 19904.367 | X9: =O9*'Reference Rates'!$B$28 -> 2050 | Y9: =IF(O9<'Reference Rates'!$B$31,'Reference Rates'!$B$32,'Reference Rates'!$B$33) -> 30 | Z9: =MIN(MAX(L9,'Reference Rates'!$B$39),'Reference Rates'!$B$40)*'Reference Rates'!$B$38 -> 508.44531 | AA9: =MIN(L9,'Reference Rates'!$B$46)*'Reference Rates'!$B$45 -> 200 | AB9: =X9+Y9+Z9+AA9 -> 2788.4453 | AC9: =L9+M9+N9+AB9 -> 24426.258
A10: ='Aug 2026'!A10 -> EMP-005 | B10: =IF('Aug 2026'!B10="","",'Aug 2026'!B10) | C10: ='Aug 2026'!C10 -> Store | D10: ='Aug 2026'!D10 -> Sales Clerk | E10: ='Aug 2026'!E10 -> Y | F10: ='Reference Rates'!$E$15 -> 94.375 | G10: 208 | H10: 7 | I10: 0 | J10: =F10*G10 -> 19630 | K10: =F10*1.25*H10 -> 825.78125 | L10: =J10+K10 -> 20455.781 | M10: ='Reference Rates'!$B$19*G10/8 -> 1300 | N10: =I10*IFERROR(INDEX('Reference Rates'!$B$21:$B$22,MATCH(C10,'Reference Rates'!$A$21:$A$22,0)),0) -> 0 | O10: =MIN('Reference Rates'!$B$30,MAX('Reference Rates'!$B$29,MROUND(L10,500))) -> 20500 | P10: =O10*'Reference Rates'!$B$27 -> 1025 | Q10: =MIN(MAX(L10,'Reference Rates'!$B$39),'Reference Rates'!$B$40)*'Reference Rates'!$B$37 -> 511.39453 | R10: =MIN(L10,'Reference Rates'!$B$46)*IF(L10>1500,'Reference Rates'!$B$43,'Reference Rates'!$B$44) -> 200 | S10: =P10+Q10+R10 -> 1736.3945 | T10: =IF(E10="Y",0,MAX(0,L10-S10)) -> 0 | U10: =IF(T10<='Reference Rates'!$D$51,0,IF(T10<='Reference Rates'!$D$52,'Reference Rates'!$B$51+(T10-'Reference Rates'!$D$51)*'Reference Rates'!$C$51,IF(T10<='Reference Rates'!$D$53,'Reference Rates'!$B$52+(T10-'Reference Rates'!$D$52)*'Reference Rates'!$C$52,IF(T10<='Reference Rates'!$D$54,'Reference Rates'!$B$53+(T10-'Reference Rates'!$D$53)*'Reference Rates'!$C$53,IF(T10<='Reference Rates'!$D$55,'Reference Rates'!$B$54+(T10-'Reference Rates'!$D$54)*'Reference Rates'!$C$54,'Reference Rates'!$B$55+(T10-'Reference Rates'!$D$55)*'Reference Rates'!$C$55))))) -> 0 | V10: =S10+U10 -> 1736.3945 | W10: =L10+M10+N10-V10 -> 20019.387 | X10: =O10*'Reference Rates'!$B$28 -> 2050 | Y10: =IF(O10<'Reference Rates'!$B$31,'Reference Rates'!$B$32,'Reference Rates'!$B$33) -> 30 | Z10: =MIN(MAX(L10,'Reference Rates'!$B$39),'Reference Rates'!$B$40)*'Reference Rates'!$B$38 -> 511.39453 | AA10: =MIN(L10,'Reference Rates'!$B$46)*'Reference Rates'!$B$45 -> 200 | AB10: =X10+Y10+Z10+AA10 -> 2791.3945 | AC10: =L10+M10+N10+AB10 -> 24547.176
A11: ='Aug 2026'!A11 -> EMP-006 | B11: =IF('Aug 2026'!B11="","",'Aug 2026'!B11) | C11: ='Aug 2026'!C11 -> Store | D11: ='Aug 2026'!D11 -> Sales Clerk | E11: ='Aug 2026'!E11 -> Y | F11: ='Reference Rates'!$E$15 -> 94.375 | G11: 208 | H11: 0 | I11: 0 | J11: =F11*G11 -> 19630 | K11: =F11*1.25*H11 -> 0 | L11: =J11+K11 -> 19630 | M11: ='Reference Rates'!$B$19*G11/8 -> 1300 | N11: =I11*IFERROR(INDEX('Reference Rates'!$B$21:$B$22,MATCH(C11,'Reference Rates'!$A$21:$A$22,0)),0) -> 0 | O11: =MIN('Reference Rates'!$B$30,MAX('Reference Rates'!$B$29,MROUND(L11,500))) -> 19500 | P11: =O11*'Reference Rates'!$B$27 -> 975 | Q11: =MIN(MAX(L11,'Reference Rates'!$B$39),'Reference Rates'!$B$40)*'Reference Rates'!$B$37 -> 490.75 | R11: =MIN(L11,'Reference Rates'!$B$46)*IF(L11>1500,'Reference Rates'!$B$43,'Reference Rates'!$B$44) -> 200 | S11: =P11+Q11+R11 -> 1665.75 | T11: =IF(E11="Y",0,MAX(0,L11-S11)) -> 0 | U11: =IF(T11<='Reference Rates'!$D$51,0,IF(T11<='Reference Rates'!$D$52,'Reference Rates'!$B$51+(T11-'Reference Rates'!$D$51)*'Reference Rates'!$C$51,IF(T11<='Reference Rates'!$D$53,'Reference Rates'!$B$52+(T11-'Reference Rates'!$D$52)*'Reference Rates'!$C$52,IF(T11<='Reference Rates'!$D$54,'Reference Rates'!$B$53+(T11-'Reference Rates'!$D$53)*'Reference Rates'!$C$53,IF(T11<='Reference Rates'!$D$55,'Reference Rates'!$B$54+(T11-'Reference Rates'!$D$54)*'Reference Rates'!$C$54,'Reference Rates'!$B$55+(T11-'Reference Rates'!$D$55)*'Reference Rates'!$C$55))))) -> 0 | V11: =S11+U11 -> 1665.75 | W11: =L11+M11+N11-V11 -> 19264.25 | X11: =O11*'Reference Rates'!$B$28 -> 1950 | Y11: =IF(O11<'Reference Rates'!$B$31,'Reference Rates'!$B$32,'Reference Rates'!$B$33) -> 30 | Z11: =MIN(MAX(L11,'Reference Rates'!$B$39),'Reference Rates'!$B$40)*'Reference Rates'!$B$38 -> 490.75 | AA11: =MIN(L11,'Reference Rates'!$B$46)*'Reference Rates'!$B$45 -> 200 | AB11: =X11+Y11+Z11+AA11 -> 2670.75 | AC11: =L11+M11+N11+AB11 -> 23600.75
A12: ='Aug 2026'!A12 -> EMP-007 | B12: =IF('Aug 2026'!B12="","",'Aug 2026'!B12) | C12: ='Aug 2026'!C12 -> Store | D12: ='Aug 2026'!D12 -> Sales Clerk | E12: ='Aug 2026'!E12 -> Y | F12: ='Reference Rates'!$E$15 -> 94.375 | G12: 208 | H12: 5 | I12: 0 | J12: =F12*G12 -> 19630 | K12: =F12*1.25*H12 -> 589.84375 | L12: =J12+K12 -> 20219.844 | M12: ='Reference Rates'!$B$19*G12/8 -> 1300 | N12: =I12*IFERROR(INDEX('Reference Rates'!$B$21:$B$22,MATCH(C12,'Reference Rates'!$A$21:$A$22,0)),0) -> 0 | O12: =MIN('Reference Rates'!$B$30,MAX('Reference Rates'!$B$29,MROUND(L12,500))) -> 20000 | P12: =O12*'Reference Rates'!$B$27 -> 1000 | Q12: =MIN(MAX(L12,'Reference Rates'!$B$39),'Reference Rates'!$B$40)*'Reference Rates'!$B$37 -> 505.49609 | R12: =MIN(L12,'Reference Rates'!$B$46)*IF(L12>1500,'Reference Rates'!$B$43,'Reference Rates'!$B$44) -> 200 | S12: =P12+Q12+R12 -> 1705.4961 | T12: =IF(E12="Y",0,MAX(0,L12-S12)) -> 0 | U12: =IF(T12<='Reference Rates'!$D$51,0,IF(T12<='Reference Rates'!$D$52,'Reference Rates'!$B$51+(T12-'Reference Rates'!$D$51)*'Reference Rates'!$C$51,IF(T12<='Reference Rates'!$D$53,'Reference Rates'!$B$52+(T12-'Reference Rates'!$D$52)*'Reference Rates'!$C$52,IF(T12<='Reference Rates'!$D$54,'Reference Rates'!$B$53+(T12-'Reference Rates'!$D$53)*'Reference Rates'!$C$53,IF(T12<='Reference Rates'!$D$55,'Reference Rates'!$B$54+(T12-'Reference Rates'!$D$54)*'Reference Rates'!$C$54,'Reference Rates'!$B$55+(T12-'Reference Rates'!$D$55)*'Reference Rates'!$C$55))))) -> 0 | V12: =S12+U12 -> 1705.4961 | W12: =L12+M12+N12-V12 -> 19814.348 | X12: =O12*'Reference Rates'!$B$28 -> 2000 | Y12: =IF(O12<'Reference Rates'!$B$31,'Reference Rates'!$B$32,'Reference Rates'!$B$33) -> 30 | Z12: =MIN(MAX(L12,'Reference Rates'!$B$39),'Reference Rates'!$B$40)*'Reference Rates'!$B$38 -> 505.49609 | AA12: =MIN(L12,'Reference Rates'!$B$46)*'Reference Rates'!$B$45 -> 200 | AB12: =X12+Y12+Z12+AA12 -> 2735.4961 | AC12: =L12+M12+N12+AB12 -> 24255.34
A13: ='Aug 2026'!A13 -> EMP-008 | B13: =IF('Aug 2026'!B13="","",'Aug 2026'!B13) | C13: ='Aug 2026'!C13 -> Store | D13: ='Aug 2026'!D13 -> Sales Clerk | E13: ='Aug 2026'!E13 -> Y | F13: ='Reference Rates'!$E$15 -> 94.375 | G13: 208 | H13: 6 | I13: 0 | J13: =F13*G13 -> 19630 | K13: =F13*1.25*H13 -> 707.8125 | L13: =J13+K13 -> 20337.812 | M13: ='Reference Rates'!$B$19*G13/8 -> 1300 | N13: =I13*IFERROR(INDEX('Reference Rates'!$B$21:$B$22,MATCH(C13,'Reference Rates'!$A$21:$A$22,0)),0) -> 0 | O13: =MIN('Reference Rates'!$B$30,MAX('Reference Rates'!$B$29,MROUND(L13,500))) -> 20500 | P13: =O13*'Reference Rates'!$B$27 -> 1025 | Q13: =MIN(MAX(L13,'Reference Rates'!$B$39),'Reference Rates'!$B$40)*'Reference Rates'!$B$37 -> 508.44531 | R13: =MIN(L13,'Reference Rates'!$B$46)*IF(L13>1500,'Reference Rates'!$B$43,'Reference Rates'!$B$44) -> 200 | S13: =P13+Q13+R13 -> 1733.4453 | T13: =IF(E13="Y",0,MAX(0,L13-S13)) -> 0 | U13: =IF(T13<='Reference Rates'!$D$51,0,IF(T13<='Reference Rates'!$D$52,'Reference Rates'!$B$51+(T13-'Reference Rates'!$D$51)*'Reference Rates'!$C$51,IF(T13<='Reference Rates'!$D$53,'Reference Rates'!$B$52+(T13-'Reference Rates'!$D$52)*'Reference Rates'!$C$52,IF(T13<='Reference Rates'!$D$54,'Reference Rates'!$B$53+(T13-'Reference Rates'!$D$53)*'Reference Rates'!$C$53,IF(T13<='Reference Rates'!$D$55,'Reference Rates'!$B$54+(T13-'Reference Rates'!$D$54)*'Reference Rates'!$C$54,'Reference Rates'!$B$55+(T13-'Reference Rates'!$D$55)*'Reference Rates'!$C$55))))) -> 0 | V13: =S13+U13 -> 1733.4453 | W13: =L13+M13+N13-V13 -> 19904.367 | X13: =O13*'Reference Rates'!$B$28 -> 2050 | Y13: =IF(O13<'Reference Rates'!$B$31,'Reference Rates'!$B$32,'Reference Rates'!$B$33) -> 30 | Z13: =MIN(MAX(L13,'Reference Rates'!$B$39),'Reference Rates'!$B$40)*'Reference Rates'!$B$38 -> 508.44531 | AA13: =MIN(L13,'Reference Rates'!$B$46)*'Reference Rates'!$B$45 -> 200 | AB13: =X13+Y13+Z13+AA13 -> 2788.4453 | AC13: =L13+M13+N13+AB13 -> 24426.258
A14: ='Aug 2026'!A14 -> EMP-009 | B14: =IF('Aug 2026'!B14="","",'Aug 2026'!B14) | C14: ='Aug 2026'!C14 -> Store | D14: ='Aug 2026'!D14 -> Sales Clerk | E14: ='Aug 2026'!E14 -> Y | F14: ='Reference Rates'!$E$15 -> 94.375 | G14: 200 | H14: 5 | I14: 0 | J14: =F14*G14 -> 18875 | K14: =F14*1.25*H14 -> 589.84375 | L14: =J14+K14 -> 19464.844 | M14: ='Reference Rates'!$B$19*G14/8 -> 1250 | N14: =I14*IFERROR(INDEX('Reference Rates'!$B$21:$B$22,MATCH(C14,'Reference Rates'!$A$21:$A$22,0)),0) -> 0 | O14: =MIN('Reference Rates'!$B$30,MAX('Reference Rates'!$B$29,MROUND(L14,500))) -> 19500 | P14: =O14*'Reference Rates'!$B$27 -> 975 | Q14: =MIN(MAX(L14,'Reference Rates'!$B$39),'Reference Rates'!$B$40)*'Reference Rates'!$B$37 -> 486.62109 | R14: =MIN(L14,'Reference Rates'!$B$46)*IF(L14>1500,'Reference Rates'!$B$43,'Reference Rates'!$B$44) -> 200 | S14: =P14+Q14+R14 -> 1661.6211 | T14: =IF(E14="Y",0,MAX(0,L14-S14)) -> 0 | U14: =IF(T14<='Reference Rates'!$D$51,0,IF(T14<='Reference Rates'!$D$52,'Reference Rates'!$B$51+(T14-'Reference Rates'!$D$51)*'Reference Rates'!$C$51,IF(T14<='Reference Rates'!$D$53,'Reference Rates'!$B$52+(T14-'Reference Rates'!$D$52)*'Reference Rates'!$C$52,IF(T14<='Reference Rates'!$D$54,'Reference Rates'!$B$53+(T14-'Reference Rates'!$D$53)*'Reference Rates'!$C$53,IF(T14<='Reference Rates'!$D$55,'Reference Rates'!$B$54+(T14-'Reference Rates'!$D$54)*'Reference Rates'!$C$54,'Reference Rates'!$B$55+(T14-'Reference Rates'!$D$55)*'Reference Rates'!$C$55))))) -> 0 | V14: =S14+U14 -> 1661.6211 | W14: =L14+M14+N14-V14 -> 19053.223 | X14: =O14*'Reference Rates'!$B$28 -> 1950 | Y14: =IF(O14<'Reference Rates'!$B$31,'Reference Rates'!$B$32,'Reference Rates'!$B$33) -> 30 | Z14: =MIN(MAX(L14,'Reference Rates'!$B$39),'Reference Rates'!$B$40)*'Reference Rates'!$B$38 -> 486.62109 | AA14: =MIN(L14,'Reference Rates'!$B$46)*'Reference Rates'!$B$45 -> 200 | AB14: =X14+Y14+Z14+AA14 -> 2666.6211 | AC14: =L14+M14+N14+AB14 -> 23381.465
A15: ='Aug 2026'!A15 -> EMP-010 | B15: =IF('Aug 2026'!B15="","",'Aug 2026'!B15) | C15: ='Aug 2026'!C15 -> Store | D15: ='Aug 2026'!D15 -> Section Attendant (Frozen / Egg) | E15: ='Aug 2026'!E15 -> Y | F15: ='Reference Rates'!$E$15 -> 94.375 | G15: 208 | H15: 6 | I15: 0 | J15: =F15*G15 -> 19630 | K15: =F15*1.25*H15 -> 707.8125 | L15: =J15+K15 -> 20337.812 | M15: ='Reference Rates'!$B$19*G15/8 -> 1300 | N15: =I15*IFERROR(INDEX('Reference Rates'!$B$21:$B$22,MATCH(C15,'Reference Rates'!$A$21:$A$22,0)),0) -> 0 | O15: =MIN('Reference Rates'!$B$30,MAX('Reference Rates'!$B$29,MROUND(L15,500))) -> 20500 | P15: =O15*'Reference Rates'!$B$27 -> 1025 | Q15: =MIN(MAX(L15,'Reference Rates'!$B$39),'Reference Rates'!$B$40)*'Reference Rates'!$B$37 -> 508.44531 | R15: =MIN(L15,'Reference Rates'!$B$46)*IF(L15>1500,'Reference Rates'!$B$43,'Reference Rates'!$B$44) -> 200 | S15: =P15+Q15+R15 -> 1733.4453 | T15: =IF(E15="Y",0,MAX(0,L15-S15)) -> 0 | U15: =IF(T15<='Reference Rates'!$D$51,0,IF(T15<='Reference Rates'!$D$52,'Reference Rates'!$B$51+(T15-'Reference Rates'!$D$51)*'Reference Rates'!$C$51,IF(T15<='Reference Rates'!$D$53,'Reference Rates'!$B$52+(T15-'Reference Rates'!$D$52)*'Reference Rates'!$C$52,IF(T15<='Reference Rates'!$D$54,'Reference Rates'!$B$53+(T15-'Reference Rates'!$D$53)*'Reference Rates'!$C$53,IF(T15<='Reference Rates'!$D$55,'Reference Rates'!$B$54+(T15-'Reference Rates'!$D$54)*'Reference Rates'!$C$54,'Reference Rates'!$B$55+(T15-'Reference Rates'!$D$55)*'Reference Rates'!$C$55))))) -> 0 | V15: =S15+U15 -> 1733.4453 | W15: =L15+M15+N15-V15 -> 19904.367 | X15: =O15*'Reference Rates'!$B$28 -> 2050 | Y15: =IF(O15<'Reference Rates'!$B$31,'Reference Rates'!$B$32,'Reference Rates'!$B$33) -> 30 | Z15: =MIN(MAX(L15,'Reference Rates'!$B$39),'Reference Rates'!$B$40)*'Reference Rates'!$B$38 -> 508.44531 | AA15: =MIN(L15,'Reference Rates'!$B$46)*'Reference Rates'!$B$45 -> 200 | AB15: =X15+Y15+Z15+AA15 -> 2788.4453 | AC15: =L15+M15+N15+AB15 -> 24426.258
A16: ='Aug 2026'!A16 -> EMP-011 | B16: =IF('Aug 2026'!B16="","",'Aug 2026'!B16) | C16: ='Aug 2026'!C16 -> Store | D16: ='Aug 2026'!D16 -> Section Attendant (Frozen / Egg) | E16: ='Aug 2026'!E16 -> Y | F16: ='Reference Rates'!$E$15 -> 94.375 | G16: 208 | H16: 8 | I16: 0 | J16: =F16*G16 -> 19630 | K16: =F16*1.25*H16 -> 943.75 | L16: =J16+K16 -> 20573.75 | M16: ='Reference Rates'!$B$19*G16/8 -> 1300 | N16: =I16*IFERROR(INDEX('Reference Rates'!$B$21:$B$22,MATCH(C16,'Reference Rates'!$A$21:$A$22,0)),0) -> 0 | O16: =MIN('Reference Rates'!$B$30,MAX('Reference Rates'!$B$29,MROUND(L16,500))) -> 20500 | P16: =O16*'Reference Rates'!$B$27 -> 1025 | Q16: =MIN(MAX(L16,'Reference Rates'!$B$39),'Reference Rates'!$B$40)*'Reference Rates'!$B$37 -> 514.34375 | R16: =MIN(L16,'Reference Rates'!$B$46)*IF(L16>1500,'Reference Rates'!$B$43,'Reference Rates'!$B$44) -> 200 | S16: =P16+Q16+R16 -> 1739.3438 | T16: =IF(E16="Y",0,MAX(0,L16-S16)) -> 0 | U16: =IF(T16<='Reference Rates'!$D$51,0,IF(T16<='Reference Rates'!$D$52,'Reference Rates'!$B$51+(T16-'Reference Rates'!$D$51)*'Reference Rates'!$C$51,IF(T16<='Reference Rates'!$D$53,'Reference Rates'!$B$52+(T16-'Reference Rates'!$D$52)*'Reference Rates'!$C$52,IF(T16<='Reference Rates'!$D$54,'Reference Rates'!$B$53+(T16-'Reference Rates'!$D$53)*'Reference Rates'!$C$53,IF(T16<='Reference Rates'!$D$55,'Reference Rates'!$B$54+(T16-'Reference Rates'!$D$54)*'Reference Rates'!$C$54,'Reference Rates'!$B$55+(T16-'Reference Rates'!$D$55)*'Reference Rates'!$C$55))))) -> 0 | V16: =S16+U16 -> 1739.3438 | W16: =L16+M16+N16-V16 -> 20134.406 | X16: =O16*'Reference Rates'!$B$28 -> 2050 | Y16: =IF(O16<'Reference Rates'!$B$31,'Reference Rates'!$B$32,'Reference Rates'!$B$33) -> 30 | Z16: =MIN(MAX(L16,'Reference Rates'!$B$39),'Reference Rates'!$B$40)*'Reference Rates'!$B$38 -> 514.34375 | AA16: =MIN(L16,'Reference Rates'!$B$46)*'Reference Rates'!$B$45 -> 200 | AB16: =X16+Y16+Z16+AA16 -> 2794.3438 | AC16: =L16+M16+N16+AB16 -> 24668.094
A17: ='Aug 2026'!A17 -> EMP-012 | B17: =IF('Aug 2026'!B17="","",'Aug 2026'!B17) | C17: ='Aug 2026'!C17 -> Store | D17: ='Aug 2026'!D17 -> Section Attendant (Frozen / Egg) | E17: ='Aug 2026'!E17 -> Y | F17: ='Reference Rates'!$E$15 -> 94.375 | G17: 200 | H17: 6 | I17: 0 | J17: =F17*G17 -> 18875 | K17: =F17*1.25*H17 -> 707.8125 | L17: =J17+K17 -> 19582.812 | M17: ='Reference Rates'!$B$19*G17/8 -> 1250 | N17: =I17*IFERROR(INDEX('Reference Rates'!$B$21:$B$22,MATCH(C17,'Reference Rates'!$A$21:$A$22,0)),0) -> 0 | O17: =MIN('Reference Rates'!$B$30,MAX('Reference Rates'!$B$29,MROUND(L17,500))) -> 19500 | P17: =O17*'Reference Rates'!$B$27 -> 975 | Q17: =MIN(MAX(L17,'Reference Rates'!$B$39),'Reference Rates'!$B$40)*'Reference Rates'!$B$37 -> 489.57031 | R17: =MIN(L17,'Reference Rates'!$B$46)*IF(L17>1500,'Reference Rates'!$B$43,'Reference Rates'!$B$44) -> 200 | S17: =P17+Q17+R17 -> 1664.5703 | T17: =IF(E17="Y",0,MAX(0,L17-S17)) -> 0 | U17: =IF(T17<='Reference Rates'!$D$51,0,IF(T17<='Reference Rates'!$D$52,'Reference Rates'!$B$51+(T17-'Reference Rates'!$D$51)*'Reference Rates'!$C$51,IF(T17<='Reference Rates'!$D$53,'Reference Rates'!$B$52+(T17-'Reference Rates'!$D$52)*'Reference Rates'!$C$52,IF(T17<='Reference Rates'!$D$54,'Reference Rates'!$B$53+(T17-'Reference Rates'!$D$53)*'Reference Rates'!$C$53,IF(T17<='Reference Rates'!$D$55,'Reference Rates'!$B$54+(T17-'Reference Rates'!$D$54)*'Reference Rates'!$C$54,'Reference Rates'!$B$55+(T17-'Reference Rates'!$D$55)*'Reference Rates'!$C$55))))) -> 0 | V17: =S17+U17 -> 1664.5703 | W17: =L17+M17+N17-V17 -> 19168.242 | X17: =O17*'Reference Rates'!$B$28 -> 1950 | Y17: =IF(O17<'Reference Rates'!$B$31,'Reference Rates'!$B$32,'Reference Rates'!$B$33) -> 30 | Z17: =MIN(MAX(L17,'Reference Rates'!$B$39),'Reference Rates'!$B$40)*'Reference Rates'!$B$38 -> 489.57031 | AA17: =MIN(L17,'Reference Rates'!$B$46)*'Reference Rates'!$B$45 -> 200 | AB17: =X17+Y17+Z17+AA17 -> 2669.5703 | AC17: =L17+M17+N17+AB17 -> 23502.383
... A25: ='Aug 2026'!A25 -> EMP-020 | B25: =IF('Aug 2026'!B25="","",'Aug 2026'!B25) | C25: ='Aug 2026'!C25 -> Warehouse | D25: ='Aug 2026'!D25 -> Inventory Clerk | E25: ='Aug 2026'!E25 -> Y | F25: ='Reference Rates'!$E$15 -> 94.375 | G25: 208 | H25: 6 | I25: 0 | J25: =F25*G25 -> 19630 | K25: =F25*1.25*H25 -> 707.8125 | L25: =J25+K25 -> 20337.812 | M25: ='Reference Rates'!$B$19*G25/8 -> 1300 | N25: =I25*IFERROR(INDEX('Reference Rates'!$B$21:$B$22,MATCH(C25,'Reference Rates'!$A$21:$A$22,0)),0) -> 0 | O25: =MIN('Reference Rates'!$B$30,MAX('Reference Rates'!$B$29,MROUND(L25,500))) -> 20500 | P25: =O25*'Reference Rates'!$B$27 -> 1025 | Q25: =MIN(MAX(L25,'Reference Rates'!$B$39),'Reference Rates'!$B$40)*'Reference Rates'!$B$37 -> 508.44531 | R25: =MIN(L25,'Reference Rates'!$B$46)*IF(L25>1500,'Reference Rates'!$B$43,'Reference Rates'!$B$44) -> 200 | S25: =P25+Q25+R25 -> 1733.4453 | T25: =IF(E25="Y",0,MAX(0,L25-S25)) -> 0 | U25: =IF(T25<='Reference Rates'!$D$51,0,IF(T25<='Reference Rates'!$D$52,'Reference Rates'!$B$51+(T25-'Reference Rates'!$D$51)*'Reference Rates'!$C$51,IF(T25<='Reference Rates'!$D$53,'Reference Rates'!$B$52+(T25-'Reference Rates'!$D$52)*'Reference Rates'!$C$52,IF(T25<='Reference Rates'!$D$54,'Reference Rates'!$B$53+(T25-'Reference Rates'!$D$53)*'Reference Rates'!$C$53,IF(T25<='Reference Rates'!$D$55,'Reference Rates'!$B$54+(T25-'Reference Rates'!$D$54)*'Reference Rates'!$C$54,'Reference Rates'!$B$55+(T25-'Reference Rates'!$D$55)*'Reference Rates'!$C$55))))) -> 0 | V25: =S25+U25 -> 1733.4453 | W25: =L25+M25+N25-V25 -> 19904.367 | X25: =O25*'Reference Rates'!$B$28 -> 2050 | Y25: =IF(O25<'Reference Rates'!$B$31,'Reference Rates'!$B$32,'Reference Rates'!$B$33) -> 30 | Z25: =MIN(MAX(L25,'Reference Rates'!$B$39),'Reference Rates'!$B$40)*'Reference Rates'!$B$38 -> 508.44531 | AA25: =MIN(L25,'Reference Rates'!$B$46)*'Reference Rates'!$B$45 -> 200 | AB25: =X25+Y25+Z25+AA25 -> 2788.4453 | AC25: =L25+M25+N25+AB25 -> 24426.258
A26: ='Aug 2026'!A26 -> EMP-021 | B26: =IF('Aug 2026'!B26="","",'Aug 2026'!B26) -> Joshua Cedric D. Cortez | C26: ='Aug 2026'!C26 -> Delivery – Luzon | D26: ='Aug 2026'!D26 -> Delivery Driver – Luzon Routes | E26: ='Aug 2026'!E26 -> N | F26: ='Aug 2026'!F26 -> 100 | G26: 208 | H26: 15 | I26: 10 | J26: =F26*G26 -> 20800 | K26: =F26*1.25*H26 -> 1875 | L26: =J26+K26 -> 22675 | M26: ='Reference Rates'!$B$19*G26/8 -> 1300 | N26: =I26*IFERROR(INDEX('Reference Rates'!$B$21:$B$22,MATCH(C26,'Reference Rates'!$A$21:$A$22,0)),0) -> 5000 | O26: =MIN('Reference Rates'!$B$30,MAX('Reference Rates'!$B$29,MROUND(L26,500))) -> 22500 | P26: =O26*'Reference Rates'!$B$27 -> 1125 | Q26: =MIN(MAX(L26,'Reference Rates'!$B$39),'Reference Rates'!$B$40)*'Reference Rates'!$B$37 -> 566.875 | R26: =MIN(L26,'Reference Rates'!$B$46)*IF(L26>1500,'Reference Rates'!$B$43,'Reference Rates'!$B$44) -> 200 | S26: =P26+Q26+R26 -> 1891.875 | T26: =IF(E26="Y",0,MAX(0,L26-S26)) -> 20783.125 | U26: =IF(T26<='Reference Rates'!$D$51,0,IF(T26<='Reference Rates'!$D$52,'Reference Rates'!$B$51+(T26-'Reference Rates'!$D$51)*'Reference Rates'!$C$51,IF(T26<='Reference Rates'!$D$53,'Reference Rates'!$B$52+(T26-'Reference Rates'!$D$52)*'Reference Rates'!$C$52,IF(T26<='Reference Rates'!$D$54,'Reference Rates'!$B$53+(T26-'Reference Rates'!$D$53)*'Reference Rates'!$C$53,IF(T26<='Reference Rates'!$D$55,'Reference Rates'!$B$54+(T26-'Reference Rates'!$D$54)*'Reference Rates'!$C$54,'Reference Rates'!$B$55+(T26-'Reference Rates'!$D$55)*'Reference Rates'!$C$55))))) -> 0 | V26: =S26+U26 -> 1891.875 | W26: =L26+M26+N26-V26 -> 27083.125 | X26: =O26*'Reference Rates'!$B$28 -> 2250 | Y26: =IF(O26<'Reference Rates'!$B$31,'Reference Rates'!$B$32,'Reference Rates'!$B$33) -> 30 | Z26: =MIN(MAX(L26,'Reference Rates'!$B$39),'Reference Rates'!$B$40)*'Reference Rates'!$B$38 -> 566.875 | AA26: =MIN(L26,'Reference Rates'!$B$46)*'Reference Rates'!$B$45 -> 200 | AB26: =X26+Y26+Z26+AA26 -> 3046.875 | AC26: =L26+M26+N26+AB26 -> 32021.875
A27: ='Aug 2026'!A27 -> EMP-022 | B27: =IF('Aug 2026'!B27="","",'Aug 2026'!B27) | C27: ='Aug 2026'!C27 -> Delivery – Luzon | D27: ='Aug 2026'!D27 -> Delivery Driver – Luzon Routes | E27: ='Aug 2026'!E27 -> N | F27: ='Aug 2026'!F27 -> 105 | G27: 208 | H27: 20 | I27: 9 | J27: =F27*G27 -> 21840 | K27: =F27*1.25*H27 -> 2625 | L27: =J27+K27 -> 24465 | M27: ='Reference Rates'!$B$19*G27/8 -> 1300 | N27: =I27*IFERROR(INDEX('Reference Rates'!$B$21:$B$22,MATCH(C27,'Reference Rates'!$A$21:$A$22,0)),0) -> 4500 | O27: =MIN('Reference Rates'!$B$30,MAX('Reference Rates'!$B$29,MROUND(L27,500))) -> 24500 | P27: =O27*'Reference Rates'!$B$27 -> 1225 | Q27: =MIN(MAX(L27,'Reference Rates'!$B$39),'Reference Rates'!$B$40)*'Reference Rates'!$B$37 -> 611.625 | R27: =MIN(L27,'Reference Rates'!$B$46)*IF(L27>1500,'Reference Rates'!$B$43,'Reference Rates'!$B$44) -> 200 | S27: =P27+Q27+R27 -> 2036.625 | T27: =IF(E27="Y",0,MAX(0,L27-S27)) -> 22428.375 | U27: =IF(T27<='Reference Rates'!$D$51,0,IF(T27<='Reference Rates'!$D$52,'Reference Rates'!$B$51+(T27-'Reference Rates'!$D$51)*'Reference Rates'!$C$51,IF(T27<='Reference Rates'!$D$53,'Reference Rates'!$B$52+(T27-'Reference Rates'!$D$52)*'Reference Rates'!$C$52,IF(T27<='Reference Rates'!$D$54,'Reference Rates'!$B$53+(T27-'Reference Rates'!$D$53)*'Reference Rates'!$C$53,IF(T27<='Reference Rates'!$D$55,'Reference Rates'!$B$54+(T27-'Reference Rates'!$D$54)*'Reference Rates'!$C$54,'Reference Rates'!$B$55+(T27-'Reference Rates'!$D$55)*'Reference Rates'!$C$55))))) -> 239.30625 | V27: =S27+U27 -> 2275.9313 | W27: =L27+M27+N27-V27 -> 27989.069 | X27: =O27*'Reference Rates'!$B$28 -> 2450 | Y27: =IF(O27<'Reference Rates'!$B$31,'Reference Rates'!$B$32,'Reference Rates'!$B$33) -> 30 | Z27: =MIN(MAX(L27,'Reference Rates'!$B$39),'Reference Rates'!$B$40)*'Reference Rates'!$B$38 -> 611.625 | AA27: =MIN(L27,'Reference Rates'!$B$46)*'Reference Rates'!$B$45 -> 200 | AB27: =X27+Y27+Z27+AA27 -> 3291.625 | AC27: =L27+M27+N27+AB27 -> 33556.625
A28: ='Aug 2026'!A28 -> EMP-023 | B28: =IF('Aug 2026'!B28="","",'Aug 2026'!B28) | C28: ='Aug 2026'!C28 -> Delivery – Luzon | D28: ='Aug 2026'!D28 -> Delivery Driver – Luzon Routes | E28: ='Aug 2026'!E28 -> N | F28: ='Aug 2026'!F28 -> 100 | G28: 208 | H28: 18 | I28: 10 | J28: =F28*G28 -> 20800 | K28: =F28*1.25*H28 -> 2250 | L28: =J28+K28 -> 23050 | M28: ='Reference Rates'!$B$19*G28/8 -> 1300 | N28: =I28*IFERROR(INDEX('Reference Rates'!$B$21:$B$22,MATCH(C28,'Reference Rates'!$A$21:$A$22,0)),0) -> 5000 | O28: =MIN('Reference Rates'!$B$30,MAX('Reference Rates'!$B$29,MROUND(L28,500))) -> 23000 | P28: =O28*'Reference Rates'!$B$27 -> 1150 | Q28: =MIN(MAX(L28,'Reference Rates'!$B$39),'Reference Rates'!$B$40)*'Reference Rates'!$B$37 -> 576.25 | R28: =MIN(L28,'Reference Rates'!$B$46)*IF(L28>1500,'Reference Rates'!$B$43,'Reference Rates'!$B$44) -> 200 | S28: =P28+Q28+R28 -> 1926.25 | T28: =IF(E28="Y",0,MAX(0,L28-S28)) -> 21123.75 | U28: =IF(T28<='Reference Rates'!$D$51,0,IF(T28<='Reference Rates'!$D$52,'Reference Rates'!$B$51+(T28-'Reference Rates'!$D$51)*'Reference Rates'!$C$51,IF(T28<='Reference Rates'!$D$53,'Reference Rates'!$B$52+(T28-'Reference Rates'!$D$52)*'Reference Rates'!$C$52,IF(T28<='Reference Rates'!$D$54,'Reference Rates'!$B$53+(T28-'Reference Rates'!$D$53)*'Reference Rates'!$C$53,IF(T28<='Reference Rates'!$D$55,'Reference Rates'!$B$54+(T28-'Reference Rates'!$D$54)*'Reference Rates'!$C$54,'Reference Rates'!$B$55+(T28-'Reference Rates'!$D$55)*'Reference Rates'!$C$55))))) -> 43.6125 | V28: =S28+U28 -> 1969.8625 | W28: =L28+M28+N28-V28 -> 27380.138 | X28: =O28*'Reference Rates'!$B$28 -> 2300 | Y28: =IF(O28<'Reference Rates'!$B$31,'Reference Rates'!$B$32,'Reference Rates'!$B$33) -> 30 | Z28: =MIN(MAX(L28,'Reference Rates'!$B$39),'Reference Rates'!$B$40)*'Reference Rates'!$B$38 -> 576.25 | AA28: =MIN(L28,'Reference Rates'!$B$46)*'Reference Rates'!$B$45 -> 200 | AB28: =X28+Y28+Z28+AA28 -> 3106.25 | AC28: =L28+M28+N28+AB28 -> 32456.25
A29: ='Aug 2026'!A29 -> EMP-024 | B29: =IF('Aug 2026'!B29="","",'Aug 2026'!B29) -> Tristan Judd Mari Magsino | C29: ='Aug 2026'!C29 -> Delivery – Samar | D29: ='Aug 2026'!D29 -> Delivery Driver – Samar Routes | E29: ='Aug 2026'!E29 -> N | F29: ='Aug 2026'!F29 -> 110 | G29: 208 | H29: 29 | I29: 13 | J29: =F29*G29 -> 22880 | K29: =F29*1.25*H29 -> 3987.5 | L29: =J29+K29 -> 26867.5 | M29: ='Reference Rates'!$B$19*G29/8 -> 1300 | N29: =I29*IFERROR(INDEX('Reference Rates'!$B$21:$B$22,MATCH(C29,'Reference Rates'!$A$21:$A$22,0)),0) -> 11700 | O29: =MIN('Reference Rates'!$B$30,MAX('Reference Rates'!$B$29,MROUND(L29,500))) -> 27000 | P29: =O29*'Reference Rates'!$B$27 -> 1350 | Q29: =MIN(MAX(L29,'Reference Rates'!$B$39),'Reference Rates'!$B$40)*'Reference Rates'!$B$37 -> 671.6875 | R29: =MIN(L29,'Reference Rates'!$B$46)*IF(L29>1500,'Reference Rates'!$B$43,'Reference Rates'!$B$44) -> 200 | S29: =P29+Q29+R29 -> 2221.6875 | T29: =IF(E29="Y",0,MAX(0,L29-S29)) -> 24645.812 | U29: =IF(T29<='Reference Rates'!$D$51,0,IF(T29<='Reference Rates'!$D$52,'Reference Rates'!$B$51+(T29-'Reference Rates'!$D$51)*'Reference Rates'!$C$51,IF(T29<='Reference Rates'!$D$53,'Reference Rates'!$B$52+(T29-'Reference Rates'!$D$52)*'Reference Rates'!$C$52,IF(T29<='Reference Rates'!$D$54,'Reference Rates'!$B$53+(T29-'Reference Rates'!$D$53)*'Reference Rates'!$C$53,IF(T29<='Reference Rates'!$D$55,'Reference Rates'!$B$54+(T29-'Reference Rates'!$D$54)*'Reference Rates'!$C$54,'Reference Rates'!$B$55+(T29-'Reference Rates'!$D$55)*'Reference Rates'!$C$55))))) -> 571.92188 | V29: =S29+U29 -> 2793.6094 | W29: =L29+M29+N29-V29 -> 37073.891 | X29: =O29*'Reference Rates'!$B$28 -> 2700 | Y29: =IF(O29<'Reference Rates'!$B$31,'Reference Rates'!$B$32,'Reference Rates'!$B$33) -> 30 | Z29: =MIN(MAX(L29,'Reference Rates'!$B$39),'Reference Rates'!$B$40)*'Reference Rates'!$B$38 -> 671.6875 | AA29: =MIN(L29,'Reference Rates'!$B$46)*'Reference Rates'!$B$45 -> 200 | AB29: =X29+Y29+Z29+AA29 -> 3601.6875 | AC29: =L29+M29+N29+AB29 -> 43469.188
A30: ='Aug 2026'!A30 -> EMP-025 | B30: =IF('Aug 2026'!B30="","",'Aug 2026'!B30) | C30: ='Aug 2026'!C30 -> Delivery – Samar | D30: ='Aug 2026'!D30 -> Delivery Driver – Samar Routes | E30: ='Aug 2026'!E30 -> N | F30: ='Aug 2026'!F30 -> 115 | G30: 208 | H30: 29 | I30: 12 | J30: =F30*G30 -> 23920 | K30: =F30*1.25*H30 -> 4168.75 | L30: =J30+K30 -> 28088.75 | M30: ='Reference Rates'!$B$19*G30/8 -> 1300 | N30: =I30*IFERROR(INDEX('Reference Rates'!$B$21:$B$22,MATCH(C30,'Reference Rates'!$A$21:$A$22,0)),0) -> 10800 | O30: =MIN('Reference Rates'!$B$30,MAX('Reference Rates'!$B$29,MROUND(L30,500))) -> 28000 | P30: =O30*'Reference Rates'!$B$27 -> 1400 | Q30: =MIN(MAX(L30,'Reference Rates'!$B$39),'Reference Rates'!$B$40)*'Reference Rates'!$B$37 -> 702.21875 | R30: =MIN(L30,'Reference Rates'!$B$46)*IF(L30>1500,'Reference Rates'!$B$43,'Reference Rates'!$B$44) -> 200 | S30: =P30+Q30+R30 -> 2302.2188 | T30: =IF(E30="Y",0,MAX(0,L30-S30)) -> 25786.531 | U30: =IF(T30<='Reference Rates'!$D$51,0,IF(T30<='Reference Rates'!$D$52,'Reference Rates'!$B$51+(T30-'Reference Rates'!$D$51)*'Reference Rates'!$C$51,IF(T30<='Reference Rates'!$D$53,'Reference Rates'!$B$52+(T30-'Reference Rates'!$D$52)*'Reference Rates'!$C$52,IF(T30<='Reference Rates'!$D$54,'Reference Rates'!$B$53+(T30-'Reference Rates'!$D$53)*'Reference Rates'!$C$53,IF(T30<='Reference Rates'!$D$55,'Reference Rates'!$B$54+(T30-'Reference Rates'!$D$54)*'Reference Rates'!$C$54,'Reference Rates'!$B$55+(T30-'Reference Rates'!$D$55)*'Reference Rates'!$C$55))))) -> 743.02969 | V30: =S30+U30 -> 3045.2484 | W30: =L30+M30+N30-V30 -> 37143.502 | X30: =O30*'Reference Rates'!$B$28 -> 2800 | Y30: =IF(O30<'Reference Rates'!$B$31,'Reference Rates'!$B$32,'Reference Rates'!$B$33) -> 30 | Z30: =MIN(MAX(L30,'Reference Rates'!$B$39),'Reference Rates'!$B$40)*'Reference Rates'!$B$38 -> 702.21875 | AA30: =MIN(L30,'Reference Rates'!$B$46)*'Reference Rates'!$B$45 -> 200 | AB30: =X30+Y30+Z30+AA30 -> 3732.2188 | AC30: =L30+M30+N30+AB30 -> 43920.969
A31: ='Aug 2026'!A31 -> EMP-026 | B31: =IF('Aug 2026'!B31="","",'Aug 2026'!B31) | C31: ='Aug 2026'!C31 -> Delivery – Samar | D31: ='Aug 2026'!D31 -> Delivery Driver – Samar Routes | E31: ='Aug 2026'!E31 -> N | F31: ='Aug 2026'!F31 -> 110 | G31: 208 | H31: 28 | I31: 11 | J31: =F31*G31 -> 22880 | K31: =F31*1.25*H31 -> 3850 | L31: =J31+K31 -> 26730 | M31: ='Reference Rates'!$B$19*G31/8 -> 1300 | N31: =I31*IFERROR(INDEX('Reference Rates'!$B$21:$B$22,MATCH(C31,'Reference Rates'!$A$21:$A$22,0)),0) -> 9900 | O31: =MIN('Reference Rates'!$B$30,MAX('Reference Rates'!$B$29,MROUND(L31,500))) -> 26500 | P31: =O31*'Reference Rates'!$B$27 -> 1325 | Q31: =MIN(MAX(L31,'Reference Rates'!$B$39),'Reference Rates'!$B$40)*'Reference Rates'!$B$37 -> 668.25 | R31: =MIN(L31,'Reference Rates'!$B$46)*IF(L31>1500,'Reference Rates'!$B$43,'Reference Rates'!$B$44) -> 200 | S31: =P31+Q31+R31 -> 2193.25 | T31: =IF(E31="Y",0,MAX(0,L31-S31)) -> 24536.75 | U31: =IF(T31<='Reference Rates'!$D$51,0,IF(T31<='Reference Rates'!$D$52,'Reference Rates'!$B$51+(T31-'Reference Rates'!$D$51)*'Reference Rates'!$C$51,IF(T31<='Reference Rates'!$D$53,'Reference Rates'!$B$52+(T31-'Reference Rates'!$D$52)*'Reference Rates'!$C$52,IF(T31<='Reference Rates'!$D$54,'Reference Rates'!$B$53+(T31-'Reference Rates'!$D$53)*'Reference Rates'!$C$53,IF(T31<='Reference Rates'!$D$55,'Reference Rates'!$B$54+(T31-'Reference Rates'!$D$54)*'Reference Rates'!$C$54,'Reference Rates'!$B$55+(T31-'Reference Rates'!$D$55)*'Reference Rates'!$C$55))))) -> 555.5625 | V31: =S31+U31 -> 2748.8125 | W31: =L31+M31+N31-V31 -> 35181.188 | X31: =O31*'Reference Rates'!$B$28 -> 2650 | Y31: =IF(O31<'Reference Rates'!$B$31,'Reference Rates'!$B$32,'Reference Rates'!$B$33) -> 30 | Z31: =MIN(MAX(L31,'Reference Rates'!$B$39),'Reference Rates'!$B$40)*'Reference Rates'!$B$38 -> 668.25 | AA31: =MIN(L31,'Reference Rates'!$B$46)*'Reference Rates'!$B$45 -> 200 | AB31: =X31+Y31+Z31+AA31 -> 3548.25 | AC31: =L31+M31+N31+AB31 -> 41478.25
A32: ='Aug 2026'!A32 -> EMP-027 | B32: =IF('Aug 2026'!B32="","",'Aug 2026'!B32) | C32: ='Aug 2026'!C32 -> Admin / Supervisory | D32: ='Aug 2026'!D32 -> Store Supervisor | E32: ='Aug 2026'!E32 -> N | F32: ='Aug 2026'!F32 -> 120 | G32: 208 | H32: 0 | I32: 0 | J32: =F32*G32 -> 24960 | K32: =F32*1.25*H32 -> 0 | L32: =J32+K32 -> 24960 | M32: ='Reference Rates'!$B$19*G32/8 -> 1300 | N32: =I32*IFERROR(INDEX('Reference Rates'!$B$21:$B$22,MATCH(C32,'Reference Rates'!$A$21:$A$22,0)),0) -> 0 | O32: =MIN('Reference Rates'!$B$30,MAX('Reference Rates'!$B$29,MROUND(L32,500))) -> 25000 | P32: =O32*'Reference Rates'!$B$27 -> 1250 | Q32: =MIN(MAX(L32,'Reference Rates'!$B$39),'Reference Rates'!$B$40)*'Reference Rates'!$B$37 -> 624 | R32: =MIN(L32,'Reference Rates'!$B$46)*IF(L32>1500,'Reference Rates'!$B$43,'Reference Rates'!$B$44) -> 200 | S32: =P32+Q32+R32 -> 2074 | T32: =IF(E32="Y",0,MAX(0,L32-S32)) -> 22886 | U32: =IF(T32<='Reference Rates'!$D$51,0,IF(T32<='Reference Rates'!$D$52,'Reference Rates'!$B$51+(T32-'Reference Rates'!$D$51)*'Reference Rates'!$C$51,IF(T32<='Reference Rates'!$D$53,'Reference Rates'!$B$52+(T32-'Reference Rates'!$D$52)*'Reference Rates'!$C$52,IF(T32<='Reference Rates'!$D$54,'Reference Rates'!$B$53+(T32-'Reference Rates'!$D$53)*'Reference Rates'!$C$53,IF(T32<='Reference Rates'!$D$55,'Reference Rates'!$B$54+(T32-'Reference Rates'!$D$54)*'Reference Rates'!$C$54,'Reference Rates'!$B$55+(T32-'Reference Rates'!$D$55)*'Reference Rates'!$C$55))))) -> 307.95 | V32: =S32+U32 -> 2381.95 | W32: =L32+M32+N32-V32 -> 23878.05 | X32: =O32*'Reference Rates'!$B$28 -> 2500 | Y32: =IF(O32<'Reference Rates'!$B$31,'Reference Rates'!$B$32,'Reference Rates'!$B$33) -> 30 | Z32: =MIN(MAX(L32,'Reference Rates'!$B$39),'Reference Rates'!$B$40)*'Reference Rates'!$B$38 -> 624 | AA32: =MIN(L32,'Reference Rates'!$B$46)*'Reference Rates'!$B$45 -> 200 | AB32: =X32+Y32+Z32+AA32 -> 3354 | AC32: =L32+M32+N32+AB32 -> 29614
A33: ='Aug 2026'!A33 -> EMP-028 | B33: =IF('Aug 2026'!B33="","",'Aug 2026'!B33) | C33: ='Aug 2026'!C33 -> Admin / Supervisory | D33: ='Aug 2026'!D33 -> Warehouse & Logistics Supervisor | E33: ='Aug 2026'!E33 -> N | F33: ='Aug 2026'!F33 -> 130 | G33: 208 | H33: 0 | I33: 0 | J33: =F33*G33 -> 27040 | K33: =F33*1.25*H33 -> 0 | L33: =J33+K33 -> 27040 | M33: ='Reference Rates'!$B$19*G33/8 -> 1300 | N33: =I33*IFERROR(INDEX('Reference Rates'!$B$21:$B$22,MATCH(C33,'Reference Rates'!$A$21:$A$22,0)),0) -> 0 | O33: =MIN('Reference Rates'!$B$30,MAX('Reference Rates'!$B$29,MROUND(L33,500))) -> 27000 | P33: =O33*'Reference Rates'!$B$27 -> 1350 | Q33: =MIN(MAX(L33,'Reference Rates'!$B$39),'Reference Rates'!$B$40)*'Reference Rates'!$B$37 -> 676 | R33: =MIN(L33,'Reference Rates'!$B$46)*IF(L33>1500,'Reference Rates'!$B$43,'Reference Rates'!$B$44) -> 200 | S33: =P33+Q33+R33 -> 2226 | T33: =IF(E33="Y",0,MAX(0,L33-S33)) -> 24814 | U33: =IF(T33<='Reference Rates'!$D$51,0,IF(T33<='Reference Rates'!$D$52,'Reference Rates'!$B$51+(T33-'Reference Rates'!$D$51)*'Reference Rates'!$C$51,IF(T33<='Reference Rates'!$D$53,'Reference Rates'!$B$52+(T33-'Reference Rates'!$D$52)*'Reference Rates'!$C$52,IF(T33<='Reference Rates'!$D$54,'Reference Rates'!$B$53+(T33-'Reference Rates'!$D$53)*'Reference Rates'!$C$53,IF(T33<='Reference Rates'!$D$55,'Reference Rates'!$B$54+(T33-'Reference Rates'!$D$54)*'Reference Rates'!$C$54,'Reference Rates'!$B$55+(T33-'Reference Rates'!$D$55)*'Reference Rates'!$C$55))))) -> 597.15 | V33: =S33+U33 -> 2823.15 | W33: =L33+M33+N33-V33 -> 25516.85 | X33: =O33*'Reference Rates'!$B$28 -> 2700 | Y33: =IF(O33<'Reference Rates'!$B$31,'Reference Rates'!$B$32,'Reference Rates'!$B$33) -> 30 | Z33: =MIN(MAX(L33,'Reference Rates'!$B$39),'Reference Rates'!$B$40)*'Reference Rates'!$B$38 -> 676 | AA33: =MIN(L33,'Reference Rates'!$B$46)*'Reference Rates'!$B$45 -> 200 | AB33: =X33+Y33+Z33+AA33 -> 3606 | AC33: =L33+M33+N33+AB33 -> 31946
A34: ='Aug 2026'!A34 -> EMP-029 | B34: =IF('Aug 2026'!B34="","",'Aug 2026'!B34) | C34: ='Aug 2026'!C34 -> Admin / Supervisory | D34: ='Aug 2026'!D34 -> Admin & Payroll Officer | E34: ='Aug 2026'!E34 -> N | F34: ='Aug 2026'!F34 -> 140 | G34: 208 | H34: 0 | I34: 0 | J34: =F34*G34 -> 29120 | K34: =F34*1.25*H34 -> 0 | L34: =J34+K34 -> 29120 | M34: ='Reference Rates'!$B$19*G34/8 -> 1300 | N34: =I34*IFERROR(INDEX('Reference Rates'!$B$21:$B$22,MATCH(C34,'Reference Rates'!$A$21:$A$22,0)),0) -> 0 | O34: =MIN('Reference Rates'!$B$30,MAX('Reference Rates'!$B$29,MROUND(L34,500))) -> 29000 | P34: =O34*'Reference Rates'!$B$27 -> 1450 | Q34: =MIN(MAX(L34,'Reference Rates'!$B$39),'Reference Rates'!$B$40)*'Reference Rates'!$B$37 -> 728 | R34: =MIN(L34,'Reference Rates'!$B$46)*IF(L34>1500,'Reference Rates'!$B$43,'Reference Rates'!$B$44) -> 200 | S34: =P34+Q34+R34 -> 2378 | T34: =IF(E34="Y",0,MAX(0,L34-S34)) -> 26742 | U34: =IF(T34<='Reference Rates'!$D$51,0,IF(T34<='Reference Rates'!$D$52,'Reference Rates'!$B$51+(T34-'Reference Rates'!$D$51)*'Reference Rates'!$C$51,IF(T34<='Reference Rates'!$D$53,'Reference Rates'!$B$52+(T34-'Reference Rates'!$D$52)*'Reference Rates'!$C$52,IF(T34<='Reference Rates'!$D$54,'Reference Rates'!$B$53+(T34-'Reference Rates'!$D$53)*'Reference Rates'!$C$53,IF(T34<='Reference Rates'!$D$55,'Reference Rates'!$B$54+(T34-'Reference Rates'!$D$54)*'Reference Rates'!$C$54,'Reference Rates'!$B$55+(T34-'Reference Rates'!$D$55)*'Reference Rates'!$C$55))))) -> 886.35 | V34: =S34+U34 -> 3264.35 | W34: =L34+M34+N34-V34 -> 27155.65 | X34: =O34*'Reference Rates'!$B$28 -> 2900 | Y34: =IF(O34<'Reference Rates'!$B$31,'Reference Rates'!$B$32,'Reference Rates'!$B$33) -> 30 | Z34: =MIN(MAX(L34,'Reference Rates'!$B$39),'Reference Rates'!$B$40)*'Reference Rates'!$B$38 -> 728 | AA34: =MIN(L34,'Reference Rates'!$B$46)*'Reference Rates'!$B$45 -> 200 | AB34: =X34+Y34+Z34+AA34 -> 3858 | AC34: =L34+M34+N34+AB34 -> 34278
A35: ='Aug 2026'!A35 -> EMP-030 | B35: =IF('Aug 2026'!B35="","",'Aug 2026'!B35) -> Johnbel A. Maliñana | C35: ='Aug 2026'!C35 -> Admin / Supervisory | D35: ='Aug 2026'!D35 -> Operations Manager | E35: ='Aug 2026'!E35 -> N | F35: ='Aug 2026'!F35 -> 160 | G35: 208 | H35: 0 | I35: 0 | J35: =F35*G35 -> 33280 | K35: =F35*1.25*H35 -> 0 | L35: =J35+K35 -> 33280 | M35: ='Reference Rates'!$B$19*G35/8 -> 1300 | N35: =I35*IFERROR(INDEX('Reference Rates'!$B$21:$B$22,MATCH(C35,'Reference Rates'!$A$21:$A$22,0)),0) -> 0 | O35: =MIN('Reference Rates'!$B$30,MAX('Reference Rates'!$B$29,MROUND(L35,500))) -> 33500 | P35: =O35*'Reference Rates'!$B$27 -> 1675 | Q35: =MIN(MAX(L35,'Reference Rates'!$B$39),'Reference Rates'!$B$40)*'Reference Rates'!$B$37 -> 832 | R35: =MIN(L35,'Reference Rates'!$B$46)*IF(L35>1500,'Reference Rates'!$B$43,'Reference Rates'!$B$44) -> 200 | S35: =P35+Q35+R35 -> 2707 | T35: =IF(E35="Y",0,MAX(0,L35-S35)) -> 30573 | U35: =IF(T35<='Reference Rates'!$D$51,0,IF(T35<='Reference Rates'!$D$52,'Reference Rates'!$B$51+(T35-'Reference Rates'!$D$51)*'Reference Rates'!$C$51,IF(T35<='Reference Rates'!$D$53,'Reference Rates'!$B$52+(T35-'Reference Rates'!$D$52)*'Reference Rates'!$C$52,IF(T35<='Reference Rates'!$D$54,'Reference Rates'!$B$53+(T35-'Reference Rates'!$D$53)*'Reference Rates'!$C$53,IF(T35<='Reference Rates'!$D$55,'Reference Rates'!$B$54+(T35-'Reference Rates'!$D$54)*'Reference Rates'!$C$54,'Reference Rates'!$B$55+(T35-'Reference Rates'!$D$55)*'Reference Rates'!$C$55))))) -> 1461 | V35: =S35+U35 -> 4168 | W35: =L35+M35+N35-V35 -> 30412 | X35: =O35*'Reference Rates'!$B$28 -> 3350 | Y35: =IF(O35<'Reference Rates'!$B$31,'Reference Rates'!$B$32,'Reference Rates'!$B$33) -> 30 | Z35: =MIN(MAX(L35,'Reference Rates'!$B$39),'Reference Rates'!$B$40)*'Reference Rates'!$B$38 -> 832 | AA35: =MIN(L35,'Reference Rates'!$B$46)*'Reference Rates'!$B$45 -> 200 | AB35: =X35+Y35+Z35+AA35 -> 4412 | AC35: =L35+M35+N35+AB35 -> 38992
A36: TOTAL | G36: =SUM(G6:G35) -> 6208 | H36: =SUM(H6:H35) -> 258 | I36: =SUM(I6:I35) -> 65 | J36: =SUM(J6:J35) -> 637100 | K36: =SUM(K6:K35) -> 32794.531 | L36: =SUM(L6:L35) -> 669894.53 | M36: =SUM(M6:M35) -> 38800 | N36: =SUM(N6:N35) -> 46900 | P36: =SUM(P6:P35) -> 33500 | Q36: =SUM(Q6:Q35) -> 16747.363 | R36: =SUM(R6:R35) -> 6000 | S36: =SUM(S6:S35) -> 56247.363 | T36: =SUM(T6:T35) -> 244319.34 | U36: =SUM(U6:U35) -> 5405.8828 | V36: =SUM(V6:V35) -> 61653.246 | W36: =SUM(W6:W35) -> 693941.29 | ... AC36: =SUM(AC6:AC35) -> 846241.89
A38: Legend: | B38: Blue = input (edit) | C38: Black = formula | D38: Green text = linked from another sheet | G38: Green row = delivery driver

Sheet 3-Month Summary
A1: 3-Month Payroll Summary — August to October 2026
A2: Net Pay and Total Cost to Company are pulled from each monthly sheet — nothing is re-entered here. The department table below sums the employee table.
A4: Employee ID | B4: Employee Name | C4: Department | D4: Aug Net Pay | E4: Sep Net Pay | F4: Oct Net Pay | G4: 3-Mo Total Net Pay | H4: Aug Total Cost | I4: Sep Total Cost | J4: Oct Total Cost | K4: 3-Mo Total Cost to Company
A5: ='Aug 2026'!A6 -> EMP-001 | B5: =IF('Aug 2026'!B6="","",'Aug 2026'!B6) -> Mikhail Dustin Elpedes | C5: ='Aug 2026'!C6 -> Store | D5: ='Aug 2026'!W6 -> 17115.625 | E5: ='Sep 2026'!W6 -> 18261.555 | F5: ='Oct 2026'!W6 -> 19904.367 | G5: =SUM(D5:F5) -> 55281.547 | H5: ='Aug 2026'!AC6 -> 21039.375 | I5: ='Sep 2026'!AC6 -> 22394.07 | J5: ='Oct 2026'!AC6 -> 24426.258 | K5: =SUM(H5:J5) -> 67859.703
A6: ='Aug 2026'!A7 -> EMP-002 | B6: =IF('Aug 2026'!B7="","",'Aug 2026'!B7) | C6: ='Aug 2026'!C7 -> Store | D6: ='Aug 2026'!W7 -> 18428.523 | E6: ='Sep 2026'!W7 -> 18558.762 | F6: ='Oct 2026'!W7 -> 19584.309 | G6: =SUM(D6:F6) -> 56571.594 | H6: ='Aug 2026'!AC7 -> 22569.602 | I6: ='Sep 2026'!AC7 -> 22782.801 | J6: ='Oct 2026'!AC7 -> 24013.504 | K6: =SUM(H6:J6) -> 69365.906
A7: ='Aug 2026'!A8 -> EMP-003 | B7: =IF('Aug 2026'!B8="","",'Aug 2026'!B8) | C7: ='Aug 2026'!C8 -> Store | D7: ='Aug 2026'!W8 -> 17115.625 | E7: ='Sep 2026'!W8 -> 18046.75 | F7: ='Oct 2026'!W8 -> 19053.223 | G7: =SUM(D7:F7) -> 54215.598 | H7: ='Aug 2026'!AC8 -> 21039.375 | I7: ='Sep 2026'!AC8 -> 22168.25 | J7: ='Oct 2026'!AC8 -> 23381.465 | K7: =SUM(H7:J7) -> 66589.09
A8: ='Aug 2026'!A9 -> EMP-004 | B8: =IF('Aug 2026'!B9="","",'Aug 2026'!B9) | C8: ='Aug 2026'!C9 -> Store | D8: ='Aug 2026'!W9 -> 17818.25 | E8: ='Sep 2026'!W9 -> 18451.359 | F8: ='Oct 2026'!W9 -> 19904.367 | G8: =SUM(D8:F8) -> 56173.977 | H8: ='Aug 2026'!AC9 -> 21851.75 | I8: ='Sep 2026'!AC9 -> 22669.891 | J8: ='Oct 2026'!AC9 -> 24426.258 | K8: =SUM(H8:J8) -> 68947.898
A9: ='Aug 2026'!A10 -> EMP-005 | B9: =IF('Aug 2026'!B10="","",'Aug 2026'!B10) | C9: ='Aug 2026'!C10 -> Store | D9: ='Aug 2026'!W10 -> 18005.008 | E9: ='Sep 2026'!W10 -> 18046.75 | F9: ='Oct 2026'!W10 -> 20019.387 | G9: =SUM(D9:F9) -> 56071.145 | H9: ='Aug 2026'!AC10 -> 22124.367 | I9: ='Sep 2026'!AC10 -> 22168.25 | J9: ='Oct 2026'!AC10 -> 24547.176 | K9: =SUM(H9:J9) -> 68839.793
A10: ='Aug 2026'!A11 -> EMP-006 | B10: =IF('Aug 2026'!B11="","",'Aug 2026'!B11) | C10: ='Aug 2026'!C11 -> Store | D10: ='Aug 2026'!W11 -> 17818.25 | E10: ='Sep 2026'!W11 -> 18046.75 | F10: ='Oct 2026'!W11 -> 19264.25 | G10: =SUM(D10:F10) -> 55129.25 | H10: ='Aug 2026'!AC11 -> 21851.75 | I10: ='Sep 2026'!AC11 -> 22168.25 | J10: ='Oct 2026'!AC11 -> 23600.75 | K10: =SUM(H10:J10) -> 67620.75
A11: ='Aug 2026'!A12 -> EMP-007 | B11: =IF('Aug 2026'!B12="","",'Aug 2026'!B12) | C11: ='Aug 2026'!C12 -> Store | D11: ='Aug 2026'!W12 -> 18615.281 | E11: ='Sep 2026'!W12 -> 17359.375 | F11: ='Oct 2026'!W12 -> 19814.348 | G11: =SUM(D11:F11) -> 55789.004 | H11: ='Aug 2026'!AC12 -> 22842.219 | I11: ='Sep 2026'!AC12 -> 21295.625 | J11: ='Oct 2026'!AC12 -> 24255.34 | K11: =SUM(H11:J11) -> 68393.184
A12: ='Aug 2026'!A13 -> EMP-008 | B12: =IF('Aug 2026'!B13="","",'Aug 2026'!B13) | C12: ='Aug 2026'!C13 -> Store | D12: ='Aug 2026'!W13 -> 17818.25 | E12: ='Sep 2026'!W13 -> 18558.762 | F12: ='Oct 2026'!W13 -> 19904.367 | G12: =SUM(D12:F12) -> 56281.379 | H12: ='Aug 2026'!AC13 -> 21851.75 | I12: ='Sep 2026'!AC13 -> 22782.801 | J12: ='Oct 2026'!AC13 -> 24426.258 | K12: =SUM(H12:J12) -> 69060.809
A13: ='Aug 2026'!A14 -> EMP-009 | B13: =IF('Aug 2026'!B14="","",'Aug 2026'!B14) | C13: ='Aug 2026'!C14 -> Store | D13: ='Aug 2026'!W14 -> 17818.25 | E13: ='Sep 2026'!W14 -> 18061.191 | F13: ='Oct 2026'!W14 -> 19053.223 | G13: =SUM(D13:F13) -> 54932.664 | H13: ='Aug 2026'!AC14 -> 21851.75 | I13: ='Sep 2026'!AC14 -> 22185.996 | J13: ='Oct 2026'!AC14 -> 23381.465 | K13: =SUM(H13:J13) -> 67419.211
A14: ='Aug 2026'!A15 -> EMP-010 | B14: =IF('Aug 2026'!B15="","",'Aug 2026'!B15) | C14: ='Aug 2026'!C15 -> Store | D14: ='Aug 2026'!W15 -> 17937.656 | E14: ='Sep 2026'!W15 -> 18558.762 | F14: ='Oct 2026'!W15 -> 19904.367 | G14: =SUM(D14:F14) -> 56400.785 | H14: ='Aug 2026'!AC15 -> 21979.844 | I14: ='Sep 2026'!AC15 -> 22782.801 | J14: ='Oct 2026'!AC15 -> 24426.258 | K14: =SUM(H14:J14) -> 69188.902
A15: ='Aug 2026'!A16 -> EMP-011 | B15: =IF('Aug 2026'!B16="","",'Aug 2026'!B16) | C15: ='Aug 2026'!C16 -> Store | D15: ='Aug 2026'!W16 -> 17818.25 | E15: ='Sep 2026'!W16 -> 18046.75 | F15: ='Oct 2026'!W16 -> 20134.406 | G15: =SUM(D15:F15) -> 55999.406 | H15: ='Aug 2026'!AC16 -> 21851.75 | I15: ='Sep 2026'!AC16 -> 22168.25 | J15: ='Oct 2026'!AC16 -> 24668.094 | K15: =SUM(H15:J15) -> 68688.094
A16: ='Aug 2026'!A17 -> EMP-012 | B16: =IF('Aug 2026'!B17="","",'Aug 2026'!B17) | C16: ='Aug 2026'!C17 -> Store | D16: ='Aug 2026'!W17 -> 17818.25 | E16: ='Sep 2026'!W17 -> 18046.75 | F16: ='Oct 2026'!W17 -> 19168.242 | G16: =SUM(D16:F16) -> 55033.242 | H16: ='Aug 2026'!AC17 -> 21851.75 | I16: ='Sep 2026'!AC17 -> 22168.25 | J16: ='Oct 2026'!AC17 -> 23502.383 | K16: =SUM(H16:J16) -> 67522.383
... A34: ='Aug 2026'!A35 -> EMP-030 | B34: =IF('Aug 2026'!B35="","",'Aug 2026'!B35) -> Johnbel A. Maliñana | C34: ='Aug 2026'!C35 -> Admin / Supervisory | D34: ='Aug 2026'!W35 -> 30412 | E34: ='Sep 2026'!W35 -> 30412 | F34: ='Oct 2026'!W35 -> 30412 | G34: =SUM(D34:F34) -> 91236 | H34: ='Aug 2026'!AC35 -> 38992 | I34: ='Sep 2026'!AC35 -> 38992 | J34: ='Oct 2026'!AC35 -> 38992 | K34: =SUM(H34:J34) -> 116976
A35: TOTAL | D35: =SUM(D5:D34) -> 644822.56 | E35: =SUM(E5:E34) -> 659486.1 | F35: =SUM(F5:F34) -> 693941.29 | G35: =SUM(G5:G34) -> 1998250 | H35: =SUM(H5:H34) -> 787570.6 | I35: =SUM(I5:I34) -> 804514.23 | J35: =SUM(J5:J34) -> 846241.89 | K35: =SUM(K5:K34) -> 2438326.7
A37: By Department (3-month totals)
A38: Department | C38: Headcount | D38: 3-Mo Net Pay | E38: 3-Mo Cost to Company | F38: % of Total Cost
A39: Store | C39: =COUNTIF($C$5:$C$34,A39) -> 12 | D39: =SUMIF($C$5:$C$34,A39,$G$5:$G$34) -> 667879.59 | E39: =SUMIF($C$5:$C$34,A39,$K$5:$K$34) -> 819495.72 | F39: =E39/$E$44 -> 0.33608938
A40: Warehouse | C40: =COUNTIF($C$5:$C$34,A40) -> 8 | D40: =SUMIF($C$5:$C$34,A40,$G$5:$G$34) -> 454140.5 | E40: =SUMIF($C$5:$C$34,A40,$K$5:$K$34) -> 557114.5 | F40: =E40/$E$44 -> 0.2284823
A41: Delivery – Luzon | C41: =COUNTIF($C$5:$C$34,A41) -> 3 | D41: =SUMIF($C$5:$C$34,A41,$G$5:$G$34) -> 240403.72 | E41: =SUMIF($C$5:$C$34,A41,$K$5:$K$34) -> 286091.44 | F41: =E41/$E$44 -> 0.11733105
A42: Delivery – Samar | C42: =COUNTIF($C$5:$C$34,A42) -> 3 | D42: =SUMIF($C$5:$C$34,A42,$G$5:$G$34) -> 314586.81 | E42: =SUMIF($C$5:$C$34,A42,$K$5:$K$34) -> 370623.81 | F42: =E42/$E$44 -> 0.15199924
A43: Admin / Supervisory | C43: =COUNTIF($C$5:$C$34,A43) -> 4 | D43: =SUMIF($C$5:$C$34,A43,$G$5:$G$34) -> 321239.34 | E43: =SUMIF($C$5:$C$34,A43,$K$5:$K$34) -> 405001.25 | F43: =E43/$E$44 -> 0.16609802
A44: TOTAL | C44: =SUM(C39:C43) -> 30 | D44: =SUM(D39:D43) -> 1998250 | E44: =SUM(E39:E43) -> 2438326.7 | F44: =SUM(F39:F43) -> 1
